Workbook
Name apple: 'Apple (iPad, Macbook)'!$A$4:$C$417
Name apple: 'Apple (безнал)'!$A$6:$C$117
Name apple: 'Apple(iPhone, Watch)'!$B$4:$D$263
Name apple: #REF!
Name audio: #REF!
Name audio: #REF!
Name audio: #REF!
Name audio: #REF!
Name audio: #REF!
Name lego: #REF!
Name аксессуары_безнал_безндс: #REF!
Name мониторы: #REF!
Name ноутбуки: #REF!
Name ноутбуки: 'Аксессуары и гаджеты в наличии'!$A$6:$E$23
Name ноутбуки: 'МБТ Xiaomi'!$A$6:$D$105
Name ноутбуки: Ноутбуки!$A$6:$F$164
Name ноутбуки: 'Ноутбуки (2)'!$A$6:$F$174
Name ноутбуки: 'Ноутбуки (3)'!$A$6:$F$416
Name ноутбуки: 'Ноутбуки (нал)'!$A$6:$C$172
Name ноутбуки: 'Предзаказ аксессуары'!$A$6:$D$101
Name ноутбуки: 'Предзаказ аксессуары и ТВ'!$A$6:$F$3067
Name ноутбуки: 'Предзаказ аксессуары(от 150)'!$A$6:$F$2314
Name ноутбуки: #REF!
Name ноутбуки: #REF!
Name ноутбуки: #REF!
Name пред_электрон_100к: #REF!
Name пред_электрон_100к: #REF!
Name пред_электрон_100к: #REF!
Name предзаказ_электрон_100к: #REF!
Name принтеры_и_мфу: #REF!
Name сетевое_оборудование: #REF!
Name смартфоны_безнал_безндс: #REF!
Name смартфоны_безнал_ндс: 'Смартфоны(безнал с НДС)'!$A$5:$C$10
Name телевизор_безнал: #REF!
Name телевизор_безнал: #REF!
Name телевизор_безнал: #REF!
Name телевизор_безнал: #REF!
Name телевизор_безнал: #REF!
Name телевизор_безнал: #REF!
Name телевизор_безнал: #REF!
Name телевизор_безнал: #REF!
Name телевизор_безнал: #REF!
Name телевизор_безнал: #REF!
Name телевизор_безнал: #REF!
Name телевизор_безнал: #REF!
Name телевизор_безнал: #REF!
Name телевизор_безнал: #REF!
Name телевизоры_безнал: #REF!
Name телевизоры_безнал_спецпр: 'Audio, приставки, умные колонки'!$B$5:$C$456
Name телевизоры_безнал_спецпр: Dyson!$B$5:$C$189
Name телевизоры_безнал_спецпр: Garmin!$B$5:$C$112
Name телевизоры_безнал_спецпр: 'Телевизоры (безнал) Спецпред-ие'!$B$5:$E$26
Name телевизоры_безнал_спецпр: 'Телевизоры в наличии'!$B$5:$E$7
Name телевизоры_наличные: #REF!
Name телевизоры_наличные: #REF!
Name телевизоры_наличные: #REF!
Name телевизоры_наличные: #REF!
Name телевизоры_наличные: #REF!
Name умная_колонка: #REF!
Name умная_колонка: #REF!

Sheet Оглавление
A1: 8-(499)-350-76-73
A2: Товар в наличии | H2: итого | I2: =SUM(I4:I22) -> 0 | J2: =SUM(J4:J22) -> 0 | K2: =SUM(K4:K22) -> 0 | L2: =SUM(L4:L22) -> 0
A3: № | B3: Категория | C3: Склад | D3: Оплата | E3: НДС | I3: кол | J3: кол б/н | K3: сумма | L3: сумма Б/Н
A4: 1 | B4: Смартфоны и кнопочные телефоны | C4: Рубин | D4: Наличные, б/н | E4: 0.22 | I4: =Смартфоны!E4 -> 0 | J4: =Смартфоны!F4 -> 0 | K4: =Смартфоны!G4 -> 0 | L4: =Смартфоны!H4 -> 0
A5: 2 | B5: Смартфоны. Безнал | C5: Рубин | D5: б/н | E5: 0.22 | I5: ='Смартфоны(безнал с НДС)'!D3 -> 0 | K5: ='Смартфоны(безнал с НДС)'!E3 -> 0
A6: 2 | B6: Apple (iPhone, Watch, Airpods, СЗУ и провода) | C6: Рубин | D6: Наличные | E6: - | I6: ='Apple(iPhone, Watch)'!E2 -> 0 | K6: ='Apple(iPhone, Watch)'!F2 -> 0
A7: 6 | B7: Гаджеты и МБТ. Выгодно! | C7: Рубин | D7: Наличные | E7: -
A8: 3 | B8: Телевизоры Xiaomi. В наличии на складе | C8: Рябиновая | D8: б/н | E8: 0.22 | I8: ='Телевизоры в наличии'!F3 -> 0 | K8: ='Телевизоры в наличии'!G3 -> 0
A9: 4 | B9: Аксессуары и гаджеты в наличии | C9: Рябиновая | D9: Наличные, б/н | E9: 0.22 | I9: ='Аксессуары и гаджеты в наличии'!F4 -> 0 | J9: ='Аксессуары и гаджеты в наличии'!G4 -> 0 | K9: ='Аксессуары и гаджеты в наличии'!H4 -> 0 | L9: ='Аксессуары и гаджеты в наличии'!I4 -> 0
A10: 5 | B10: Уцененный товар | C10: Рубин | D10: Наличные | E10: - | I10: ='Уцененный товар'!E3 -> 0 | K10: ='Уцененный товар'!F3 -> 0
A11: Под заказ
A12: № | B12: Категория | C12: Склад | D12: Оплата | E12: НДС
A13: 6 | B13: Apple (iPad, MacBook, iMac, Apple Display, CUSTOM, Pencil, Keyboard) | C13: Рубин | D13: Наличные | E13: - | I13: ='Apple (iPad, Macbook)'!D2 -> 0 | K13: ='Apple (iPad, Macbook)'!E2 -> 0
A14: 7 | B14: Гаджеты и МБТ | C14: Рубин | D14: Наличные | E14: - | I14: ='Гаджеты и МБТ'!D2 -> 0 | K14: ='Гаджеты и МБТ'!E2 -> 0
A15: 8 | B15: Гаджеты и МБТ (от 150 тыс). | C15: Рябиновая | D15: Наличные, б/н | E15: 0.22 | I15: ='Предзаказ аксессуары'!E4 -> 0 | J15: ='Предзаказ аксессуары'!F4 -> 0 | K15: ='Предзаказ аксессуары'!G4 -> 0 | L15: ='Предзаказ аксессуары'!H4 -> 0
A16: 9 | B16: Гаджеты, МБТ, ТВ, оргтехника (от 200 тыс). | C16: Рябиновая | D16: Наличные, б/н | E16: 0.22 | I16: ='Предзаказ аксессуары и ТВ'!G4 -> 0 | J16: ='Предзаказ аксессуары и ТВ'!H4 -> 0 | K16: ='Предзаказ аксессуары и ТВ'!I4 -> 0 | L16: ='Предзаказ аксессуары и ТВ'!J4 -> 0
A17: 10 | B17: МБТ Xiaomi | C17: Рябиновая | D17: Наличные, б/н | E17: 0.22 | I17: ='МБТ Xiaomi'!E4 -> 0 | J17: ='МБТ Xiaomi'!F4 -> 0 | K17: ='МБТ Xiaomi'!G4 -> 0 | L17: ='МБТ Xiaomi'!H4 -> 0
A18: 11 | B18: Телевизоры Xiaomi | C18: Рябиновая | D18: б/н | E18: 0.22
A19: 12 | B19: Audio, приставки, колонки | C19: Рубин | D19: Наличные | E19: - | I19: ='Audio, приставки, умные колонки'!D3 -> 0 | K19: ='Audio, приставки, умные колонки'!E3 -> 0
A20: 13 | B20: Dyson. | C20: Рубин | D20: Наличные | E20: - | I20: =Dyson!D3 -> 0 | K20: =Dyson!E3 -> 0
A21: 14 | B21: GARMIN | C21: Рубин | D21: Наличные | E21: -
A22: 15 | B22: Apple. (безнал от 150 тыс.) | C22: Рубин | D22: б/н | E22: 0.22 | I22: ='Apple (безнал)'!D4 -> 0 | K22: ='Apple (безнал)'!E4 -> 0
A23: 16 | B23: Ноутбуки 1 | C23: Рубин | D23: Наличные, б/н | E23: 0.22 | I23: =Ноутбуки!G4 -> 0 | J23: =Ноутбуки!H4 -> 0 | K23: =Ноутбуки!I4 -> 0 | L23: =Ноутбуки!J4 -> 0
A24: 17 | B24: Ноутбуки 2 | C24: Рубин | D24: Наличные, б/н | E24: 0.22 | I24: ='Ноутбуки (2)'!G4 -> 0 | J24: ='Ноутбуки (2)'!H4 -> 0 | K24: ='Ноутбуки (2)'!I4 -> 0 | L24: ='Ноутбуки (2)'!J4 -> 0
A25: 18 | B25: Ноутбуки 3 | C25: Рубин | D25: Наличные, б/н | E25: 0.22 | I25: ='Ноутбуки (3)'!G4 -> 0 | J25: ='Ноутбуки (3)'!H4 -> 0 | K25: ='Ноутбуки (3)'!I4 -> 0 | L25: ='Ноутбуки (3)'!J4 -> 0
A26: 19 | B26: Ноутбуки (наличные) | C26: Рубин | D26: Наличные | E26: - | I26: ='Ноутбуки (нал)'!D4 -> 0 | K26: ='Ноутбуки (нал)'!E4 -> 0
A27: "ТрейдМи" — надёжный оптовый поставщик электроники с 10+ летним опытом. Более 10 лет мы поставляем оригинальную электронику, гаджеты и бытовую технику ведущих брендов: Xiaomi, Samsung, Apple, Honor, Huawei, Realme и многих других. Работаем по всей России, напрямую со склада в Москве. Наш приоритет — долгосрочные отношения, поэтому Вы можете быть уверены в оперативности, стабильности и прозрачных условиях работы. Хотите выгодные цены и гарантированное качество? Загрузите наш актуальный прайс:
A28: 👉 Прайс-лист ТрейдМи
A29: "ТрейдМи" – электроника с доверием! 🚀
A30: Cсылка на прайс
A31: Канал в Telegram
A32: Сайт
A33: Отзывы о нас
A34: Условия сотрудничества
A35: 1. Режим работы, адрес самовывоза.
A36: Прием заявок: пн-пт с 10 до 18 часов (МСК). Сб, вс - по согласованию с менеджером. Время работы склада: пн-пт с 10 до 19 часов, сб с 10 до 16 часов Самовывоз: г. Москва, ул.Барклая 8, БЦ "Рубин", проходная. Время самовывоза небходимо согласовать с менеджером ЗАРАНЕЕ! В противном случае возможны задержки при сборке Вашего заказа.
A37: 2. Минимальный заказ
A38: Минимальная сумма заказа: 50 000 руб. Минимальное количество позиций: от 3-х штук из категории электроника. Cкидки рассчитываются индивидуально и зависят от объема конкретного заказа
... A50: Если обнаружены внешние дефекты на смартфонах, планшетах, ноутбуках, мы в качестве компенсации предоставляем скидку, либо осуществляем возврат д/с или обмен товара на аналогичный, только если клиент предоставит видео распаковки товара. Если клиент не может предоставить видео распаковки товара, мы со своей стороны готовы погасить 50% расходов по замене бракованной детали. В течение 3 (трёх) рабочих дней с момента получения товара Покупатель может обратиться к Поставщику по вопросу комплектности и внешнего вида товара, независимо от способа его покупки (наличные д/с / б/н). Если в течение этого срока Покупатель не обратился к Поставщику с рекламацией, считается, что он принял товар надлежащего качества и комплектности. При отправке телевизоров транспортными компаниями настоятельно рекомендуем заказывать жесткую упаковку или обрешетку. В противном случае претензии по внешнему виду мы не принимаем!

Sheet Смартфоны
A1: Назад в оглавление
A2: Смартфоны наличные. Предоплата 100%
A3: Внимание! Товары Samsung могут иметь вскрытую упаковку из-за таможенного досмотра.
A4: Устройства новые, неактивированные, в полной комплектации. На работу это не влияет. Возврат и обмен невозможны — нарушение упаковки не является браком, т.к. произошло не по вине поставщика. | C4: итого | E4: =SUM(смарты_нал5[Заказ нал.]) -> 0 | F4: =SUM(смарты_нал5[Заказ Б.Н.]) -> 0 | G4: =SUM(смарты_нал5[Сумма заказа нал.]) -> 0 | H4: =SUM(смарты_нал5[Сумма заказа Б.Н.]) -> 0
A5: Код | B5: Наименование | C5: Цена | D5: Цена Б.Н. | E5: Заказ нал. | F5: Заказ Б.Н. | G5: Сумма заказа нал. | H5: Сумма заказа Б.Н. | I5: особенности заказа
A6: Электроника / Blackview | D6: =IF(смарты_нал5[[#This Row],[Цена ]]>0,смарты_нал5[[#This Row],[Цена ]]/0.87,"") | G6: =IF(смарты_нал5[[#This Row],[Цена ]]<>"",смарты_нал5[[#This Row],[Цена ]]*смарты_нал5[[#This Row],[Заказ нал.]],"") | H6: =IF(смарты_нал5[[#This Row],[Цена Б.Н.]]<>"",смарты_нал5[[#This Row],[Цена Б.Н.]]*смарты_нал5[[#This Row],[Заказ Б.Н.]],"")
A7: 17813-2 | B7: Blackview BL7000 5G 8+256GB NFC Orange RUS | C7: 18600 | D7: =IF(смарты_нал5[[#This Row],[Цена ]]>0,смарты_нал5[[#This Row],[Цена ]]/0.87,"") -> 21379.31 | G7: =IF(смарты_нал5[[#This Row],[Цена ]]<>"",смарты_нал5[[#This Row],[Цена ]]*смарты_нал5[[#This Row],[Заказ нал.]],"") -> 0 | H7: =IF(смарты_нал5[[#This Row],[Цена Б.Н.]]<>"",смарты_нал5[[#This Row],[Цена Б.Н.]]*смарты_нал5[[#This Row],[Заказ Б.Н.]],"") -> 0
A8: 17803-1 | B8: Blackview BV4800 Pro 4+128GB Black RUS | C8: 8800 | D8: =IF(смарты_нал5[[#This Row],[Цена ]]>0,смарты_нал5[[#This Row],[Цена ]]/0.87,"") -> 10114.943 | G8: =IF(смарты_нал5[[#This Row],[Цена ]]<>"",смарты_нал5[[#This Row],[Цена ]]*смарты_нал5[[#This Row],[Заказ нал.]],"") -> 0 | H8: =IF(смарты_нал5[[#This Row],[Цена Б.Н.]]<>"",смарты_нал5[[#This Row],[Цена Б.Н.]]*смарты_нал5[[#This Row],[Заказ Б.Н.]],"") -> 0
A9: 17803-2 | B9: Blackview BV4800 Pro 4+128GB Orange RUS | C9: 8800 | D9: =IF(смарты_нал5[[#This Row],[Цена ]]>0,смарты_нал5[[#This Row],[Цена ]]/0.87,"") -> 10114.943 | G9: =IF(смарты_нал5[[#This Row],[Цена ]]<>"",смарты_нал5[[#This Row],[Цена ]]*смарты_нал5[[#This Row],[Заказ нал.]],"") -> 0 | H9: =IF(смарты_нал5[[#This Row],[Цена Б.Н.]]<>"",смарты_нал5[[#This Row],[Цена Б.Н.]]*смарты_нал5[[#This Row],[Заказ Б.Н.]],"") -> 0
A10: 17816-1 | B10: Blackview Fort 1 6+256GB NFC Black RUS | C10: 13400 | D10: =IF(смарты_нал5[[#This Row],[Цена ]]>0,смарты_нал5[[#This Row],[Цена ]]/0.87,"") -> 15402.299 | G10: =IF(смарты_нал5[[#This Row],[Цена ]]<>"",смарты_нал5[[#This Row],[Цена ]]*смарты_нал5[[#This Row],[Заказ нал.]],"") -> 0 | H10: =IF(смарты_нал5[[#This Row],[Цена Б.Н.]]<>"",смарты_нал5[[#This Row],[Цена Б.Н.]]*смарты_нал5[[#This Row],[Заказ Б.Н.]],"") -> 0
A11: 17815-2 | B11: Blackview Rock 2 5G 8+256GB NFC Orange RUS | C11: 17100 | D11: =IF(смарты_нал5[[#This Row],[Цена ]]>0,смарты_нал5[[#This Row],[Цена ]]/0.87,"") -> 19655.172 | G11: =IF(смарты_нал5[[#This Row],[Цена ]]<>"",смарты_нал5[[#This Row],[Цена ]]*смарты_нал5[[#This Row],[Заказ нал.]],"") -> 0 | H11: =IF(смарты_нал5[[#This Row],[Цена Б.Н.]]<>"",смарты_нал5[[#This Row],[Цена Б.Н.]]*смарты_нал5[[#This Row],[Заказ Б.Н.]],"") -> 0
A12: Электроника / Blackview / Планшеты Blackview | D12: =IF(смарты_нал5[[#This Row],[Цена ]]>0,смарты_нал5[[#This Row],[Цена ]]/0.87,"") | G12: =IF(смарты_нал5[[#This Row],[Цена ]]<>"",смарты_нал5[[#This Row],[Цена ]]*смарты_нал5[[#This Row],[Заказ нал.]],"") | H12: =IF(смарты_нал5[[#This Row],[Цена Б.Н.]]<>"",смарты_нал5[[#This Row],[Цена Б.Н.]]*смарты_нал5[[#This Row],[Заказ Б.Н.]],"")
A13: 17912-1 | B13: Blackview Active 7 11" 8+128GB LTE Black RUS | C13: 15500 | D13: =IF(смарты_нал5[[#This Row],[Цена ]]>0,смарты_нал5[[#This Row],[Цена ]]/0.87,"") -> 17816.092 | G13: =IF(смарты_нал5[[#This Row],[Цена ]]<>"",смарты_нал5[[#This Row],[Цена ]]*смарты_нал5[[#This Row],[Заказ нал.]],"") -> 0 | H13: =IF(смарты_нал5[[#This Row],[Цена Б.Н.]]<>"",смарты_нал5[[#This Row],[Цена Б.Н.]]*смарты_нал5[[#This Row],[Заказ Б.Н.]],"") -> 0
A14: 17913-1 | B14: Blackview Active 8 Pro 10.36" 8+256GB LTE Black RUS | C14: 21600 | D14: =IF(смарты_нал5[[#This Row],[Цена ]]>0,смарты_нал5[[#This Row],[Цена ]]/0.87,"") -> 24827.586 | G14: =IF(смарты_нал5[[#This Row],[Цена ]]<>"",смарты_нал5[[#This Row],[Цена ]]*смарты_нал5[[#This Row],[Заказ нал.]],"") -> 0 | H14: =IF(смарты_нал5[[#This Row],[Цена Б.Н.]]<>"",смарты_нал5[[#This Row],[Цена Б.Н.]]*смарты_нал5[[#This Row],[Заказ Б.Н.]],"") -> 0
A15: 17905-1 | B15: Blackview MEGA 2 12" 12+256GB LTE Gray RUS | C15: 16900 | D15: =IF(смарты_нал5[[#This Row],[Цена ]]>0,смарты_нал5[[#This Row],[Цена ]]/0.87,"") -> 19425.287 | G15: =IF(смарты_нал5[[#This Row],[Цена ]]<>"",смарты_нал5[[#This Row],[Цена ]]*смарты_нал5[[#This Row],[Заказ нал.]],"") -> 0 | H15: =IF(смарты_нал5[[#This Row],[Цена Б.Н.]]<>"",смарты_нал5[[#This Row],[Цена Б.Н.]]*смарты_нал5[[#This Row],[Заказ Б.Н.]],"") -> 0
A16: Электроника / Google Pixel | D16: =IF(смарты_нал5[[#This Row],[Цена ]]>0,смарты_нал5[[#This Row],[Цена ]]/0.87,"") | G16: =IF(смарты_нал5[[#This Row],[Цена ]]<>"",смарты_нал5[[#This Row],[Цена ]]*смарты_нал5[[#This Row],[Заказ нал.]],"") | H16: =IF(смарты_нал5[[#This Row],[Цена Б.Н.]]<>"",смарты_нал5[[#This Row],[Цена Б.Н.]]*смарты_нал5[[#This Row],[Заказ Б.Н.]],"")
A17: 21017-2IN | B17: Google Pixel 10 5G 12/256GB NFC Indigo IN | C17: 51500 | D17: =IF(смарты_нал5[[#This Row],[Цена ]]>0,смарты_нал5[[#This Row],[Цена ]]/0.87,"") -> 59195.402 | G17: =IF(смарты_нал5[[#This Row],[Цена ]]<>"",смарты_нал5[[#This Row],[Цена ]]*смарты_нал5[[#This Row],[Заказ нал.]],"") -> 0 | H17: =IF(смарты_нал5[[#This Row],[Цена Б.Н.]]<>"",смарты_нал5[[#This Row],[Цена Б.Н.]]*смарты_нал5[[#This Row],[Заказ Б.Н.]],"") -> 0
A18: 21017-4IN | B18: Google Pixel 10 5G 12/256GB NFC Lemongrass IN | C18: 51500 | D18: =IF(смарты_нал5[[#This Row],[Цена ]]>0,смарты_нал5[[#This Row],[Цена ]]/0.87,"") -> 59195.402 | G18: =IF(смарты_нал5[[#This Row],[Цена ]]<>"",смарты_нал5[[#This Row],[Цена ]]*смарты_нал5[[#This Row],[Заказ нал.]],"") -> 0 | H18: =IF(смарты_нал5[[#This Row],[Цена Б.Н.]]<>"",смарты_нал5[[#This Row],[Цена Б.Н.]]*смарты_нал5[[#This Row],[Заказ Б.Н.]],"") -> 0
A19: 21017-1IN | B19: Google Pixel 10 5G 12/256GB NFC Obsidian IN | C19: 51500 | D19: =IF(смарты_нал5[[#This Row],[Цена ]]>0,смарты_нал5[[#This Row],[Цена ]]/0.87,"") -> 59195.402 | G19: =IF(смарты_нал5[[#This Row],[Цена ]]<>"",смарты_нал5[[#This Row],[Цена ]]*смарты_нал5[[#This Row],[Заказ нал.]],"") -> 0 | H19: =IF(смарты_нал5[[#This Row],[Цена Б.Н.]]<>"",смарты_нал5[[#This Row],[Цена Б.Н.]]*смарты_нал5[[#This Row],[Заказ Б.Н.]],"") -> 0
A20: 21028-2AU | B20: Google Pixel 10a 5G 8/128GB NFC Fog AU | C20: 34700 | D20: =IF(смарты_нал5[[#This Row],[Цена ]]>0,смарты_нал5[[#This Row],[Цена ]]/0.87,"") -> 39885.057 | G20: =IF(смарты_нал5[[#This Row],[Цена ]]<>"",смарты_нал5[[#This Row],[Цена ]]*смарты_нал5[[#This Row],[Заказ нал.]],"") -> 0 | H20: =IF(смарты_нал5[[#This Row],[Цена Б.Н.]]<>"",смарты_нал5[[#This Row],[Цена Б.Н.]]*смарты_нал5[[#This Row],[Заказ Б.Н.]],"") -> 0
A21: 21028-3AU | B21: Google Pixel 10a 5G 8/128GB NFC Lavander AU | C21: 34700 | D21: =IF(смарты_нал5[[#This Row],[Цена ]]>0,смарты_нал5[[#This Row],[Цена ]]/0.87,"") -> 39885.057 | G21: =IF(смарты_нал5[[#This Row],[Цена ]]<>"",смарты_нал5[[#This Row],[Цена ]]*смарты_нал5[[#This Row],[Заказ нал.]],"") -> 0 | H21: =IF(смарты_нал5[[#This Row],[Цена Б.Н.]]<>"",смарты_нал5[[#This Row],[Цена Б.Н.]]*смарты_нал5[[#This Row],[Заказ Б.Н.]],"") -> 0
A22: 21028-1AU | B22: Google Pixel 10a 5G 8/128GB NFC Obsidian AU | C22: 34700 | D22: =IF(смарты_нал5[[#This Row],[Цена ]]>0,смарты_нал5[[#This Row],[Цена ]]/0.87,"") -> 39885.057 | G22: =IF(смарты_нал5[[#This Row],[Цена ]]<>"",смарты_нал5[[#This Row],[Цена ]]*смарты_нал5[[#This Row],[Заказ нал.]],"") -> 0 | H22: =IF(смарты_нал5[[#This Row],[Цена Б.Н.]]<>"",смарты_нал5[[#This Row],[Цена Б.Н.]]*смарты_нал5[[#This Row],[Заказ Б.Н.]],"") -> 0
A23: 21011-1CA | B23: Google Pixel 9 Pro XL 5G 16GB/1TB NFC Obsidian CA | C23: 64700 | D23: =IF(смарты_нал5[[#This Row],[Цена ]]>0,смарты_нал5[[#This Row],[Цена ]]/0.87,"") -> 74367.816 | G23: =IF(смарты_нал5[[#This Row],[Цена ]]<>"",смарты_нал5[[#This Row],[Цена ]]*смарты_нал5[[#This Row],[Заказ нал.]],"") -> 0 | H23: =IF(смарты_нал5[[#This Row],[Цена Б.Н.]]<>"",смарты_нал5[[#This Row],[Цена Б.Н.]]*смарты_нал5[[#This Row],[Заказ Б.Н.]],"") -> 0
A24: 21015-1IN | B24: Google Pixel 9a 5G 8/256GB NFC Obsidian IN | C24: 31800 | D24: =IF(смарты_нал5[[#This Row],[Цена ]]>0,смарты_нал5[[#This Row],[Цена ]]/0.87,"") -> 36551.724 | G24: =IF(смарты_нал5[[#This Row],[Цена ]]<>"",смарты_нал5[[#This Row],[Цена ]]*смарты_нал5[[#This Row],[Заказ нал.]],"") -> 0 | H24: =IF(смарты_нал5[[#This Row],[Цена Б.Н.]]<>"",смарты_нал5[[#This Row],[Цена Б.Н.]]*смарты_нал5[[#This Row],[Заказ Б.Н.]],"") -> 0
A25: Электроника / Honor | D25: =IF(смарты_нал5[[#This Row],[Цена ]]>0,смарты_нал5[[#This Row],[Цена ]]/0.87,"") | G25: =IF(смарты_нал5[[#This Row],[Цена ]]<>"",смарты_нал5[[#This Row],[Цена ]]*смарты_нал5[[#This Row],[Заказ нал.]],"") | H25: =IF(смарты_нал5[[#This Row],[Цена Б.Н.]]<>"",смарты_нал5[[#This Row],[Цена Б.Н.]]*смарты_нал5[[#This Row],[Заказ Б.Н.]],"") | M25: 52
A26: 16533-3UK | B26: Honor 400 12/256GB NFC Desert Gold UK | C26: 29400 | D26: =IF(смарты_нал5[[#This Row],[Цена ]]>0,смарты_нал5[[#This Row],[Цена ]]/0.87,"") -> 33793.103 | G26: =IF(смарты_нал5[[#This Row],[Цена ]]<>"",смарты_нал5[[#This Row],[Цена ]]*смарты_нал5[[#This Row],[Заказ нал.]],"") -> 0 | H26: =IF(смарты_нал5[[#This Row],[Цена Б.Н.]]<>"",смарты_нал5[[#This Row],[Цена Б.Н.]]*смарты_нал5[[#This Row],[Заказ Б.Н.]],"") -> 0
A27: 16533-1UK | B27: Honor 400 12/256GB NFC Midnight Black UK | C27: 29400 | D27: =IF(смарты_нал5[[#This Row],[Цена ]]>0,смарты_нал5[[#This Row],[Цена ]]/0.87,"") -> 33793.103 | G27: =IF(смарты_нал5[[#This Row],[Цена ]]<>"",смарты_нал5[[#This Row],[Цена ]]*смарты_нал5[[#This Row],[Заказ нал.]],"") -> 0 | H27: =IF(смарты_нал5[[#This Row],[Цена Б.Н.]]<>"",смарты_нал5[[#This Row],[Цена Б.Н.]]*смарты_нал5[[#This Row],[Заказ Б.Н.]],"") -> 0
A28: 16534-1UK | B28: Honor 400 12/512GB NFC Midnight Black UK | C28: 31000 | D28: =IF(смарты_нал5[[#This Row],[Цена ]]>0,смарты_нал5[[#This Row],[Цена ]]/0.87,"") -> 35632.184 | G28: =IF(смарты_нал5[[#This Row],[Цена ]]<>"",смарты_нал5[[#This Row],[Цена ]]*смарты_нал5[[#This Row],[Заказ нал.]],"") -> 0 | H28: =IF(смарты_нал5[[#This Row],[Цена Б.Н.]]<>"",смарты_нал5[[#This Row],[Цена Б.Н.]]*смарты_нал5[[#This Row],[Заказ Б.Н.]],"") -> 0
A29: 16534-4UK | B29: Honor 400 12/512GB NFC Tidal Blue UK | C29: 31000 | D29: =IF(смарты_нал5[[#This Row],[Цена ]]>0,смарты_нал5[[#This Row],[Цена ]]/0.87,"") -> 35632.184 | G29: =IF(смарты_нал5[[#This Row],[Цена ]]<>"",смарты_нал5[[#This Row],[Цена ]]*смарты_нал5[[#This Row],[Заказ нал.]],"") -> 0 | H29: =IF(смарты_нал5[[#This Row],[Цена Б.Н.]]<>"",смарты_нал5[[#This Row],[Цена Б.Н.]]*смарты_нал5[[#This Row],[Заказ Б.Н.]],"") -> 0
A30: 16533-3 | B30: Honor 400 12+256GB NFC Desert Gold RUS | C30: 30100 | D30: =IF(смарты_нал5[[#This Row],[Цена ]]>0,смарты_нал5[[#This Row],[Цена ]]/0.87,"") -> 34597.701 | G30: =IF(смарты_нал5[[#This Row],[Цена ]]<>"",смарты_нал5[[#This Row],[Цена ]]*смарты_нал5[[#This Row],[Заказ нал.]],"") -> 0 | H30: =IF(смарты_нал5[[#This Row],[Цена Б.Н.]]<>"",смарты_нал5[[#This Row],[Цена Б.Н.]]*смарты_нал5[[#This Row],[Заказ Б.Н.]],"") -> 0
A31: 16533-2 | B31: Honor 400 12+256GB NFC Meteor Silver RUS | C31: 30100 | D31: =IF(смарты_нал5[[#This Row],[Цена ]]>0,смарты_нал5[[#This Row],[Цена ]]/0.87,"") -> 34597.701 | G31: =IF(смарты_нал5[[#This Row],[Цена ]]<>"",смарты_нал5[[#This Row],[Цена ]]*смарты_нал5[[#This Row],[Заказ нал.]],"") -> 0 | H31: =IF(смарты_нал5[[#This Row],[Цена Б.Н.]]<>"",смарты_нал5[[#This Row],[Цена Б.Н.]]*смарты_нал5[[#This Row],[Заказ Б.Н.]],"") -> 0 | M31: 15
A32: 16533-1 | B32: Honor 400 12+256GB NFC Midnight Black RUS | C32: 30100 | D32: =IF(смарты_нал5[[#This Row],[Цена ]]>0,смарты_нал5[[#This Row],[Цена ]]/0.87,"") -> 34597.701 | G32: =IF(смарты_нал5[[#This Row],[Цена ]]<>"",смарты_нал5[[#This Row],[Цена ]]*смарты_нал5[[#This Row],[Заказ нал.]],"") -> 0 | H32: =IF(смарты_нал5[[#This Row],[Цена Б.Н.]]<>"",смарты_нал5[[#This Row],[Цена Б.Н.]]*смарты_нал5[[#This Row],[Заказ Б.Н.]],"") -> 0
A33: 16532-3KZ | B33: Honor 400 8/256GB NFC Desert Gold KZ | C33: 27400 | D33: =IF(смарты_нал5[[#This Row],[Цена ]]>0,смарты_нал5[[#This Row],[Цена ]]/0.87,"") -> 31494.253 | G33: =IF(смарты_нал5[[#This Row],[Цена ]]<>"",смарты_нал5[[#This Row],[Цена ]]*смарты_нал5[[#This Row],[Заказ нал.]],"") -> 0 | H33: =IF(смарты_нал5[[#This Row],[Цена Б.Н.]]<>"",смарты_нал5[[#This Row],[Цена Б.Н.]]*смарты_нал5[[#This Row],[Заказ Б.Н.]],"") -> 0
A34: 16560-3EU | B34: Honor 400 8/512GB NFC (No Charger) Desert Gold EU | C34: 28000 | D34: =IF(смарты_нал5[[#This Row],[Цена ]]>0,смарты_нал5[[#This Row],[Цена ]]/0.87,"") -> 32183.908 | G34: =IF(смарты_нал5[[#This Row],[Цена ]]<>"",смарты_нал5[[#This Row],[Цена ]]*смарты_нал5[[#This Row],[Заказ нал.]],"") -> 0 | H34: =IF(смарты_нал5[[#This Row],[Цена Б.Н.]]<>"",смарты_нал5[[#This Row],[Цена Б.Н.]]*смарты_нал5[[#This Row],[Заказ Б.Н.]],"") -> 0
A35: 16560-1EU | B35: Honor 400 8/512GB NFC (No Charger) Midnight Black EU | C35: 28000 | D35: =IF(смарты_нал5[[#This Row],[Цена ]]>0,смарты_нал5[[#This Row],[Цена ]]/0.87,"") -> 32183.908 | G35: =IF(смарты_нал5[[#This Row],[Цена ]]<>"",смарты_нал5[[#This Row],[Цена ]]*смарты_нал5[[#This Row],[Заказ нал.]],"") -> 0 | H35: =IF(смарты_нал5[[#This Row],[Цена Б.Н.]]<>"",смарты_нал5[[#This Row],[Цена Б.Н.]]*смарты_нал5[[#This Row],[Заказ Б.Н.]],"") -> 0
A36: 16532-3 | B36: Honor 400 8+256GB NFC Desert Gold RUS | C36: 27700 | D36: =IF(смарты_нал5[[#This Row],[Цена ]]>0,смарты_нал5[[#This Row],[Цена ]]/0.87,"") -> 31839.08 | G36: =IF(смарты_нал5[[#This Row],[Цена ]]<>"",смарты_нал5[[#This Row],[Цена ]]*смарты_нал5[[#This Row],[Заказ нал.]],"") -> 0 | H36: =IF(смарты_нал5[[#This Row],[Цена Б.Н.]]<>"",смарты_нал5[[#This Row],[Цена Б.Н.]]*смарты_нал5[[#This Row],[Заказ Б.Н.]],"") -> 0
A37: 16532-2 | B37: Honor 400 8+256GB NFC Meteor Silver RUS | C37: 27700 | D37: =IF(смарты_нал5[[#This Row],[Цена ]]>0,смарты_нал5[[#This Row],[Цена ]]/0.87,"") -> 31839.08 | G37: =IF(смарты_нал5[[#This Row],[Цена ]]<>"",смарты_нал5[[#This Row],[Цена ]]*смарты_нал5[[#This Row],[Заказ нал.]],"") -> 0 | H37: =IF(смарты_нал5[[#This Row],[Цена Б.Н.]]<>"",смарты_нал5[[#This Row],[Цена Б.Н.]]*смарты_нал5[[#This Row],[Заказ Б.Н.]],"") -> 0 | M37: 13
A38: 16532-1 | B38: Honor 400 8+256GB NFC Midnight Black RUS | C38: 27700 | D38: =IF(смарты_нал5[[#This Row],[Цена ]]>0,смарты_нал5[[#This Row],[Цена ]]/0.87,"") -> 31839.08 | G38: =IF(смарты_нал5[[#This Row],[Цена ]]<>"",смарты_нал5[[#This Row],[Цена ]]*смарты_нал5[[#This Row],[Заказ нал.]],"") -> 0 | H38: =IF(смарты_нал5[[#This Row],[Цена Б.Н.]]<>"",смарты_нал5[[#This Row],[Цена Б.Н.]]*смарты_нал5[[#This Row],[Заказ Б.Н.]],"") -> 0
A39: 16528-3 | B39: Honor 400 Lite 5G 8+256GB NFC Marrs Green RUS | C39: 18400 | D39: =IF(смарты_нал5[[#This Row],[Цена ]]>0,смарты_нал5[[#This Row],[Цена ]]/0.87,"") -> 21149.425 | G39: =IF(смарты_нал5[[#This Row],[Цена ]]<>"",смарты_нал5[[#This Row],[Цена ]]*смарты_нал5[[#This Row],[Заказ нал.]],"") -> 0 | H39: =IF(смарты_нал5[[#This Row],[Цена Б.Н.]]<>"",смарты_нал5[[#This Row],[Цена Б.Н.]]*смарты_нал5[[#This Row],[Заказ Б.Н.]],"") -> 0
A40: 16528-1 | B40: Honor 400 Lite 5G 8+256GB NFC Velvet Black RUS | C40: 18400 | D40: =IF(смарты_нал5[[#This Row],[Цена ]]>0,смарты_нал5[[#This Row],[Цена ]]/0.87,"") -> 21149.425 | G40: =IF(смарты_нал5[[#This Row],[Цена ]]<>"",смарты_нал5[[#This Row],[Цена ]]*смарты_нал5[[#This Row],[Заказ нал.]],"") -> 0 | H40: =IF(смарты_нал5[[#This Row],[Цена Б.Н.]]<>"",смарты_нал5[[#This Row],[Цена Б.Н.]]*смарты_нал5[[#This Row],[Заказ Б.Н.]],"") -> 0
A41: 16536-2AE | B41: Honor 400 Pro 12/512GB NFC Lunar Gray AE | C41: 46600 | D41: =IF(смарты_нал5[[#This Row],[Цена ]]>0,смарты_нал5[[#This Row],[Цена ]]/0.87,"") -> 53563.218 | G41: =IF(смарты_нал5[[#This Row],[Цена ]]<>"",смарты_нал5[[#This Row],[Цена ]]*смарты_нал5[[#This Row],[Заказ нал.]],"") -> 0 | H41: =IF(смарты_нал5[[#This Row],[Цена Б.Н.]]<>"",смарты_нал5[[#This Row],[Цена Б.Н.]]*смарты_нал5[[#This Row],[Заказ Б.Н.]],"") -> 0
A42: 16536-3UK | B42: Honor 400 Pro 12/512GB NFC Tidal Blue UK | C42: 46600 | D42: =IF(смарты_нал5[[#This Row],[Цена ]]>0,смарты_нал5[[#This Row],[Цена ]]/0.87,"") -> 53563.218 | G42: =IF(смарты_нал5[[#This Row],[Цена ]]<>"",смарты_нал5[[#This Row],[Цена ]]*смарты_нал5[[#This Row],[Заказ нал.]],"") -> 0 | H42: =IF(смарты_нал5[[#This Row],[Цена Б.Н.]]<>"",смарты_нал5[[#This Row],[Цена Б.Н.]]*смарты_нал5[[#This Row],[Заказ Б.Н.]],"") -> 0
A43: 16535-1 | B43: Honor 400 Pro 12+256GB NFC Midnight Black RUS | C43: 43500 | D43: =IF(смарты_нал5[[#This Row],[Цена ]]>0,смарты_нал5[[#This Row],[Цена ]]/0.87,"") -> 50000 | G43: =IF(смарты_нал5[[#This Row],[Цена ]]<>"",смарты_нал5[[#This Row],[Цена ]]*смарты_нал5[[#This Row],[Заказ нал.]],"") -> 0 | H43: =IF(смарты_нал5[[#This Row],[Цена Б.Н.]]<>"",смарты_нал5[[#This Row],[Цена Б.Н.]]*смарты_нал5[[#This Row],[Заказ Б.Н.]],"") -> 0
A44: 16555-2KZ | B44: Honor 600 Lite 5G 8/256GB NFC Velvet Gray KZ | C44: 21400 | D44: =IF(смарты_нал5[[#This Row],[Цена ]]>0,смарты_нал5[[#This Row],[Цена ]]/0.87,"") -> 24597.701 | G44: =IF(смарты_нал5[[#This Row],[Цена ]]<>"",смарты_нал5[[#This Row],[Цена ]]*смарты_нал5[[#This Row],[Заказ нал.]],"") -> 0 | H44: =IF(смарты_нал5[[#This Row],[Цена Б.Н.]]<>"",смарты_нал5[[#This Row],[Цена Б.Н.]]*смарты_нал5[[#This Row],[Заказ Б.Н.]],"") -> 0
A45: 16555-1 | B45: Honor 600 Lite 5G 8+256GB NFC Velvet Black RUS | C45: 21500 | D45: =IF(смарты_нал5[[#This Row],[Цена ]]>0,смарты_нал5[[#This Row],[Цена ]]/0.87,"") -> 24712.644 | G45: =IF(смарты_нал5[[#This Row],[Цена ]]<>"",смарты_нал5[[#This Row],[Цена ]]*смарты_нал5[[#This Row],[Заказ нал.]],"") -> 0 | H45: =IF(смарты_нал5[[#This Row],[Цена Б.Н.]]<>"",смарты_нал5[[#This Row],[Цена Б.Н.]]*смарты_нал5[[#This Row],[Заказ Б.Н.]],"") -> 0
A46: 13094-3EU | B46: Honor 90 5G 12/512GB NFC Emerald Green EU | C46: 23500 | D46: =IF(смарты_нал5[[#This Row],[Цена ]]>0,смарты_нал5[[#This Row],[Цена ]]/0.87,"") -> 27011.494 | G46: =IF(смарты_нал5[[#This Row],[Цена ]]<>"",смарты_нал5[[#This Row],[Цена ]]*смарты_нал5[[#This Row],[Заказ нал.]],"") -> 0 | H46: =IF(смарты_нал5[[#This Row],[Цена Б.Н.]]<>"",смарты_нал5[[#This Row],[Цена Б.Н.]]*смарты_нал5[[#This Row],[Заказ Б.Н.]],"") -> 0
A47: 16525-1 | B47: Honor Magic 7 5G 12+256GB NFC Black RUS | C47: 50200 | D47: =IF(смарты_нал5[[#This Row],[Цена ]]>0,смарты_нал5[[#This Row],[Цена ]]/0.87,"") -> 57701.149 | G47: =IF(смарты_нал5[[#This Row],[Цена ]]<>"",смарты_нал5[[#This Row],[Цена ]]*смарты_нал5[[#This Row],[Заказ нал.]],"") -> 0 | H47: =IF(смарты_нал5[[#This Row],[Цена Б.Н.]]<>"",смарты_нал5[[#This Row],[Цена Б.Н.]]*смарты_нал5[[#This Row],[Заказ Б.Н.]],"") -> 0
A48: 16519-1UK | B48: Honor Magic 7 Pro 5G 12/512GB NFC Black UK | C48: 58500 | D48: =IF(смарты_нал5[[#This Row],[Цена ]]>0,смарты_нал5[[#This Row],[Цена ]]/0.87,"") -> 67241.379 | G48: =IF(смарты_нал5[[#This Row],[Цена ]]<>"",смарты_нал5[[#This Row],[Цена ]]*смарты_нал5[[#This Row],[Заказ нал.]],"") -> 0 | H48: =IF(смарты_нал5[[#This Row],[Цена Б.Н.]]<>"",смарты_нал5[[#This Row],[Цена Б.Н.]]*смарты_нал5[[#This Row],[Заказ Б.Н.]],"") -> 0
A49: 16519-3UK | B49: Honor Magic 7 Pro 5G 12/512GB NFC Breeze Blue UK | C49: 58500 | D49: =IF(смарты_нал5[[#This Row],[Цена ]]>0,смарты_нал5[[#This Row],[Цена ]]/0.87,"") -> 67241.379 | G49: =IF(смарты_нал5[[#This Row],[Цена ]]<>"",смарты_нал5[[#This Row],[Цена ]]*смарты_нал5[[#This Row],[Заказ нал.]],"") -> 0 | H49: =IF(смарты_нал5[[#This Row],[Цена Б.Н.]]<>"",смарты_нал5[[#This Row],[Цена Б.Н.]]*смарты_нал5[[#This Row],[Заказ Б.Н.]],"") -> 0
... A62: 16521-3 | B62: Honor X7C 8+512GB NFC Moonlight White RUS | C62: 16100 | D62: =IF(смарты_нал5[[#This Row],[Цена ]]>0,смарты_нал5[[#This Row],[Цена ]]/0.87,"") -> 18505.747 | G62: =IF(смарты_нал5[[#This Row],[Цена ]]<>"",смарты_нал5[[#This Row],[Цена ]]*смарты_нал5[[#This Row],[Заказ нал.]],"") -> 0 | H62: =IF(смарты_нал5[[#This Row],[Цена Б.Н.]]<>"",смарты_нал5[[#This Row],[Цена Б.Н.]]*смарты_нал5[[#This Row],[Заказ Б.Н.]],"") -> 0
A63: 16540-3 | B63: Honor X7d 6+128GB NFC Desert Gold RUS | C63: 11400 | D63: =IF(смарты_нал5[[#This Row],[Цена ]]>0,смарты_нал5[[#This Row],[Цена ]]/0.87,"") -> 13103.448 | G63: =IF(смарты_нал5[[#This Row],[Цена ]]<>"",смарты_нал5[[#This Row],[Цена ]]*смарты_нал5[[#This Row],[Заказ нал.]],"") -> 0 | H63: =IF(смарты_нал5[[#This Row],[Цена Б.Н.]]<>"",смарты_нал5[[#This Row],[Цена Б.Н.]]*смарты_нал5[[#This Row],[Заказ Б.Н.]],"") -> 0 | M63: 3
A64: 16540-1 | B64: Honor X7d 6+128GB NFC Velvet Black RUS | C64: 11400 | D64: =IF(смарты_нал5[[#This Row],[Цена ]]>0,смарты_нал5[[#This Row],[Цена ]]/0.87,"") -> 13103.448 | G64: =IF(смарты_нал5[[#This Row],[Цена ]]<>"",смарты_нал5[[#This Row],[Цена ]]*смарты_нал5[[#This Row],[Заказ нал.]],"") -> 0 | H64: =IF(смарты_нал5[[#This Row],[Цена Б.Н.]]<>"",смарты_нал5[[#This Row],[Цена Б.Н.]]*смарты_нал5[[#This Row],[Заказ Б.Н.]],"") -> 0
A65: 16551-3 | B65: Honor X7d 8+128GB NFC Desert Gold RUS | C65: 12300 | D65: =IF(смарты_нал5[[#This Row],[Цена ]]>0,смарты_нал5[[#This Row],[Цена ]]/0.87,"") -> 14137.931 | G65: =IF(смарты_нал5[[#This Row],[Цена ]]<>"",смарты_нал5[[#This Row],[Цена ]]*смарты_нал5[[#This Row],[Заказ нал.]],"") -> 0 | H65: =IF(смарты_нал5[[#This Row],[Цена Б.Н.]]<>"",смарты_нал5[[#This Row],[Цена Б.Н.]]*смарты_нал5[[#This Row],[Заказ Б.Н.]],"") -> 0
A66: 16551-2 | B66: Honor X7d 8+128GB NFC Meteor Silver RUS | C66: 12300 | D66: =IF(смарты_нал5[[#This Row],[Цена ]]>0,смарты_нал5[[#This Row],[Цена ]]/0.87,"") -> 14137.931 | G66: =IF(смарты_нал5[[#This Row],[Цена ]]<>"",смарты_нал5[[#This Row],[Цена ]]*смарты_нал5[[#This Row],[Заказ нал.]],"") -> 0 | H66: =IF(смарты_нал5[[#This Row],[Цена Б.Н.]]<>"",смарты_нал5[[#This Row],[Цена Б.Н.]]*смарты_нал5[[#This Row],[Заказ Б.Н.]],"") -> 0
A67: 16551-1 | B67: Honor X7d 8+128GB NFC Velvet Black RUS | C67: 12300 | D67: =IF(смарты_нал5[[#This Row],[Цена ]]>0,смарты_нал5[[#This Row],[Цена ]]/0.87,"") -> 14137.931 | G67: =IF(смарты_нал5[[#This Row],[Цена ]]<>"",смарты_нал5[[#This Row],[Цена ]]*смарты_нал5[[#This Row],[Заказ нал.]],"") -> 0 | H67: =IF(смарты_нал5[[#This Row],[Цена Б.Н.]]<>"",смарты_нал5[[#This Row],[Цена Б.Н.]]*смарты_нал5[[#This Row],[Заказ Б.Н.]],"") -> 0 | M67: 6
A68: 16541-3 | B68: Honor X7d 8+256GB NFC Desert Gold RUS | C68: 15000 | D68: =IF(смарты_нал5[[#This Row],[Цена ]]>0,смарты_нал5[[#This Row],[Цена ]]/0.87,"") -> 17241.379 | G68: =IF(смарты_нал5[[#This Row],[Цена ]]<>"",смарты_нал5[[#This Row],[Цена ]]*смарты_нал5[[#This Row],[Заказ нал.]],"") -> 0 | H68: =IF(смарты_нал5[[#This Row],[Цена Б.Н.]]<>"",смарты_нал5[[#This Row],[Цена Б.Н.]]*смарты_нал5[[#This Row],[Заказ Б.Н.]],"") -> 0
A69: 16541-2 | B69: Honor X7d 8+256GB NFC Meteor Silver RUS | C69: 15000 | D69: =IF(смарты_нал5[[#This Row],[Цена ]]>0,смарты_нал5[[#This Row],[Цена ]]/0.87,"") -> 17241.379 | G69: =IF(смарты_нал5[[#This Row],[Цена ]]<>"",смарты_нал5[[#This Row],[Цена ]]*смарты_нал5[[#This Row],[Заказ нал.]],"") -> 0 | H69: =IF(смарты_нал5[[#This Row],[Цена Б.Н.]]<>"",смарты_нал5[[#This Row],[Цена Б.Н.]]*смарты_нал5[[#This Row],[Заказ Б.Н.]],"") -> 0
A70: 16547-3 | B70: Honor X8d 8+128GB NFC Light Blue RUS | C70: 15300 | D70: =IF(смарты_нал5[[#This Row],[Цена ]]>0,смарты_нал5[[#This Row],[Цена ]]/0.87,"") -> 17586.207 | G70: =IF(смарты_нал5[[#This Row],[Цена ]]<>"",смарты_нал5[[#This Row],[Цена ]]*смарты_нал5[[#This Row],[Заказ нал.]],"") -> 0 | H70: =IF(смарты_нал5[[#This Row],[Цена Б.Н.]]<>"",смарты_нал5[[#This Row],[Цена Б.Н.]]*смарты_нал5[[#This Row],[Заказ Б.Н.]],"") -> 0
A71: 16547-1 | B71: Honor X8d 8+128GB NFC Velvet Black RUS | C71: 15300 | D71: =IF(смарты_нал5[[#This Row],[Цена ]]>0,смарты_нал5[[#This Row],[Цена ]]/0.87,"") -> 17586.207 | G71: =IF(смарты_нал5[[#This Row],[Цена ]]<>"",смарты_нал5[[#This Row],[Цена ]]*смарты_нал5[[#This Row],[Заказ нал.]],"") -> 0 | H71: =IF(смарты_нал5[[#This Row],[Цена Б.Н.]]<>"",смарты_нал5[[#This Row],[Цена Б.Н.]]*смарты_нал5[[#This Row],[Заказ Б.Н.]],"") -> 0
A72: 16547-2 | B72: Honor X8d 8+128GB NFC Velvet Gray RUS | C72: 15300 | D72: =IF(смарты_нал5[[#This Row],[Цена ]]>0,смарты_нал5[[#This Row],[Цена ]]/0.87,"") -> 17586.207 | G72: =IF(смарты_нал5[[#This Row],[Цена ]]<>"",смарты_нал5[[#This Row],[Цена ]]*смарты_нал5[[#This Row],[Заказ нал.]],"") -> 0 | H72: =IF(смарты_нал5[[#This Row],[Цена Б.Н.]]<>"",смарты_нал5[[#This Row],[Цена Б.Н.]]*смарты_нал5[[#This Row],[Заказ Б.Н.]],"") -> 0
A73: 16548-2 | B73: Honor X8d 8+256GB NFC Velvet Gray RUS | C73: 17500 | D73: =IF(смарты_нал5[[#This Row],[Цена ]]>0,смарты_нал5[[#This Row],[Цена ]]/0.87,"") -> 20114.943 | G73: =IF(смарты_нал5[[#This Row],[Цена ]]<>"",смарты_нал5[[#This Row],[Цена ]]*смарты_нал5[[#This Row],[Заказ нал.]],"") -> 0 | H73: =IF(смарты_нал5[[#This Row],[Цена Б.Н.]]<>"",смарты_нал5[[#This Row],[Цена Б.Н.]]*смарты_нал5[[#This Row],[Заказ Б.Н.]],"") -> 0 | M73: 4
A74: 16552-1EU | B74: Honor X9d 5G 12/512GB NFC Графитовый / Midnight Black EU | C74: 31300 | D74: =IF(смарты_нал5[[#This Row],[Цена ]]>0,смарты_нал5[[#This Row],[Цена ]]/0.87,"") -> 35977.011 | G74: =IF(смарты_нал5[[#This Row],[Цена ]]<>"",смарты_нал5[[#This Row],[Цена ]]*смарты_нал5[[#This Row],[Заказ нал.]],"") -> 0 | H74: =IF(смарты_нал5[[#This Row],[Цена Б.Н.]]<>"",смарты_нал5[[#This Row],[Цена Б.Н.]]*смарты_нал5[[#This Row],[Заказ Б.Н.]],"") -> 0
A75: 16552-3EU | B75: Honor X9d 5G 12/512GB NFC Терракотовый / Reddish Brown EU | C75: 31300 | D75: =IF(смарты_нал5[[#This Row],[Цена ]]>0,смарты_нал5[[#This Row],[Цена ]]/0.87,"") -> 35977.011 | G75: =IF(смарты_нал5[[#This Row],[Цена ]]<>"",смарты_нал5[[#This Row],[Цена ]]*смарты_нал5[[#This Row],[Заказ нал.]],"") -> 0 | H75: =IF(смарты_нал5[[#This Row],[Цена Б.Н.]]<>"",смарты_нал5[[#This Row],[Цена Б.Н.]]*смарты_нал5[[#This Row],[Заказ Б.Н.]],"") -> 0
A76: 16544-4 | B76: Honor X9d 5G 12+256GB NFC Бежевый / Sunrise Gold RUS | C76: 24000 | D76: =IF(смарты_нал5[[#This Row],[Цена ]]>0,смарты_нал5[[#This Row],[Цена ]]/0.87,"") -> 27586.207 | G76: =IF(смарты_нал5[[#This Row],[Цена ]]<>"",смарты_нал5[[#This Row],[Цена ]]*смарты_нал5[[#This Row],[Заказ нал.]],"") -> 0 | H76: =IF(смарты_нал5[[#This Row],[Цена Б.Н.]]<>"",смарты_нал5[[#This Row],[Цена Б.Н.]]*смарты_нал5[[#This Row],[Заказ Б.Н.]],"") -> 0 | M76: 2
A77: 16544-1 | B77: Honor X9d 5G 12+256GB NFC Графитовый / Midnight Black RUS | C77: 24500 | D77: =IF(смарты_нал5[[#This Row],[Цена ]]>0,смарты_нал5[[#This Row],[Цена ]]/0.87,"") -> 28160.92 | G77: =IF(смарты_нал5[[#This Row],[Цена ]]<>"",смарты_нал5[[#This Row],[Цена ]]*смарты_нал5[[#This Row],[Заказ нал.]],"") -> 0 | H77: =IF(смарты_нал5[[#This Row],[Цена Б.Н.]]<>"",смарты_нал5[[#This Row],[Цена Б.Н.]]*смарты_нал5[[#This Row],[Заказ Б.Н.]],"") -> 0
A78: 16544-2 | B78: Honor X9d 5G 12+256GB NFC Мятный / Forest Green RUS | C78: 24000 | D78: =IF(смарты_нал5[[#This Row],[Цена ]]>0,смарты_нал5[[#This Row],[Цена ]]/0.87,"") -> 27586.207 | G78: =IF(смарты_нал5[[#This Row],[Цена ]]<>"",смарты_нал5[[#This Row],[Цена ]]*смарты_нал5[[#This Row],[Заказ нал.]],"") -> 0 | H78: =IF(смарты_нал5[[#This Row],[Цена Б.Н.]]<>"",смарты_нал5[[#This Row],[Цена Б.Н.]]*смарты_нал5[[#This Row],[Заказ Б.Н.]],"") -> 0 | M78: 9
A79: 16544-3 | B79: Honor X9d 5G 12+256GB NFC Терракотовый / Reddish Brown RUS | C79: 24500 | D79: =IF(смарты_нал5[[#This Row],[Цена ]]>0,смарты_нал5[[#This Row],[Цена ]]/0.87,"") -> 28160.92 | G79: =IF(смарты_нал5[[#This Row],[Цена ]]<>"",смарты_нал5[[#This Row],[Цена ]]*смарты_нал5[[#This Row],[Заказ нал.]],"") -> 0 | H79: =IF(смарты_нал5[[#This Row],[Цена Б.Н.]]<>"",смарты_нал5[[#This Row],[Цена Б.Н.]]*смарты_нал5[[#This Row],[Заказ Б.Н.]],"") -> 0
A80: 16556-4EU | B80: Honor X9d 5G 8/512GB NFC Бежевый / Sunrise Gold EU | C80: 25900 | D80: =IF(смарты_нал5[[#This Row],[Цена ]]>0,смарты_нал5[[#This Row],[Цена ]]/0.87,"") -> 29770.115 | G80: =IF(смарты_нал5[[#This Row],[Цена ]]<>"",смарты_нал5[[#This Row],[Цена ]]*смарты_нал5[[#This Row],[Заказ нал.]],"") -> 0 | H80: =IF(смарты_нал5[[#This Row],[Цена Б.Н.]]<>"",смарты_нал5[[#This Row],[Цена Б.Н.]]*смарты_нал5[[#This Row],[Заказ Б.Н.]],"") -> 0
A81: 16556-1EU | B81: Honor X9d 5G 8/512GB NFC Графитовый / Midnight Black EU | C81: 25900 | D81: =IF(смарты_нал5[[#This Row],[Цена ]]>0,смарты_нал5[[#This Row],[Цена ]]/0.87,"") -> 29770.115 | G81: =IF(смарты_нал5[[#This Row],[Цена ]]<>"",смарты_нал5[[#This Row],[Цена ]]*смарты_нал5[[#This Row],[Заказ нал.]],"") -> 0 | H81: =IF(смарты_нал5[[#This Row],[Цена Б.Н.]]<>"",смарты_нал5[[#This Row],[Цена Б.Н.]]*смарты_нал5[[#This Row],[Заказ Б.Н.]],"") -> 0
A82: 16542-4 | B82: Honor X9d 5G 8+256GB NFC Бежевый / Sunrise Gold RUS | C82: 22300 | D82: =IF(смарты_нал5[[#This Row],[Цена ]]>0,смарты_нал5[[#This Row],[Цена ]]/0.87,"") -> 25632.184 | G82: =IF(смарты_нал5[[#This Row],[Цена ]]<>"",смарты_нал5[[#This Row],[Цена ]]*смарты_нал5[[#This Row],[Заказ нал.]],"") -> 0 | H82: =IF(смарты_нал5[[#This Row],[Цена Б.Н.]]<>"",смарты_нал5[[#This Row],[Цена Б.Н.]]*смарты_нал5[[#This Row],[Заказ Б.Н.]],"") -> 0
A83: 16542-2 | B83: Honor X9d 5G 8+256GB NFC Мятный / Forest Green RUS | C83: 22300 | D83: =IF(смарты_нал5[[#This Row],[Цена ]]>0,смарты_нал5[[#This Row],[Цена ]]/0.87,"") -> 25632.184 | G83: =IF(смарты_нал5[[#This Row],[Цена ]]<>"",смарты_нал5[[#This Row],[Цена ]]*смарты_нал5[[#This Row],[Заказ нал.]],"") -> 0 | H83: =IF(смарты_нал5[[#This Row],[Цена Б.Н.]]<>"",смарты_нал5[[#This Row],[Цена Б.Н.]]*смарты_нал5[[#This Row],[Заказ Б.Н.]],"") -> 0
A84: 16542-3 | B84: Honor X9d 5G 8+256GB NFC Терракотовый / Reddish Brown RUS | C84: 22300 | D84: =IF(смарты_нал5[[#This Row],[Цена ]]>0,смарты_нал5[[#This Row],[Цена ]]/0.87,"") -> 25632.184 | G84: =IF(смарты_нал5[[#This Row],[Цена ]]<>"",смарты_нал5[[#This Row],[Цена ]]*смарты_нал5[[#This Row],[Заказ нал.]],"") -> 0 | H84: =IF(смарты_нал5[[#This Row],[Цена Б.Н.]]<>"",смарты_нал5[[#This Row],[Цена Б.Н.]]*смарты_нал5[[#This Row],[Заказ Б.Н.]],"") -> 0
A85: Электроника / Honor / Планшеты Honor | D85: =IF(смарты_нал5[[#This Row],[Цена ]]>0,смарты_нал5[[#This Row],[Цена ]]/0.87,"") | G85: =IF(смарты_нал5[[#This Row],[Цена ]]<>"",смарты_нал5[[#This Row],[Цена ]]*смарты_нал5[[#This Row],[Заказ нал.]],"") | H85: =IF(смарты_нал5[[#This Row],[Цена Б.Н.]]<>"",смарты_нал5[[#This Row],[Цена Б.Н.]]*смарты_нал5[[#This Row],[Заказ Б.Н.]],"")
A86: 16606-1 | B86: Honor Pad X8A NDL-L09 11" 4+128GB LTE Gray RUS | C86: 16200 | D86: =IF(смарты_нал5[[#This Row],[Цена ]]>0,смарты_нал5[[#This Row],[Цена ]]/0.87,"") -> 18620.69 | G86: =IF(смарты_нал5[[#This Row],[Цена ]]<>"",смарты_нал5[[#This Row],[Цена ]]*смарты_нал5[[#This Row],[Заказ нал.]],"") -> 0 | H86: =IF(смарты_нал5[[#This Row],[Цена Б.Н.]]<>"",смарты_нал5[[#This Row],[Цена Б.Н.]]*смарты_нал5[[#This Row],[Заказ Б.Н.]],"") -> 0
A87: Электроника / Huawei | D87: =IF(смарты_нал5[[#This Row],[Цена ]]>0,смарты_нал5[[#This Row],[Цена ]]/0.87,"") | G87: =IF(смарты_нал5[[#This Row],[Цена ]]<>"",смарты_нал5[[#This Row],[Цена ]]*смарты_нал5[[#This Row],[Заказ нал.]],"") | H87: =IF(смарты_нал5[[#This Row],[Цена Б.Н.]]<>"",смарты_нал5[[#This Row],[Цена Б.Н.]]*смарты_нал5[[#This Row],[Заказ Б.Н.]],"") | M87: 39
A88: 10568-1 | B88: Huawei Mate 70 Pro 5G 12+512GB NFC Black RUS | C88: 51300 | D88: =IF(смарты_нал5[[#This Row],[Цена ]]>0,смарты_нал5[[#This Row],[Цена ]]/0.87,"") -> 58965.517 | G88: =IF(смарты_нал5[[#This Row],[Цена ]]<>"",смарты_нал5[[#This Row],[Цена ]]*смарты_нал5[[#This Row],[Заказ нал.]],"") -> 0 | H88: =IF(смарты_нал5[[#This Row],[Цена Б.Н.]]<>"",смарты_нал5[[#This Row],[Цена Б.Н.]]*смарты_нал5[[#This Row],[Заказ Б.Н.]],"") -> 0
A89: 10568-2 | B89: Huawei Mate 70 Pro 5G 12+512GB NFC Green RUS | C89: 50200 | D89: =IF(смарты_нал5[[#This Row],[Цена ]]>0,смарты_нал5[[#This Row],[Цена ]]/0.87,"") -> 57701.149 | G89: =IF(смарты_нал5[[#This Row],[Цена ]]<>"",смарты_нал5[[#This Row],[Цена ]]*смарты_нал5[[#This Row],[Заказ нал.]],"") -> 0 | H89: =IF(смарты_нал5[[#This Row],[Цена Б.Н.]]<>"",смарты_нал5[[#This Row],[Цена Б.Н.]]*смарты_нал5[[#This Row],[Заказ Б.Н.]],"") -> 0
A90: 10592-1UK | B90: Huawei Mate 80 Pro 16/512GB NFC Black UK | C90: 61600 | D90: =IF(смарты_нал5[[#This Row],[Цена ]]>0,смарты_нал5[[#This Row],[Цена ]]/0.87,"") -> 70804.598 | G90: =IF(смарты_нал5[[#This Row],[Цена ]]<>"",смарты_нал5[[#This Row],[Цена ]]*смарты_нал5[[#This Row],[Заказ нал.]],"") -> 0 | H90: =IF(смарты_нал5[[#This Row],[Цена Б.Н.]]<>"",смарты_нал5[[#This Row],[Цена Б.Н.]]*смарты_нал5[[#This Row],[Заказ Б.Н.]],"") -> 0
A91: 10592-3UK | B91: Huawei Mate 80 Pro 16/512GB NFC Gold UK | C91: 61600 | D91: =IF(смарты_нал5[[#This Row],[Цена ]]>0,смарты_нал5[[#This Row],[Цена ]]/0.87,"") -> 70804.598 | G91: =IF(смарты_нал5[[#This Row],[Цена ]]<>"",смарты_нал5[[#This Row],[Цена ]]*смарты_нал5[[#This Row],[Заказ нал.]],"") -> 0 | H91: =IF(смарты_нал5[[#This Row],[Цена Б.Н.]]<>"",смарты_нал5[[#This Row],[Цена Б.Н.]]*смарты_нал5[[#This Row],[Заказ Б.Н.]],"") -> 0
A92: 10592-2UK | B92: Huawei Mate 80 Pro 16/512GB NFC Green UK | C92: 61600 | D92: =IF(смарты_нал5[[#This Row],[Цена ]]>0,смарты_нал5[[#This Row],[Цена ]]/0.87,"") -> 70804.598 | G92: =IF(смарты_нал5[[#This Row],[Цена ]]<>"",смарты_нал5[[#This Row],[Цена ]]*смарты_нал5[[#This Row],[Заказ нал.]],"") -> 0 | H92: =IF(смарты_нал5[[#This Row],[Цена Б.Н.]]<>"",смарты_нал5[[#This Row],[Цена Б.Н.]]*смарты_нал5[[#This Row],[Заказ Б.Н.]],"") -> 0
A93: 10564-2UK | B93: Huawei Mate X6 5G 12/512GB NFC Nebula Gray UK | C93: 83900 | D93: =IF(смарты_нал5[[#This Row],[Цена ]]>0,смарты_нал5[[#This Row],[Цена ]]/0.87,"") -> 96436.782 | G93: =IF(смарты_нал5[[#This Row],[Цена ]]<>"",смарты_нал5[[#This Row],[Цена ]]*смарты_нал5[[#This Row],[Заказ нал.]],"") -> 0 | H93: =IF(смарты_нал5[[#This Row],[Цена Б.Н.]]<>"",смарты_нал5[[#This Row],[Цена Б.Н.]]*смарты_нал5[[#This Row],[Заказ Б.Н.]],"") -> 0
A94: 10564-3 | B94: Huawei Mate X6 5G 12+512GB NFC Nebula Red RUS | C94: 84900 | D94: =IF(смарты_нал5[[#This Row],[Цена ]]>0,смарты_нал5[[#This Row],[Цена ]]/0.87,"") -> 97586.207 | G94: =IF(смарты_нал5[[#This Row],[Цена ]]<>"",смарты_нал5[[#This Row],[Цена ]]*смарты_нал5[[#This Row],[Заказ нал.]],"") -> 0 | H94: =IF(смарты_нал5[[#This Row],[Цена Б.Н.]]<>"",смарты_нал5[[#This Row],[Цена Б.Н.]]*смарты_нал5[[#This Row],[Заказ Б.Н.]],"") -> 0
A95: 10585-1 | B95: Huawei Mate X7 16+512GB NFC Black RUS | C95: 108200 | D95: =IF(смарты_нал5[[#This Row],[Цена ]]>0,смарты_нал5[[#This Row],[Цена ]]/0.87,"") -> 124367.82 | G95: =IF(смарты_нал5[[#This Row],[Цена ]]<>"",смарты_нал5[[#This Row],[Цена ]]*смарты_нал5[[#This Row],[Заказ нал.]],"") -> 0 | H95: =IF(смарты_нал5[[#This Row],[Цена Б.Н.]]<>"",смарты_нал5[[#This Row],[Цена Б.Н.]]*смарты_нал5[[#This Row],[Заказ Б.Н.]],"") -> 0
A96: 10585-3 | B96: Huawei Mate X7 16+512GB NFC White RUS | C96: 109800 | D96: =IF(смарты_нал5[[#This Row],[Цена ]]>0,смарты_нал5[[#This Row],[Цена ]]/0.87,"") -> 126206.9 | G96: =IF(смарты_нал5[[#This Row],[Цена ]]<>"",смарты_нал5[[#This Row],[Цена ]]*смарты_нал5[[#This Row],[Заказ нал.]],"") -> 0 | H96: =IF(смарты_нал5[[#This Row],[Цена Б.Н.]]<>"",смарты_нал5[[#This Row],[Цена Б.Н.]]*смарты_нал5[[#This Row],[Заказ Б.Н.]],"") -> 0
A97: 10591-1KZ | B97: Huawei Mate XT Ultimate Design 16GB/1TB Black KZ | C97: 194600 | D97: =IF(смарты_нал5[[#This Row],[Цена ]]>0,смарты_нал5[[#This Row],[Цена ]]/0.87,"") -> 223678.16 | G97: =IF(смарты_нал5[[#This Row],[Цена ]]<>"",смарты_нал5[[#This Row],[Цена ]]*смарты_нал5[[#This Row],[Заказ нал.]],"") -> 0 | H97: =IF(смарты_нал5[[#This Row],[Цена Б.Н.]]<>"",смарты_нал5[[#This Row],[Цена Б.Н.]]*смарты_нал5[[#This Row],[Заказ Б.Н.]],"") -> 0
A98: 10591-2KZ | B98: Huawei Mate XT Ultimate Design 16GB/1TB Red KZ | C98: 194600 | D98: =IF(смарты_нал5[[#This Row],[Цена ]]>0,смарты_нал5[[#This Row],[Цена ]]/0.87,"") -> 223678.16 | G98: =IF(смарты_нал5[[#This Row],[Цена ]]<>"",смарты_нал5[[#This Row],[Цена ]]*смарты_нал5[[#This Row],[Заказ нал.]],"") -> 0 | H98: =IF(смарты_нал5[[#This Row],[Цена Б.Н.]]<>"",смарты_нал5[[#This Row],[Цена Б.Н.]]*смарты_нал5[[#This Row],[Заказ Б.Н.]],"") -> 0
A99: 10583-2 | B99: Huawei Nova 13 Pro 12+512GB NFC Green RUS | C99: 23300 | D99: =IF(смарты_нал5[[#This Row],[Цена ]]>0,смарты_нал5[[#This Row],[Цена ]]/0.87,"") -> 26781.609 | G99: =IF(смарты_нал5[[#This Row],[Цена ]]<>"",смарты_нал5[[#This Row],[Цена ]]*смарты_нал5[[#This Row],[Заказ нал.]],"") -> 0 | H99: =IF(смарты_нал5[[#This Row],[Цена Б.Н.]]<>"",смарты_нал5[[#This Row],[Цена Б.Н.]]*смарты_нал5[[#This Row],[Заказ Б.Н.]],"") -> 0
... A101: 10582-4 | B101: Huawei Nova 14 Pro 12+512GB NFC Pink RUS | C101: 28700 | D101: =IF(смарты_нал5[[#This Row],[Цена ]]>0,смарты_нал5[[#This Row],[Цена ]]/0.87,"") -> 32988.506 | G101: =IF(смарты_нал5[[#This Row],[Цена ]]<>"",смарты_нал5[[#This Row],[Цена ]]*смарты_нал5[[#This Row],[Заказ нал.]],"") -> 0 | H101: =IF(смарты_нал5[[#This Row],[Цена Б.Н.]]<>"",смарты_нал5[[#This Row],[Цена Б.Н.]]*смарты_нал5[[#This Row],[Заказ Б.Н.]],"") -> 0
A102: 10580-1 | B102: Huawei Nova 14i 8+128GB NFC Black RUS | C102: 10200 | D102: =IF(смарты_нал5[[#This Row],[Цена ]]>0,смарты_нал5[[#This Row],[Цена ]]/0.87,"") -> 11724.138 | G102: =IF(смарты_нал5[[#This Row],[Цена ]]<>"",смарты_нал5[[#This Row],[Цена ]]*смарты_нал5[[#This Row],[Заказ нал.]],"") -> 0 | H102: =IF(смарты_нал5[[#This Row],[Цена Б.Н.]]<>"",смарты_нал5[[#This Row],[Цена Б.Н.]]*смарты_нал5[[#This Row],[Заказ Б.Н.]],"") -> 0 | M102: 1
A103: 10580-2 | B103: Huawei Nova 14i 8+128GB NFC Blue RUS | C103: 10200 | D103: =IF(смарты_нал5[[#This Row],[Цена ]]>0,смарты_нал5[[#This Row],[Цена ]]/0.87,"") -> 11724.138 | G103: =IF(смарты_нал5[[#This Row],[Цена ]]<>"",смарты_нал5[[#This Row],[Цена ]]*смарты_нал5[[#This Row],[Заказ нал.]],"") -> 0 | H103: =IF(смарты_нал5[[#This Row],[Цена Б.Н.]]<>"",смарты_нал5[[#This Row],[Цена Б.Н.]]*смарты_нал5[[#This Row],[Заказ Б.Н.]],"") -> 0
A104: 10581-1 | B104: Huawei Nova 14i 8+256GB NFC Black RUS | C104: 11600 | D104: =IF(смарты_нал5[[#This Row],[Цена ]]>0,смарты_нал5[[#This Row],[Цена ]]/0.87,"") -> 13333.333 | G104: =IF(смарты_нал5[[#This Row],[Цена ]]<>"",смарты_нал5[[#This Row],[Цена ]]*смарты_нал5[[#This Row],[Заказ нал.]],"") -> 0 | H104: =IF(смарты_нал5[[#This Row],[Цена Б.Н.]]<>"",смарты_нал5[[#This Row],[Цена Б.Н.]]*смарты_нал5[[#This Row],[Заказ Б.Н.]],"") -> 0 | M104: 5
A105: 10581-2 | B105: Huawei Nova 14i 8+256GB NFC Blue RUS | C105: 11600 | D105: =IF(смарты_нал5[[#This Row],[Цена ]]>0,смарты_нал5[[#This Row],[Цена ]]/0.87,"") -> 13333.333 | G105: =IF(смарты_нал5[[#This Row],[Цена ]]<>"",смарты_нал5[[#This Row],[Цена ]]*смарты_нал5[[#This Row],[Заказ нал.]],"") -> 0 | H105: =IF(смарты_нал5[[#This Row],[Цена Б.Н.]]<>"",смарты_нал5[[#This Row],[Цена Б.Н.]]*смарты_нал5[[#This Row],[Заказ Б.Н.]],"") -> 0
A106: 10579-1 | B106: Huawei Nova Y63 6+128GB NFC Black RUS | C106: 6700 | D106: =IF(смарты_нал5[[#This Row],[Цена ]]>0,смарты_нал5[[#This Row],[Цена ]]/0.87,"") -> 7701.1494 | G106: =IF(смарты_нал5[[#This Row],[Цена ]]<>"",смарты_нал5[[#This Row],[Цена ]]*смарты_нал5[[#This Row],[Заказ нал.]],"") -> 0 | H106: =IF(смарты_нал5[[#This Row],[Цена Б.Н.]]<>"",смарты_нал5[[#This Row],[Цена Б.Н.]]*смарты_нал5[[#This Row],[Заказ Б.Н.]],"") -> 0 | M106: 3
A107: 10579-2 | B107: Huawei Nova Y63 6+128GB NFC Silver RUS | C107: 6700 | D107: =IF(смарты_нал5[[#This Row],[Цена ]]>0,смарты_нал5[[#This Row],[Цена ]]/0.87,"") -> 7701.1494 | G107: =IF(смарты_нал5[[#This Row],[Цена ]]<>"",смарты_нал5[[#This Row],[Цена ]]*смарты_нал5[[#This Row],[Заказ нал.]],"") -> 0 | H107: =IF(смарты_нал5[[#This Row],[Цена Б.Н.]]<>"",смарты_нал5[[#This Row],[Цена Б.Н.]]*смарты_нал5[[#This Row],[Заказ Б.Н.]],"") -> 0
A108: 10574-1 | B108: Huawei Nova Y73 8+128GB NFC Black RUS | C108: 8000 | D108: =IF(смарты_нал5[[#This Row],[Цена ]]>0,смарты_нал5[[#This Row],[Цена ]]/0.87,"") -> 9195.4023 | G108: =IF(смарты_нал5[[#This Row],[Цена ]]<>"",смарты_нал5[[#This Row],[Цена ]]*смарты_нал5[[#This Row],[Заказ нал.]],"") -> 0 | H108: =IF(смарты_нал5[[#This Row],[Цена Б.Н.]]<>"",смарты_нал5[[#This Row],[Цена Б.Н.]]*смарты_нал5[[#This Row],[Заказ Б.Н.]],"") -> 0 | M108: 16
A109: 10574-2 | B109: Huawei Nova Y73 8+128GB NFC Blue RUS | C109: 8000 | D109: =IF(смарты_нал5[[#This Row],[Цена ]]>0,смарты_нал5[[#This Row],[Цена ]]/0.87,"") -> 9195.4023 | G109: =IF(смарты_нал5[[#This Row],[Цена ]]<>"",смарты_нал5[[#This Row],[Цена ]]*смарты_нал5[[#This Row],[Заказ нал.]],"") -> 0 | H109: =IF(смарты_нал5[[#This Row],[Цена Б.Н.]]<>"",смарты_нал5[[#This Row],[Цена Б.Н.]]*смарты_нал5[[#This Row],[Заказ Б.Н.]],"") -> 0 | M109: 8
A110: 10575-1 | B110: Huawei Nova Y73 8+256GB NFC Black RUS | C110: 8700 | D110: =IF(смарты_нал5[[#This Row],[Цена ]]>0,смарты_нал5[[#This Row],[Цена ]]/0.87,"") -> 10000 | G110: =IF(смарты_нал5[[#This Row],[Цена ]]<>"",смарты_нал5[[#This Row],[Цена ]]*смарты_нал5[[#This Row],[Заказ нал.]],"") -> 0 | H110: =IF(смарты_нал5[[#This Row],[Цена Б.Н.]]<>"",смарты_нал5[[#This Row],[Цена Б.Н.]]*смарты_нал5[[#This Row],[Заказ Б.Н.]],"") -> 0 | M110: 5
A111: 10575-2 | B111: Huawei Nova Y73 8+256GB NFC Blue RUS | C111: 8700 | D111: =IF(смарты_нал5[[#This Row],[Цена ]]>0,смарты_нал5[[#This Row],[Цена ]]/0.87,"") -> 10000 | G111: =IF(смарты_нал5[[#This Row],[Цена ]]<>"",смарты_нал5[[#This Row],[Цена ]]*смарты_нал5[[#This Row],[Заказ нал.]],"") -> 0 | H111: =IF(смарты_нал5[[#This Row],[Цена Б.Н.]]<>"",смарты_нал5[[#This Row],[Цена Б.Н.]]*смарты_нал5[[#This Row],[Заказ Б.Н.]],"") -> 0 | M111: 1
A112: 10577-1 | B112: Huawei Pura 80 12+256GB Black RUS | C112: 36800 | D112: =IF(смарты_нал5[[#This Row],[Цена ]]>0,смарты_нал5[[#This Row],[Цена ]]/0.87,"") -> 42298.851 | G112: =IF(смарты_нал5[[#This Row],[Цена ]]<>"",смарты_нал5[[#This Row],[Цена ]]*смарты_нал5[[#This Row],[Заказ нал.]],"") -> 0 | H112: =IF(смарты_нал5[[#This Row],[Цена Б.Н.]]<>"",смарты_нал5[[#This Row],[Цена Б.Н.]]*смарты_нал5[[#This Row],[Заказ Б.Н.]],"") -> 0
A113: 10577-3 | B113: Huawei Pura 80 12+256GB Gold RUS | C113: 36800 | D113: =IF(смарты_нал5[[#This Row],[Цена ]]>0,смарты_нал5[[#This Row],[Цена ]]/0.87,"") -> 42298.851 | G113: =IF(смарты_нал5[[#This Row],[Цена ]]<>"",смарты_нал5[[#This Row],[Цена ]]*смарты_нал5[[#This Row],[Заказ нал.]],"") -> 0 | H113: =IF(смарты_нал5[[#This Row],[Цена Б.Н.]]<>"",смарты_нал5[[#This Row],[Цена Б.Н.]]*смарты_нал5[[#This Row],[Заказ Б.Н.]],"") -> 0
...

Sheet Смартфоны(безнал с НДС)
A1: Назад в оглавление
A2: Смартфоны (б/н с НДС 22%)
A3: Товар в наличии на складе | C3: итого | D3: =SUM(смарты_бн_бндс[Заказ]) -> 0 | E3: =SUM(смарты_бн_бндс[Сумма заказа]) -> 0
A4: Наименование | B4: Количество | C4: Цена | D4: Заказ | E4: Сумма заказа
E5: =смарты_бн_бндс[[#This Row],[Цена]]*смарты_бн_бндс[[#This Row],[Заказ]] -> 0
E6: =смарты_бн_бндс[[#This Row],[Цена]]*смарты_бн_бндс[[#This Row],[Заказ]] -> 0
E7: =смарты_бн_бндс[[#This Row],[Цена]]*смарты_бн_бндс[[#This Row],[Заказ]] -> 0
E8: =смарты_бн_бндс[[#This Row],[Цена]]*смарты_бн_бндс[[#This Row],[Заказ]] -> 0
E9: =смарты_бн_бндс[[#This Row],[Цена]]*смарты_бн_бндс[[#This Row],[Заказ]] -> 0
E10: =смарты_бн_бндс[[#This Row],[Цена]]*смарты_бн_бндс[[#This Row],[Заказ]] -> 0
E11: =смарты_бн_бндс[[#This Row],[Цена]]*смарты_бн_бндс[[#This Row],[Заказ]] -> 0
E12: =смарты_бн_бндс[[#This Row],[Цена]]*смарты_бн_бндс[[#This Row],[Заказ]] -> 0
E13: =смарты_бн_бндс[[#This Row],[Цена]]*смарты_бн_бндс[[#This Row],[Заказ]] -> 0
E14: =смарты_бн_бндс[[#This Row],[Цена]]*смарты_бн_бндс[[#This Row],[Заказ]] -> 0
E15: =смарты_бн_бндс[[#This Row],[Цена]]*смарты_бн_бндс[[#This Row],[Заказ]] -> 0
E16: =смарты_бн_бндс[[#This Row],[Цена]]*смарты_бн_бндс[[#This Row],[Заказ]] -> 0
... E50: =смарты_бн_бндс[[#This Row],[Цена]]*смарты_бн_бндс[[#This Row],[Заказ]] -> 0
A51: Итог | D51: =SUBTOTAL(109,смарты_бн_бндс[Заказ]) -> 0 | E51: =SUBTOTAL(109,смарты_бн_бндс[Сумма заказа]) -> 0

Sheet Apple(iPhone, Watch)
A1: Назад в оглавление
A2: Apple (наличные). Предоплата 100% | D2: итого | E2: =SUM(Таблица512[Заказ]) -> 0 | F2: =SUM(Таблица512[Сумма заказа]) -> 0
A3: артикул | B3: Наименование | C3: страна | D3: Цена | E3: Заказ | F3: Сумма заказа
B4: Apple iPhone 11: | F4: =Таблица512[[#This Row],[Цена]]*Таблица512[[#This Row],[Заказ]] -> 0
A5: 10270-1 | B5: Apple iPhone 11 64GB Black 1sim | C5: США | D5: 28000 | F5: =Таблица512[[#This Row],[Цена]]*Таблица512[[#This Row],[Заказ]] -> 0
B6: Apple iPhone 12: | F6: =Таблица512[[#This Row],[Цена]]*Таблица512[[#This Row],[Заказ]] -> 0
A7: 10286-2 | B7: Apple iPhone 12 64GB Black 1sim | C7: США | D7: 30500 | F7: =Таблица512[[#This Row],[Цена]]*Таблица512[[#This Row],[Заказ]] -> 0
B8: Apple iPhone 13: | F8: =Таблица512[[#This Row],[Цена]]*Таблица512[[#This Row],[Заказ]] -> 0
A9: 10298-1 | B9: Apple iPhone 13 128GB Midnight 1sim | C9: Индия | D9: 38200 | F9: =Таблица512[[#This Row],[Цена]]*Таблица512[[#This Row],[Заказ]] -> 0
A10: 10299-1 | B10: Apple iPhone 13 256GB Midnight 1sim | C10: США | D10: 45800 | F10: =Таблица512[[#This Row],[Цена]]*Таблица512[[#This Row],[Заказ]] -> 0
A11: 10299-2 | B11: Apple iPhone 13 256GB Blue 1sim | C11: США | D11: 45800 | F11: =Таблица512[[#This Row],[Цена]]*Таблица512[[#This Row],[Заказ]] -> 0
A12: 10299-4 | B12: Apple iPhone 13 256GB Pink 1sim | C12: США | D12: 46300 | F12: =Таблица512[[#This Row],[Цена]]*Таблица512[[#This Row],[Заказ]] -> 0
A13: 10300-3 | B13: Apple iPhone 13 512GB Starlight 1sim | C13: США | D13: 50300 | F13: =Таблица512[[#This Row],[Цена]]*Таблица512[[#This Row],[Заказ]] -> 0
A14: 10300-5 | B14: Apple iPhone 13 512GB Red 1sim | C14: США | D14: 49500 | F14: =Таблица512[[#This Row],[Цена]]*Таблица512[[#This Row],[Заказ]] -> 0
B15: Apple iPhone 14: | F15: =Таблица512[[#This Row],[Цена]]*Таблица512[[#This Row],[Заказ]] -> 0
A16: 10312-3 | B16: Apple iPhone 14 128GB Starlight 1sim | C16: Индия | D16: 41700 | F16: =Таблица512[[#This Row],[Цена]]*Таблица512[[#This Row],[Заказ]] -> 0
A17: 10312-2 | B17: Apple iPhone 14 128GB Blue 1sim | C17: Индия | D17: 41300 | F17: =Таблица512[[#This Row],[Цена]]*Таблица512[[#This Row],[Заказ]] -> 0
A18: 10312-4 | B18: Apple iPhone 14 128GB Purple 1sim | C18: Индия | D18: 43000 | F18: =Таблица512[[#This Row],[Цена]]*Таблица512[[#This Row],[Заказ]] -> 0
A19: 10312-6 | B19: Apple iPhone 14 128GB Yellow 1sim | C19: Индия | D19: 39000 | F19: =Таблица512[[#This Row],[Цена]]*Таблица512[[#This Row],[Заказ]] -> 0
A20: 10313-1 | B20: Apple iPhone 14 256GB Midnight 1sim | C20: Индия | D20: 44200 | F20: =Таблица512[[#This Row],[Цена]]*Таблица512[[#This Row],[Заказ]] -> 0
A21: 10313-3 | B21: Apple iPhone 14 256GB Starlight 1sim | C21: Индия | D21: 47000 | F21: =Таблица512[[#This Row],[Цена]]*Таблица512[[#This Row],[Заказ]] -> 0
A22: 10313-2 | B22: Apple iPhone 14 256GB Blue 1sim | C22: Индия | D22: 48800 | F22: =Таблица512[[#This Row],[Цена]]*Таблица512[[#This Row],[Заказ]] -> 0
B23: Apple iPhone 14 512GB Blue eSIM | C23: США | D23: 42700 | F23: =Таблица512[[#This Row],[Цена]]*Таблица512[[#This Row],[Заказ]] -> 0
B24: Apple iPhone 14 512GB Midnight eSIM | C24: США | D24: 43100 | F24: =Таблица512[[#This Row],[Цена]]*Таблица512[[#This Row],[Заказ]] -> 0
B25: Apple iPhone 14 512GB Midnight 1sim | C25: Индия | D25: 47000 | F25: =Таблица512[[#This Row],[Цена]]*Таблица512[[#This Row],[Заказ]] -> 0
A26: 10314-3 | B26: Apple iPhone 14 512GB Starlight 1sim | C26: Индия | D26: 49600 | F26: =Таблица512[[#This Row],[Цена]]*Таблица512[[#This Row],[Заказ]] -> 0
A27: 10314-2 | B27: Apple iPhone 14 512GB Blue 1sim | C27: Индия | D27: 49600 | F27: =Таблица512[[#This Row],[Цена]]*Таблица512[[#This Row],[Заказ]] -> 0
B28: Apple iPhone 14 512GB Purple 1sim | C28: Индия | D28: 49700 | F28: =Таблица512[[#This Row],[Цена]]*Таблица512[[#This Row],[Заказ]] -> 0
A29: 10314-5 | B29: Apple iPhone 14 512GB Red 1sim | C29: Индия | D29: 46800 | F29: =Таблица512[[#This Row],[Цена]]*Таблица512[[#This Row],[Заказ]] -> 0
B30: Apple iPhone 14 Plus: | F30: =Таблица512[[#This Row],[Цена]]*Таблица512[[#This Row],[Заказ]] -> 0
B31: Apple iPhone 14 Plus 128GB Yellow 2sim | C31: Гонконг | D31: 42400 | F31: =Таблица512[[#This Row],[Цена]]*Таблица512[[#This Row],[Заказ]] -> 0
A32: 10323-6 | B32: Apple iPhone 14 Plus 128GB Yellow 1sim | C32: Индия | D32: 42500 | F32: =Таблица512[[#This Row],[Цена]]*Таблица512[[#This Row],[Заказ]] -> 0
B33: Apple iPhone 14 Plus 256GB Blue eSIM | C33: США | D33: 44400 | F33: =Таблица512[[#This Row],[Цена]]*Таблица512[[#This Row],[Заказ]] -> 0
B34: Apple iPhone 14 Plus 256GB Purple eSIM | C34: США | D34: 44400 | F34: =Таблица512[[#This Row],[Цена]]*Таблица512[[#This Row],[Заказ]] -> 0
B35: Apple iPhone 14 Plus 256GB Red eSIM | C35: США | D35: 43500 | F35: =Таблица512[[#This Row],[Цена]]*Таблица512[[#This Row],[Заказ]] -> 0
B36: Apple iPhone 14 Plus 512GB Yellow eSIM | C36: США | D36: 46800 | F36: =Таблица512[[#This Row],[Цена]]*Таблица512[[#This Row],[Заказ]] -> 0
B37: Apple iPhone 14 Plus 512GB Starlight 1sim | C37: Индия | D37: 50000 | F37: =Таблица512[[#This Row],[Цена]]*Таблица512[[#This Row],[Заказ]] -> 0
B38: Apple iPhone 14 Plus 512GB Blue 1sim | C38: Индия | D38: 50300 | F38: =Таблица512[[#This Row],[Цена]]*Таблица512[[#This Row],[Заказ]] -> 0
B39: Apple iPhone 14 Plus 512GB Purple 1sim | C39: Индия | D39: 50000 | F39: =Таблица512[[#This Row],[Цена]]*Таблица512[[#This Row],[Заказ]] -> 0
B40: Apple iPhone 14 Pro Max: | F40: =Таблица512[[#This Row],[Цена]]*Таблица512[[#This Row],[Заказ]] -> 0
B41: Apple iPhone 14 Pro Max 128GB Deep Purple 1sim | C41: ОАЭ | D41: 69800 | F41: =Таблица512[[#This Row],[Цена]]*Таблица512[[#This Row],[Заказ]] -> 0
B42: Apple iPhone 14 Pro Max 128GB Deep Purple 1sim | C42: ЕС | D42: 69800 | F42: =Таблица512[[#This Row],[Цена]]*Таблица512[[#This Row],[Заказ]] -> 0
B43: Apple iPhone 15: | F43: =Таблица512[[#This Row],[Цена]]*Таблица512[[#This Row],[Заказ]] -> 0
B44: Apple iPhone 15 128GB Black eSIM | C44: США | D44: 44300 | F44: =Таблица512[[#This Row],[Цена]]*Таблица512[[#This Row],[Заказ]] -> 0
A45: 10326-1 | B45: Apple iPhone 15 128GB Black 1sim | C45: Индия | D45: 44800 | F45: =Таблица512[[#This Row],[Цена]]*Таблица512[[#This Row],[Заказ]] -> 0
A46: 10326-2 | B46: Apple iPhone 15 128GB Blue 1sim | C46: Индия | D46: 44800 | F46: =Таблица512[[#This Row],[Цена]]*Таблица512[[#This Row],[Заказ]] -> 0
A47: 10326-5 | B47: Apple iPhone 15 128GB Pink 1sim | C47: Индия | D47: 49300 | F47: =Таблица512[[#This Row],[Цена]]*Таблица512[[#This Row],[Заказ]] -> 0
A48: 10326-4 | B48: Apple iPhone 15 128GB Yellow 1sim | C48: Индия | D48: 48300 | F48: =Таблица512[[#This Row],[Цена]]*Таблица512[[#This Row],[Заказ]] -> 0
A49: 10327-1 | B49: Apple iPhone 15 256GB Black 1sim | C49: Индия | D49: 52400 | F49: =Таблица512[[#This Row],[Цена]]*Таблица512[[#This Row],[Заказ]] -> 0
A50: 10327-2 | B50: Apple iPhone 15 256GB Blue 1sim | C50: Индия | D50: 52300 | F50: =Таблица512[[#This Row],[Цена]]*Таблица512[[#This Row],[Заказ]] -> 0
A51: 10327-4 | B51: Apple iPhone 15 256GB Yellow 1sim | C51: Индия | D51: 51500 | F51: =Таблица512[[#This Row],[Цена]]*Таблица512[[#This Row],[Заказ]] -> 0
B52: Apple iPhone 15 512GB Pink eSIM | C52: США | D52: 56800 | F52: =Таблица512[[#This Row],[Цена]]*Таблица512[[#This Row],[Заказ]] -> 0
B53: Apple iPhone 15 512GB Blue eSIM | C53: США | D53: 52500 | F53: =Таблица512[[#This Row],[Цена]]*Таблица512[[#This Row],[Заказ]] -> 0
B54: Apple iPhone 15 512GB Green eSIM | C54: США | D54: 52000 | F54: =Таблица512[[#This Row],[Цена]]*Таблица512[[#This Row],[Заказ]] -> 0
B55: Apple iPhone 15 512GB Yellow eSIM | C55: США | D55: 52000 | F55: =Таблица512[[#This Row],[Цена]]*Таблица512[[#This Row],[Заказ]] -> 0
B56: Apple iPhone 15 512GB Blue 1sim | C56: Индия | D56: 65300 | F56: =Таблица512[[#This Row],[Цена]]*Таблица512[[#This Row],[Заказ]] -> 0
B57: Apple iPhone 15 512GB Green 1sim | C57: Индия | D57: 61000 | F57: =Таблица512[[#This Row],[Цена]]*Таблица512[[#This Row],[Заказ]] -> 0
B58: Apple iPhone 15 512GB Yellow 1sim | C58: ОАЭ | D58: 57600 | F58: =Таблица512[[#This Row],[Цена]]*Таблица512[[#This Row],[Заказ]] -> 0
B59: Apple iPhone 15 512GB Yellow 1sim | C59: ЕС | D59: 57600 | F59: =Таблица512[[#This Row],[Цена]]*Таблица512[[#This Row],[Заказ]] -> 0
B60: Apple iPhone 15 Plus: | F60: =Таблица512[[#This Row],[Цена]]*Таблица512[[#This Row],[Заказ]] -> 0
A61: 10329-2 | B61: Apple iPhone 15 Plus 128GB Blue 1sim | C61: Индия | D61: 47300 | F61: =Таблица512[[#This Row],[Цена]]*Таблица512[[#This Row],[Заказ]] -> 0
A62: 10329-3 | B62: Apple iPhone 15 Plus 128GB Green 1sim | C62: Индия | D62: 49500 | F62: =Таблица512[[#This Row],[Цена]]*Таблица512[[#This Row],[Заказ]] -> 0
A63: 10329-5 | B63: Apple iPhone 15 Plus 128GB Pink 1sim | C63: Индия | D63: 47300 | F63: =Таблица512[[#This Row],[Цена]]*Таблица512[[#This Row],[Заказ]] -> 0
B64: Apple iPhone 15 Plus 128GB Yellow 1sim | C64: Индия | D64: 48800 | F64: =Таблица512[[#This Row],[Цена]]*Таблица512[[#This Row],[Заказ]] -> 0
B65: Apple iPhone 15 Plus 512GB Black 1sim | C65: Индия | D65: 65300 | F65: =Таблица512[[#This Row],[Цена]]*Таблица512[[#This Row],[Заказ]] -> 0
A66: 10331-2 | B66: Apple iPhone 15 Plus 512GB Blue 1sim | C66: Индия | D66: 57800 | F66: =Таблица512[[#This Row],[Цена]]*Таблица512[[#This Row],[Заказ]] -> 0
A67: 10331-3 | B67: Apple iPhone 15 Plus 512GB Green 1sim | C67: Индия | D67: 55600 | F67: =Таблица512[[#This Row],[Цена]]*Таблица512[[#This Row],[Заказ]] -> 0
B68: Apple iPhone 15 Plus 512GB Pink 1sim | C68: Индия | D68: 57800 | F68: =Таблица512[[#This Row],[Цена]]*Таблица512[[#This Row],[Заказ]] -> 0
B69: Apple iPhone 15 Plus 512GB Yellow 1sim | C69: Япония | D69: 51000 | F69: =Таблица512[[#This Row],[Цена]]*Таблица512[[#This Row],[Заказ]] -> 0
B70: Apple iPhone 15 Pro: | F70: =Таблица512[[#This Row],[Цена]]*Таблица512[[#This Row],[Заказ]] -> 0
B71: Apple iPhone 15 Pro 128GB Natural eSIM | C71: США | D71: 65300 | F71: =Таблица512[[#This Row],[Цена]]*Таблица512[[#This Row],[Заказ]] -> 0
B72: Apple iPhone 15 Pro 128GB White eSIM | C72: США | D72: 62600 | F72: =Таблица512[[#This Row],[Цена]]*Таблица512[[#This Row],[Заказ]] -> 0
B73: Apple iPhone 15 Pro 128GB Blue 2Sim | C73: Китай | D73: 66300 | F73: =Таблица512[[#This Row],[Цена]]*Таблица512[[#This Row],[Заказ]] -> 0
A74: 10332-2 | B74: Apple iPhone 15 Pro 128GB Blue 1sim | C74: ОАЭ | D74: 68000 | F74: =Таблица512[[#This Row],[Цена]]*Таблица512[[#This Row],[Заказ]] -> 0
A75: 10332-2 | B75: Apple iPhone 15 Pro 128GB Blue 1sim | C75: ЕС | D75: 68000 | F75: =Таблица512[[#This Row],[Цена]]*Таблица512[[#This Row],[Заказ]] -> 0
A76: 10332-4 | B76: Apple iPhone 15 Pro 128GB White 1sim | C76: ОАЭ | D76: 69700 | F76: =Таблица512[[#This Row],[Цена]]*Таблица512[[#This Row],[Заказ]] -> 0
A77: 10332-4 | B77: Apple iPhone 15 Pro 128GB White 1sim | C77: ЕС | D77: 69700 | F77: =Таблица512[[#This Row],[Цена]]*Таблица512[[#This Row],[Заказ]] -> 0
A78: 10334-3 | B78: Apple iPhone 15 Pro 256GB Natural 1sim | C78: Япония | D78: 89800 | F78: =Таблица512[[#This Row],[Цена]]*Таблица512[[#This Row],[Заказ]] -> 0
B79: Apple iPhone 15 Pro Max: | F79: =Таблица512[[#This Row],[Цена]]*Таблица512[[#This Row],[Заказ]] -> 0
B80: Apple iPhone 15 Pro Max 256GB Black 2Sim | C80: Китай | D80: 80300 | F80: =Таблица512[[#This Row],[Цена]]*Таблица512[[#This Row],[Заказ]] -> 0
B81: Apple iPhone 16e: | F81: =Таблица512[[#This Row],[Цена]]*Таблица512[[#This Row],[Заказ]] -> 0
A82: 10390-1 | B82: Apple iPhone 16e 128GB Black 1sim | C82: Индия | D82: 42300 | F82: =Таблица512[[#This Row],[Цена]]*Таблица512[[#This Row],[Заказ]] -> 0
A83: 10390-2 | B83: Apple iPhone 16e 128GB White 1sim | C83: Индия | D83: 42300 | F83: =Таблица512[[#This Row],[Цена]]*Таблица512[[#This Row],[Заказ]] -> 0
A84: 10391-2 | B84: Apple iPhone 16e 256GB White 1sim | C84: Индия | D84: 50300 | F84: =Таблица512[[#This Row],[Цена]]*Таблица512[[#This Row],[Заказ]] -> 0
B85: Apple iPhone 16: | F85: =Таблица512[[#This Row],[Цена]]*Таблица512[[#This Row],[Заказ]] -> 0
B86: Apple iPhone 16 128GB Black eSIM | C86: США | D86: 48300 | F86: =Таблица512[[#This Row],[Цена]]*Таблица512[[#This Row],[Заказ]] -> 0
A87: 10354-1 | B87: Apple iPhone 16 128GB Black 1sim | C87: Индия | D87: 50100 | F87: =Таблица512[[#This Row],[Цена]]*Таблица512[[#This Row],[Заказ]] -> 0
A88: 10354-5 | B88: Apple iPhone 16 128GB Pink 1sim | C88: Индия | D88: 50300 | F88: =Таблица512[[#This Row],[Цена]]*Таблица512[[#This Row],[Заказ]] -> 0
A89: 10354-2 | B89: Apple iPhone 16 128GB White 1sim | C89: Индия | D89: 50200 | F89: =Таблица512[[#This Row],[Цена]]*Таблица512[[#This Row],[Заказ]] -> 0
A90: 10354-4 | B90: Apple iPhone 16 128GB Teal 1sim | C90: Индия | D90: 49800 | F90: =Таблица512[[#This Row],[Цена]]*Таблица512[[#This Row],[Заказ]] -> 0
A91: 10354-3 | B91: Apple iPhone 16 128GB Ultramarine 1sim | C91: Индия | D91: 49800 | F91: =Таблица512[[#This Row],[Цена]]*Таблица512[[#This Row],[Заказ]] -> 0
B92: Apple iPhone 16 256GB Black eSIM | C92: США | D92: 60300 | F92: =Таблица512[[#This Row],[Цена]]*Таблица512[[#This Row],[Заказ]] -> 0
A93: 10355-1 | B93: Apple iPhone 16 256GB Black 1sim | C93: Индия | D93: 63800 | F93: =Таблица512[[#This Row],[Цена]]*Таблица512[[#This Row],[Заказ]] -> 0
A94: 10355-5 | B94: Apple iPhone 16 256GB Pink 1sim | C94: Индия | D94: 56600 | F94: =Таблица512[[#This Row],[Цена]]*Таблица512[[#This Row],[Заказ]] -> 0
A95: 10355-2 | B95: Apple iPhone 16 256GB White 1sim | C95: Индия | D95: 63800 | F95: =Таблица512[[#This Row],[Цена]]*Таблица512[[#This Row],[Заказ]] -> 0
A96: 10355-3 | B96: Apple iPhone 16 256GB Ultramarine 1sim | C96: Индия | D96: 62800 | F96: =Таблица512[[#This Row],[Цена]]*Таблица512[[#This Row],[Заказ]] -> 0
A97: 10356-1 | B97: Apple iPhone 16 512GB Black 1sim | C97: Индия | D97: 79300 | F97: =Таблица512[[#This Row],[Цена]]*Таблица512[[#This Row],[Заказ]] -> 0
A98: 10356-4 | B98: Apple iPhone 16 512GB Teal 1sim | C98: Индия | D98: 71700 | F98: =Таблица512[[#This Row],[Цена]]*Таблица512[[#This Row],[Заказ]] -> 0
B99: Apple iPhone 16 512GB White 1sim | C99: Индия | D99: 75300 | F99: =Таблица512[[#This Row],[Цена]]*Таблица512[[#This Row],[Заказ]] -> 0
B100: Apple iPhone 16 512GB Ultramarine 1sim | C100: Индия | D100: 77300 | F100: =Таблица512[[#This Row],[Цена]]*Таблица512[[#This Row],[Заказ]] -> 0
...

Sheet Apple (iPad, Macbook)
A1: Назад в оглавление
A2: Apple (наличные). Срок поставки на наш склад: 1 день. Предоплата 100% | C2: итого | D2: =SUM(Таблица59[Заказ]) -> 0 | E2: =SUM(Таблица59[Сумма заказа]) -> 0
A3: Наименование | B3: Особенности | C3: Цена | D3: Заказ | E3: Сумма заказа
A4: iPad Air M4 (2026) | E4: =Таблица59[[#This Row],[Цена]]*Таблица59[[#This Row],[Заказ]] -> 0
A5: Pencil USB-C | C5: 7000 | E5: =Таблица59[[#This Row],[Цена]]*Таблица59[[#This Row],[Заказ]] -> 0
A6: Apple Pencil 2 | C6: 7300 | E6: =Таблица59[[#This Row],[Цена]]*Таблица59[[#This Row],[Заказ]] -> 0
A7: Apple Pencil 2 б/у | C7: 5500 | E7: =Таблица59[[#This Row],[Цена]]*Таблица59[[#This Row],[Заказ]] -> 0
A8: Apple Pencil Pro | C8: 9500 | E8: =Таблица59[[#This Row],[Цена]]*Таблица59[[#This Row],[Заказ]] -> 0
A9: Magic Keyboard iPad Air 11 М2/M3/М4 2024 -2026 Белый (MDFV4) | C9: 30500 | E9: =Таблица59[[#This Row],[Цена]]*Таблица59[[#This Row],[Заказ]] -> 0
A10: Magic Keyboard iPad Air 11 М2/M3/М4 2024 -2026 Черный (MGYX4) | C10: 30500 | E10: =Таблица59[[#This Row],[Цена]]*Таблица59[[#This Row],[Заказ]] -> 0
A11: iPad Air 11 (M4) 2026 128 Wi-Fi Grey | B11: Гонконг, Grey | C11: 45500 | E11: =Таблица59[[#This Row],[Цена]]*Таблица59[[#This Row],[Заказ]] -> 0
A12: iPad Air 11 (M4) 2026 128 Wi-Fi Starlight | B12: Гонконг, Starlight | C12: 45000 | E12: =Таблица59[[#This Row],[Цена]]*Таблица59[[#This Row],[Заказ]] -> 0
A13: iPad Air 11 (M4) 2026 128 Wi-Fi Blue | B13: Гонконг, Blue | C13: 45000 | E13: =Таблица59[[#This Row],[Цена]]*Таблица59[[#This Row],[Заказ]] -> 0
A14: iPad Air 11 (M4) 2026 128 Wi-Fi Purple | B14: Гонконг, Purple | C14: 44500 | E14: =Таблица59[[#This Row],[Цена]]*Таблица59[[#This Row],[Заказ]] -> 0
A15: iPad Air 11 (M4) 2026 128 LTE Grey | B15: Гонконг, Grey | C15: 62900 | E15: =Таблица59[[#This Row],[Цена]]*Таблица59[[#This Row],[Заказ]] -> 0
A16: iPad Air 11 (M4) 2026 128 LTE Starlight | B16: Гонконг, Starlight | C16: 62900 | E16: =Таблица59[[#This Row],[Цена]]*Таблица59[[#This Row],[Заказ]] -> 0
A17: iPad Air 11 (M4) 2026 128 LTE Blue | B17: Гонконг, Blue | C17: 61500 | E17: =Таблица59[[#This Row],[Цена]]*Таблица59[[#This Row],[Заказ]] -> 0
A18: iPad Air 11 (M4) 2026 128 LTE Purple | B18: Гонконг, Purple | C18: 61500 | E18: =Таблица59[[#This Row],[Цена]]*Таблица59[[#This Row],[Заказ]] -> 0
A19: iPad Air 11 (M4) 2026 256 Wi-Fi Grey | B19: Гонконг, Grey | C19: 56000 | E19: =Таблица59[[#This Row],[Цена]]*Таблица59[[#This Row],[Заказ]] -> 0
A20: iPad Air 11 (M4) 2026 256 Wi-Fi Blue | B20: Гонконг, Blue | C20: 54900 | E20: =Таблица59[[#This Row],[Цена]]*Таблица59[[#This Row],[Заказ]] -> 0
A21: iPad Air 11 (M4) 2026 256 Wi-Fi Purple | B21: Гонконг, Purple | C21: 56000 | E21: =Таблица59[[#This Row],[Цена]]*Таблица59[[#This Row],[Заказ]] -> 0
A22: iPad Air 11 (M4) 2026 256 Wi-Fi Starlight | B22: Гонконг, Starlight | C22: 57000 | E22: =Таблица59[[#This Row],[Цена]]*Таблица59[[#This Row],[Заказ]] -> 0
... A66: iPad Air 13 (M4) 2026 1TB LTE Purple | B66: США, Purple | C66: 137000 | E66: =Таблица59[[#This Row],[Цена]]*Таблица59[[#This Row],[Заказ]] -> 0
A67: iPad Air M3 (2025) | E67: =Таблица59[[#This Row],[Цена]]*Таблица59[[#This Row],[Заказ]] -> 0
A68: iPad Air 11 M3 (2025) 128 LTE Gray | B68: США, Gray | C68: 59000 | E68: =Таблица59[[#This Row],[Цена]]*Таблица59[[#This Row],[Заказ]] -> 0
A69: iPad Air 11 M3 (2025) 256 LTE Grey | B69: Grey | C69: 71500 | E69: =Таблица59[[#This Row],[Цена]]*Таблица59[[#This Row],[Заказ]] -> 0
A70: iPad Air 11 M3 (2025) 256 LTE Starlight | B70: Starlight | C70: 71500 | E70: =Таблица59[[#This Row],[Цена]]*Таблица59[[#This Row],[Заказ]] -> 0
A71: iPad Air 11 M3 (2025) 256 LTE Blue | B71: Blue | C71: 71500 | E71: =Таблица59[[#This Row],[Цена]]*Таблица59[[#This Row],[Заказ]] -> 0
A72: iPad Air 13 128GB Purple M3 LTE | B72: Purple | C72: 67000 | E72: =Таблица59[[#This Row],[Цена]]*Таблица59[[#This Row],[Заказ]] -> 0
A73: iPad Air 13 128GB Starlight M3 LTE | B73: Starlight | C73: 68500 | E73: =Таблица59[[#This Row],[Цена]]*Таблица59[[#This Row],[Заказ]] -> 0
A74: iPad Air 13 128GB Blue M3 LTE | B74: Blue | C74: 67000 | E74: =Таблица59[[#This Row],[Цена]]*Таблица59[[#This Row],[Заказ]] -> 0
A75: iPad Air M2 (2024) | E75: =Таблица59[[#This Row],[Цена]]*Таблица59[[#This Row],[Заказ]] -> 0
A76: iPad Air 11 (M2) 2024 128 LTE Grey | B76: США, Grey | C76: 56000 | E76: =Таблица59[[#This Row],[Цена]]*Таблица59[[#This Row],[Заказ]] -> 0
A77: iPad Air 11 (M2) 2024 128 LTE Starlight | B77: США, Starlight | C77: 56000 | E77: =Таблица59[[#This Row],[Цена]]*Таблица59[[#This Row],[Заказ]] -> 0
A78: iPad Air 11 (M2) 2024 128 LTE Blue | B78: США, Blue | C78: 56000 | E78: =Таблица59[[#This Row],[Цена]]*Таблица59[[#This Row],[Заказ]] -> 0
A79: iPad Air 11 (M2) 2024 128 LTE Purple | B79: США, Purple | C79: 56000 | E79: =Таблица59[[#This Row],[Цена]]*Таблица59[[#This Row],[Заказ]] -> 0
A80: iPad Air 11 (M2) 2024 256 LTE Blue | B80: США, Blue | C80: 60000 | E80: =Таблица59[[#This Row],[Цена]]*Таблица59[[#This Row],[Заказ]] -> 0
A81: iPad Air 11 (M2) 2024 512 Wi-Fi Starlight | B81: Мексика, ОАЭ, Starlight | C81: 60000 | E81: =Таблица59[[#This Row],[Цена]]*Таблица59[[#This Row],[Заказ]] -> 0
A82: iPad Air 11 (M2) 2024 512 LTE Grey | B82: США, Grey | C82: 65000 | E82: =Таблица59[[#This Row],[Цена]]*Таблица59[[#This Row],[Заказ]] -> 0
A83: iPad Air 11 (M2) 2024 512 LTE Starlight | B83: США, Starlight | C83: 65000 | E83: =Таблица59[[#This Row],[Цена]]*Таблица59[[#This Row],[Заказ]] -> 0
A84: iPad Air 11 (M2) 2024 512 LTE Blue | B84: США, Blue | C84: 65000 | E84: =Таблица59[[#This Row],[Цена]]*Таблица59[[#This Row],[Заказ]] -> 0
A85: iPad Air 11 (M2) 2024 512 LTE Purple | B85: США, Purple | C85: 65000 | E85: =Таблица59[[#This Row],[Цена]]*Таблица59[[#This Row],[Заказ]] -> 0
A86: iPad Air 11 (M2) 2024 1Tb LTE Grey | B86: США, Grey | C86: 71000 | E86: =Таблица59[[#This Row],[Цена]]*Таблица59[[#This Row],[Заказ]] -> 0
A87: iPad Air 11 (M2) 2024 1Tb LTE Starlight | B87: США, Starlight | C87: 71000 | E87: =Таблица59[[#This Row],[Цена]]*Таблица59[[#This Row],[Заказ]] -> 0
... A123: iPad Air 13 (M2) 2024 1Tb LTE Blue | B123: Blue | C123: 85500 | E123: =Таблица59[[#This Row],[Цена]]*Таблица59[[#This Row],[Заказ]] -> 0
A124: iPad Pro M5/M4 | E124: =Таблица59[[#This Row],[Цена]]*Таблица59[[#This Row],[Заказ]] -> 0
A125: Magic Keyboard Black iPad Pro 11 | B125: США, Black | C125: 32000 | E125: =Таблица59[[#This Row],[Цена]]*Таблица59[[#This Row],[Заказ]] -> 0
A126: Magic Keyboard White iPad Pro 11 | B126: США, White | C126: 27000 | E126: =Таблица59[[#This Row],[Цена]]*Таблица59[[#This Row],[Заказ]] -> 0
A127: Magic Keyboard Black iPad Pro 13 | B127: Black | C127: 33500 | E127: =Таблица59[[#This Row],[Цена]]*Таблица59[[#This Row],[Заказ]] -> 0
A128: Magic Keyboard White iPad Pro 13 | B128: США, White | C128: 34500 | E128: =Таблица59[[#This Row],[Цена]]*Таблица59[[#This Row],[Заказ]] -> 0
A129: iPro 11 M5 256 Black Wi-Fi | B129: США, Black | C129: 74500 | E129: =Таблица59[[#This Row],[Цена]]*Таблица59[[#This Row],[Заказ]] -> 0
A130: iPro 11 M5 256 Silver Wi-Fi | B130: США, Silver | C130: 74500 | E130: =Таблица59[[#This Row],[Цена]]*Таблица59[[#This Row],[Заказ]] -> 0
A131: iPro 11 M5 256 Black LTE | B131: США, Black | C131: 86000 | E131: =Таблица59[[#This Row],[Цена]]*Таблица59[[#This Row],[Заказ]] -> 0
A132: iPro 11 M5 256 Silver LTE | B132: США, Silver | C132: 88000 | E132: =Таблица59[[#This Row],[Цена]]*Таблица59[[#This Row],[Заказ]] -> 0
A133: iPro 11 M5 512 Black Wi-Fi | B133: США, Black | C133: 95000 | E133: =Таблица59[[#This Row],[Цена]]*Таблица59[[#This Row],[Заказ]] -> 0
A134: iPro 11 M5 512 Silver Wi-Fi | B134: США, Silver | C134: 96000 | E134: =Таблица59[[#This Row],[Цена]]*Таблица59[[#This Row],[Заказ]] -> 0
A135: iPro 11 M5 512 Black LTE | B135: США, Black | C135: 118800 | E135: =Таблица59[[#This Row],[Цена]]*Таблица59[[#This Row],[Заказ]] -> 0
A136: iPro 11 M5 512 Silver LTE | B136: США, Silver | C136: 122000 | E136: =Таблица59[[#This Row],[Цена]]*Таблица59[[#This Row],[Заказ]] -> 0
... A164: iPad Pro 13 (2024) 5G 512GB Silver M4 | B164: США, Silver | C164: 112000 | E164: =Таблица59[[#This Row],[Цена]]*Таблица59[[#This Row],[Заказ]] -> 0
A165: iPad 10/11/Mini | E165: =Таблица59[[#This Row],[Цена]]*Таблица59[[#This Row],[Заказ]] -> 0
A166: iPad 10 64 Silver LTE | B166: США, Silver | C166: 30000 | E166: =Таблица59[[#This Row],[Цена]]*Таблица59[[#This Row],[Заказ]] -> 0
A167: iPad 10 64 Blue LTE | B167: США, Blue | C167: 30000 | E167: =Таблица59[[#This Row],[Цена]]*Таблица59[[#This Row],[Заказ]] -> 0
A168: iPad 11 2025 128 Silver Wi-Fi | B168: США, Silver | C168: 27700 | E168: =Таблица59[[#This Row],[Цена]]*Таблица59[[#This Row],[Заказ]] -> 0
A169: iPad 11 2025 128 Pink Wi-Fi | B169: США, Pink | C169: 27700 | E169: =Таблица59[[#This Row],[Цена]]*Таблица59[[#This Row],[Заказ]] -> 0
A170: iPad 11 2025 128 Blue Wi-Fi | B170: США, Blue | C170: 27300 | E170: =Таблица59[[#This Row],[Цена]]*Таблица59[[#This Row],[Заказ]] -> 0
A171: iPad 11 2025 128 Yellow Wi-Fi | B171: США, Yellow | C171: 28300 | E171: =Таблица59[[#This Row],[Цена]]*Таблица59[[#This Row],[Заказ]] -> 0
A172: iPad 11 2025 128 Blue LTE | B172: США, Blue | C172: 39800 | E172: =Таблица59[[#This Row],[Цена]]*Таблица59[[#This Row],[Заказ]] -> 0
A173: iPad 11 2025 128 Silver LTE | B173: США, Silver | C173: 40200 | E173: =Таблица59[[#This Row],[Цена]]*Таблица59[[#This Row],[Заказ]] -> 0
A174: iPad 11 2025 128 Yellow LTE | B174: США, Yellow | C174: 42500 | E174: =Таблица59[[#This Row],[Цена]]*Таблица59[[#This Row],[Заказ]] -> 0
A175: iPad 11 2025 128 Pink LTE | B175: США, Pink | C175: 41200 | E175: =Таблица59[[#This Row],[Цена]]*Таблица59[[#This Row],[Заказ]] -> 0
A176: iPad 11 2025 256 Silver Wi-Fi | B176: США, Silver | C176: 37200 | E176: =Таблица59[[#This Row],[Цена]]*Таблица59[[#This Row],[Заказ]] -> 0
A177: iPad 11 2025 256 Pink Wi-Fi | B177: США, Pink | C177: 36800 | E177: =Таблица59[[#This Row],[Цена]]*Таблица59[[#This Row],[Заказ]] -> 0
... A220: iPad mini 7 512 LTE Purple | B220: США, Purple | C220: 90000 | E220: =Таблица59[[#This Row],[Цена]]*Таблица59[[#This Row],[Заказ]] -> 0
A221: Magic Keyboard MK2A3 | C221: 12200 | E221: =Таблица59[[#This Row],[Цена]]*Таблица59[[#This Row],[Заказ]] -> 0
A222: Magic Keyboard MK2A3RS/A | B222: Россия | C222: 13300 | E222: =Таблица59[[#This Row],[Цена]]*Таблица59[[#This Row],[Заказ]] -> 0
A223: Magic Keyboard Numeric MQ052 | C223: 14800 | E223: =Таблица59[[#This Row],[Цена]]*Таблица59[[#This Row],[Заказ]] -> 0
A224: Magic Keyboard с Touch ID MK293RS/A | B224: Россия | C224: 16600 | E224: =Таблица59[[#This Row],[Цена]]*Таблица59[[#This Row],[Заказ]] -> 0
A225: Magic Mouse Black USB-C | B225: Черный, США | C225: 9000 | E225: =Таблица59[[#This Row],[Цена]]*Таблица59[[#This Row],[Заказ]] -> 0
A226: Magic Mouse White USB-C | B226: Белый, США | C226: 7700 | E226: =Таблица59[[#This Row],[Цена]]*Таблица59[[#This Row],[Заказ]] -> 0
A227: Magic Trackpad White MXK93 | B227: Белый, США | C227: 14500 | E227: =Таблица59[[#This Row],[Цена]]*Таблица59[[#This Row],[Заказ]] -> 0
A228: Magic Trackpad Black MXKA3 | B228: Черный, США | C228: 14500 | E228: =Таблица59[[#This Row],[Цена]]*Таблица59[[#This Row],[Заказ]] -> 0
A229: Magic Keyboard USB-C White MXCL3 | B229: Белый, США | C229: 11500 | E229: =Таблица59[[#This Row],[Цена]]*Таблица59[[#This Row],[Заказ]] -> 0
A230: Magic Keyboard Touch ID USB-C White MXCK3 | B230: Белый, США | C230: 18500 | E230: =Таблица59[[#This Row],[Цена]]*Таблица59[[#This Row],[Заказ]] -> 0
A231: Magic Keyboard Touch ID Numeric USB-C Black MXK83 | B231: Черный, США | C231: 19500 | E231: =Таблица59[[#This Row],[Цена]]*Таблица59[[#This Row],[Заказ]] -> 0
A232: Magic Keyboard Touch ID Numeric USB-C White MXK73 | B232: Белый, США | C232: 19500 | E232: =Таблица59[[#This Row],[Цена]]*Таблица59[[#This Row],[Заказ]] -> 0
A233: Studio Display Standart Glass Tilt Stand MYJG3R | B233: Россия | C233: 189000 | E233: =Таблица59[[#This Row],[Цена]]*Таблица59[[#This Row],[Заказ]] -> 0
A234: Studio Display Nano Glass Tilt Stand MYJK3 | B234: Россия | C234: 203000 | E234: =Таблица59[[#This Row],[Цена]]*Таблица59[[#This Row],[Заказ]] -> 0
A235: Studio Display Nano Glass Tilt Stand MMYW3 | B235: США | C235: 200000 | E235: =Таблица59[[#This Row],[Цена]]*Таблица59[[#This Row],[Заказ]] -> 0
... A239: Apple Pro Stand MX5N3 | B239: Россия | C239: 128000 | E239: =Таблица59[[#This Row],[Цена]]*Таблица59[[#This Row],[Заказ]] -> 0
A240: Apple VESA Mount Adapter MX5M3 | C240: 39000 | E240: =Таблица59[[#This Row],[Цена]]*Таблица59[[#This Row],[Заказ]] -> 0
A241: [MWUC3] iMac M4 (8/8/16/256) Silver | B241: Серебристый, Россия | C241: 143000 | E241: =Таблица59[[#This Row],[Цена]]*Таблица59[[#This Row],[Заказ]] -> 0
A242: [MWUF3] iMac M4 (8/8/16/256) Blue | B242: Синий, Россия | C242: 143000 | E242: =Таблица59[[#This Row],[Цена]]*Таблица59[[#This Row],[Заказ]] -> 0
A243: [Z1E8000J1] iMac M4 (8/8/16/256) Orange | B243: Оранжевый, Россия | C243: 143000 | E243: =Таблица59[[#This Row],[Цена]]*Таблица59[[#This Row],[Заказ]] -> 0
A244: [Z1E3000JC] iMac M4 (8/8/16/256) Yellow | B244: Желтый, Россия | C244: 143000 | E244: =Таблица59[[#This Row],[Цена]]*Таблица59[[#This Row],[Заказ]] -> 0
A245: [Z1E7000KB] iMac M4 (8/8/16/256) Purple | B245: Фиолетовый, Россия | C245: 143000 | E245: =Таблица59[[#This Row],[Цена]]*Таблица59[[#This Row],[Заказ]] -> 0
A246: [MWUU3] iMac M4 (10/10/16/256) Silver | B246: Серебристый, Россия | C246: 161000 | E246: =Таблица59[[#This Row],[Цена]]*Таблица59[[#This Row],[Заказ]] -> 0
A247: [MWV13] iMac M4 (10/10/16/256) Blue | B247: Синий, Россия | C247: 161000 | E247: =Таблица59[[#This Row],[Цена]]*Таблица59[[#This Row],[Заказ]] -> 0
A248: [MWUY3] iMac M4 (10/10/16/256) Green | B248: Зеленый, Россия | C248: 161000 | E248: =Таблица59[[#This Row],[Цена]]*Таблица59[[#This Row],[Заказ]] -> 0
A249: [Z1EV000KZ] iMac M4 (10/10/16/256) Orange | B249: Оранжевый, Россия | C249: 161000 | E249: =Таблица59[[#This Row],[Цена]]*Таблица59[[#This Row],[Заказ]] -> 0
A250: [Z1EK000L2] iMac M4 (10/10/16/256) Yellow | B250: Желтый, Россия | C250: 161000 | E250: =Таблица59[[#This Row],[Цена]]*Таблица59[[#This Row],[Заказ]] -> 0
...

Sheet Телевизоры в наличии
A1: Назад в оглавление
A2: Телевизоры (безнал с НДС 22%) Спецпредложение!
A3: В наличии на складе, предоплата 100%, от 1 штуки! | E3: итого | F3: =SUM(Таблица13[Заказ]) -> 0 | G3: =SUM(Таблица13[Сумма заказа]) -> 0
A4: Артикул | B4: Наименование | C4: доступное количество | D4: от 1шт | E4: от 20 шт | F4: Заказ | G4: Сумма заказа | H4: доп.информация
A5: 68481RUS | B5: Mi LED TV A 43 FHD 2026 (L43MB-AFRU) | C5: 10 | D5: 20800 | E5: 20500 | G5: =IF('Телевизоры в наличии'!$F5<=19,D5*F5,'Телевизоры в наличии'!$E5*F5) -> 0 | H5: промо
A6: 68473RUS | B6: Mi LED TV A Pro 50 2026 (L50MB-APRU) | C6: 2 | D6: 30000 | E6: 29500 | G6: =IF('Телевизоры в наличии'!$F6<=19,D6*F6,'Телевизоры в наличии'!$E6*F6) -> 0
A7: 68472RUS | B7: Mi LED TV A 65 2026 (L65MB-ARU) | C7: 3 | D7: 42200 | E7: 41400 | G7: =IF('Телевизоры в наличии'!$F7<=19,D7*F7,'Телевизоры в наличии'!$E7*F7) -> 0 | H7: промо
A8: Итог | F8: =SUBTOTAL(109,Таблица13[Заказ]) -> 0 | G8: =SUBTOTAL(109,Таблица13[Сумма заказа]) -> 0

Sheet Уцененный товар
A1: Назад в оглавление
A2: Уцененный товар. На объемные заказы - скидка
D3: итого | E3: =SUM(Таблица323[Заказ]) -> 0 | F3: =SUM(Таблица323[Сумма заказа]) -> 0
A4: Код | B4: Наименование | C4: Причина уценки | D4: Цена | E4: Заказ | F4: Сумма заказа
A5: Электроника / Уценка Электроника | F5: =IF(Таблица323[[#This Row],[Цена ]]>0,Таблица323[[#This Row],[Цена ]]*Таблица323[[#This Row],[Заказ]],"")
A6: 16538-1BU | B6: Honor X6c 6+128GB NFC Midnight Black RUS Уценка | C6: Надорвана коробка с тыльной стороны | D6: 7500 | F6: =IF(Таблица323[[#This Row],[Цена ]]>0,Таблица323[[#This Row],[Цена ]]*Таблица323[[#This Row],[Заказ]],"") -> 0
A7: 16540-2BU | B7: Honor X7d 6+128GB NFC Meteor Silver RUS Уценка | C7: Повреждена коробка с тыльной стороны | D7: 11000 | F7: =IF(Таблица323[[#This Row],[Цена ]]>0,Таблица323[[#This Row],[Цена ]]*Таблица323[[#This Row],[Заказ]],"") -> 0
A8: 16541-1BU | B8: Honor X7d 8+256GB NFC Velvet Black RUS Уценка | C8: Повреждена коробка с тыльной стороны | D8: 13000 | F8: =IF(Таблица323[[#This Row],[Цена ]]>0,Таблица323[[#This Row],[Цена ]]*Таблица323[[#This Row],[Заказ]],"") -> 0
A9: 16727-1BU | B9: Infinix HOT 60 Pro 8+128GB NFC Black RUS Уценка | C9: С тыльной стороны повреждена коробка | D9: 10900 | F9: =IF(Таблица323[[#This Row],[Цена ]]>0,Таблица323[[#This Row],[Цена ]]*Таблица323[[#This Row],[Заказ]],"") -> 0
A10: 282156-1BU | B10: Realme Note 70 6+128GB NFC Black RUS Уценка | C10: Коробка с тыльной стороны пробита в двух местах | D10: 6800 | F10: =IF(Таблица323[[#This Row],[Цена ]]>0,Таблица323[[#This Row],[Цена ]]*Таблица323[[#This Row],[Заказ]],"") -> 0
A11: 281326-1BU | B11: Samsung Galaxy A07 4+128GB Black RUS Уценка | C11: С тыльной стороны повреждена коробка , пломбы целые | D11: 7500 | F11: =IF(Таблица323[[#This Row],[Цена ]]>0,Таблица323[[#This Row],[Цена ]]*Таблица323[[#This Row],[Заказ]],"") -> 0
A12: 281295-1BU | B12: Samsung Galaxy A16 4+128GB Blue Black RUS Уценка | C12: надорвана коробка , пломбы целы , не вскрывался | D12: 9000 | F12: =IF(Таблица323[[#This Row],[Цена ]]>0,Таблица323[[#This Row],[Цена ]]*Таблица323[[#This Row],[Заказ]],"") -> 0
A13: 281312-3BU | B13: Samsung Galaxy A26 5G 6+128GB Peach Pink RUS Уценка | C13: Коробка пробита с тыльной стороны, пломбы целые | D13: 13200 | F13: =IF(Таблица323[[#This Row],[Цена ]]>0,Таблица323[[#This Row],[Цена ]]*Таблица323[[#This Row],[Заказ]],"") -> 0
A14: 281313-4BU | B14: Samsung Galaxy A26 5G 8+256GB White RUS Уценка | C14: Коробка пробита с тыльной стороны, пломбы целые | D14: 16500 | F14: =IF(Таблица323[[#This Row],[Цена ]]>0,Таблица323[[#This Row],[Цена ]]*Таблица323[[#This Row],[Заказ]],"") -> 0
A15: Итог | E15: =SUBTOTAL(109,Таблица323[Заказ]) -> 0 | F15: =SUBTOTAL(109,Таблица323[Сумма заказа]) -> 0

Sheet Аксессуары и гаджеты в наличии
A1: Назад в оглавление
A2: Аксессуары и гаджеты в наличии (безнал с НДС 22% и наличные)
A3: Срок поставки с нашего склада 1-2 день. Предоплата 100%
E4: итого | F4: =SUM(Таблица62541616[Заказ наличные]) -> 0 | G4: =SUM(Таблица62541616[заказ б/н]) -> 0 | H4: =SUM(Таблица62541616[сумма заказа наличные]) -> 0 | I4: =SUM(Таблица62541616[Сумма заказа б/н]) -> 0
A5: артикул | B5: Полное название модели | C5: доступное количество | D5: цена наличные | E5: Цена б/н | F5: Заказ наличные | G5: заказ б/н | H5: сумма заказа наличные | I5: Сумма заказа б/н
A6: Аксессуары / Наушники / Беспроводные наушники / Redmi | H6: =IF(Таблица62541616[[#This Row],[цена наличные]]<>"",Таблица62541616[[#This Row],[цена наличные]]*Таблица62541616[[#This Row],[Заказ наличные]],"") | I6: =IF(Таблица62541616[[#This Row],[цена наличные]]<>"",Таблица62541616[[#This Row],[Цена б/н]]*Таблица62541616[[#This Row],[заказ б/н]],"")
A7: 994057-3RUS | B7: Беспроводные наушники REDMI Buds 8 Pro (BHR08GJGL) Cloud White RUS | C7: 7 | D7: 4500 | E7: 5350 | H7: =IF(Таблица62541616[[#This Row],[цена наличные]]<>"",Таблица62541616[[#This Row],[цена наличные]]*Таблица62541616[[#This Row],[Заказ наличные]],"") -> 0 | I7: =IF(Таблица62541616[[#This Row],[цена наличные]]<>"",Таблица62541616[[#This Row],[Цена б/н]]*Таблица62541616[[#This Row],[заказ б/н]],"") -> 0
A8: 994057-1RUS | B8: Беспроводные наушники REDMI Buds 8 Pro (BHR08GMGL) Glacier Blue RUS | C8: 13 | D8: 4500 | E8: 5350 | H8: =IF(Таблица62541616[[#This Row],[цена наличные]]<>"",Таблица62541616[[#This Row],[цена наличные]]*Таблица62541616[[#This Row],[Заказ наличные]],"") -> 0 | I8: =IF(Таблица62541616[[#This Row],[цена наличные]]<>"",Таблица62541616[[#This Row],[Цена б/н]]*Таблица62541616[[#This Row],[заказ б/н]],"") -> 0
A9: Аксессуары / Пылесосы / Роботы-пылесосы / Mi | H9: =IF(Таблица62541616[[#This Row],[цена наличные]]<>"",Таблица62541616[[#This Row],[цена наличные]]*Таблица62541616[[#This Row],[Заказ наличные]],"") | I9: =IF(Таблица62541616[[#This Row],[цена наличные]]<>"",Таблица62541616[[#This Row],[Цена б/н]]*Таблица62541616[[#This Row],[заказ б/н]],"")
A10: 904520RUS | B10: Робот-пылесос Xiaomi Robot Vacuum H40 (BHR07XBEU) RUS | C10: 10 | D10: 17900 | E10: 21910 | H10: =IF(Таблица62541616[[#This Row],[цена наличные]]<>"",Таблица62541616[[#This Row],[цена наличные]]*Таблица62541616[[#This Row],[Заказ наличные]],"") -> 0 | I10: =IF(Таблица62541616[[#This Row],[цена наличные]]<>"",Таблица62541616[[#This Row],[Цена б/н]]*Таблица62541616[[#This Row],[заказ б/н]],"") -> 0
A11: 822374-1RUS | B11: Робот-пылесос Xiaomi Robot Vacuum S40 (BHR084AEU) White RUS | C11: 15 | D11: 12400 | E11: 14590 | H11: =IF(Таблица62541616[[#This Row],[цена наличные]]<>"",Таблица62541616[[#This Row],[цена наличные]]*Таблица62541616[[#This Row],[Заказ наличные]],"") -> 0 | I11: =IF(Таблица62541616[[#This Row],[цена наличные]]<>"",Таблица62541616[[#This Row],[Цена б/н]]*Таблица62541616[[#This Row],[заказ б/н]],"") -> 0
A12: 822377-1RUS | B12: Робот-пылесос Xiaomi Robot Vacuum S40 Pro (BHR089REU) White RUS | C12: 10 | D12: 18200 | E12: 21290 | H12: =IF(Таблица62541616[[#This Row],[цена наличные]]<>"",Таблица62541616[[#This Row],[цена наличные]]*Таблица62541616[[#This Row],[Заказ наличные]],"") -> 0 | I12: =IF(Таблица62541616[[#This Row],[цена наличные]]<>"",Таблица62541616[[#This Row],[Цена б/н]]*Таблица62541616[[#This Row],[заказ б/н]],"") -> 0
A13: 822375-1RUS | B13: Робот-пылесос Xiaomi Robot Vacuum S40C (BHR9664EU) White RUS | C13: 14 | D13: 10400 | E13: 12240 | H13: =IF(Таблица62541616[[#This Row],[цена наличные]]<>"",Таблица62541616[[#This Row],[цена наличные]]*Таблица62541616[[#This Row],[Заказ наличные]],"") -> 0 | I13: =IF(Таблица62541616[[#This Row],[цена наличные]]<>"",Таблица62541616[[#This Row],[Цена б/н]]*Таблица62541616[[#This Row],[заказ б/н]],"") -> 0
A14: Аксессуары / Часы и фитнес-браслеты / Фитнес-браслеты / Mi | H14: =IF(Таблица62541616[[#This Row],[цена наличные]]<>"",Таблица62541616[[#This Row],[цена наличные]]*Таблица62541616[[#This Row],[Заказ наличные]],"") | I14: =IF(Таблица62541616[[#This Row],[цена наличные]]<>"",Таблица62541616[[#This Row],[Цена б/н]]*Таблица62541616[[#This Row],[заказ б/н]],"")
A15: 440028-5RUS | B15: Фитнес трекер Xiaomi Smart Band 9 Active (BHR08L3GL) Purple RUS | C15: 13 | D15: 3000 | E15: 3400 | H15: =IF(Таблица62541616[[#This Row],[цена наличные]]<>"",Таблица62541616[[#This Row],[цена наличные]]*Таблица62541616[[#This Row],[Заказ наличные]],"") -> 0 | I15: =IF(Таблица62541616[[#This Row],[цена наличные]]<>"",Таблица62541616[[#This Row],[Цена б/н]]*Таблица62541616[[#This Row],[заказ б/н]],"") -> 0
A16: 440028-1RUS | B16: Фитнес трекер Xiaomi Smart Band 9 Active (BHR9441GL) Beige White RUS | C16: 10 | D16: 3000 | E16: 3400 | H16: =IF(Таблица62541616[[#This Row],[цена наличные]]<>"",Таблица62541616[[#This Row],[цена наличные]]*Таблица62541616[[#This Row],[Заказ наличные]],"") -> 0 | I16: =IF(Таблица62541616[[#This Row],[цена наличные]]<>"",Таблица62541616[[#This Row],[Цена б/н]]*Таблица62541616[[#This Row],[заказ б/н]],"") -> 0
A17: 440028-3RUS | B17: Фитнес трекер Xiaomi Smart Band 9 Active (BHR9917GL) Pink RUS | C17: 13 | D17: 4200 | E17: 4700 | H17: =IF(Таблица62541616[[#This Row],[цена наличные]]<>"",Таблица62541616[[#This Row],[цена наличные]]*Таблица62541616[[#This Row],[Заказ наличные]],"") -> 0 | I17: =IF(Таблица62541616[[#This Row],[цена наличные]]<>"",Таблица62541616[[#This Row],[Цена б/н]]*Таблица62541616[[#This Row],[заказ б/н]],"") -> 0
A18: 902059-1RUS | B18: Фитнес-браслет Xiaomi Smart Band 10 Ceramic (BHR07Y5GL) Ceramic Edition Pearl White RUS | C18: 13 | D18: 3000 | E18: 3400 | H18: =IF(Таблица62541616[[#This Row],[цена наличные]]<>"",Таблица62541616[[#This Row],[цена наличные]]*Таблица62541616[[#This Row],[Заказ наличные]],"") -> 0 | I18: =IF(Таблица62541616[[#This Row],[цена наличные]]<>"",Таблица62541616[[#This Row],[Цена б/н]]*Таблица62541616[[#This Row],[заказ б/н]],"") -> 0
A19: 900962-1RUS | B19: Фитнес-браслет Xiaomi Smart Band 10 Glacier Silver (BHR07PSGL) RUS | C19: 10 | D19: 1650 | E19: 1900 | H19: =IF(Таблица62541616[[#This Row],[цена наличные]]<>"",Таблица62541616[[#This Row],[цена наличные]]*Таблица62541616[[#This Row],[Заказ наличные]],"") -> 0 | I19: =IF(Таблица62541616[[#This Row],[цена наличные]]<>"",Таблица62541616[[#This Row],[Цена б/н]]*Таблица62541616[[#This Row],[заказ б/н]],"") -> 0
A20: 900962-2RUS | B20: Фитнес-браслет Xiaomi Smart Band 10 Midnight Black (BHR07PYGL) RUS | C20: 14 | D20: 1650 | E20: 1900 | H20: =IF(Таблица62541616[[#This Row],[цена наличные]]<>"",Таблица62541616[[#This Row],[цена наличные]]*Таблица62541616[[#This Row],[Заказ наличные]],"") -> 0 | I20: =IF(Таблица62541616[[#This Row],[цена наличные]]<>"",Таблица62541616[[#This Row],[Цена б/н]]*Таблица62541616[[#This Row],[заказ б/н]],"") -> 0
A21: 900962-3RUS | B21: Фитнес-браслет Xiaomi Smart Band 10 Mystic Rose (BHR9999GL) RUS | C21: 13 | D21: 1650 | E21: 1900 | H21: =IF(Таблица62541616[[#This Row],[цена наличные]]<>"",Таблица62541616[[#This Row],[цена наличные]]*Таблица62541616[[#This Row],[Заказ наличные]],"") -> 0 | I21: =IF(Таблица62541616[[#This Row],[цена наличные]]<>"",Таблица62541616[[#This Row],[Цена б/н]]*Таблица62541616[[#This Row],[заказ б/н]],"") -> 0
A22: 801461-1RUS | B22: Фитнес-браслет Xiaomi Smart Band 9 Pro Moonlight Silver (BHR8715GL) RUS | C22: 11 | D22: 5350 | E22: 6000 | H22: =IF(Таблица62541616[[#This Row],[цена наличные]]<>"",Таблица62541616[[#This Row],[цена наличные]]*Таблица62541616[[#This Row],[Заказ наличные]],"") -> 0 | I22: =IF(Таблица62541616[[#This Row],[цена наличные]]<>"",Таблица62541616[[#This Row],[Цена б/н]]*Таблица62541616[[#This Row],[заказ б/н]],"") -> 0
A23: 801461-2RUS | B23: Фитнес-браслет Xiaomi Smart Band 9 Pro Obsidian Black (BHR8710GL) RUS | C23: 12 | D23: 5350 | E23: 6000 | H23: =IF(Таблица62541616[[#This Row],[цена наличные]]<>"",Таблица62541616[[#This Row],[цена наличные]]*Таблица62541616[[#This Row],[Заказ наличные]],"") -> 0 | I23: =IF(Таблица62541616[[#This Row],[цена наличные]]<>"",Таблица62541616[[#This Row],[Цена б/н]]*Таблица62541616[[#This Row],[заказ б/н]],"") -> 0

Sheet Гаджеты и МБТ
A1: Назад в оглавление
A2: Аксессуары(наличные). Отгрузка со склада "Рубин" 1 рабочий день. Предолата 100% | C2: итого | D2: =SUM(Таблица7[Заказ]) -> 0 | E2: =SUM(Таблица7[Сумма заказа]) -> 0
A3: Код | B3: Наименование | C3: Цена | D3: Заказ | E3: Сумма заказа | F3: Особенности заказа | G3: Особенности заказа2
A4: Аксессуары / Аксессуары и гаджеты / Asus | E4: =IF(Таблица7[[#This Row],[Цена]]<>"",Таблица7[[#This Row],[Цена]]*Таблица7[[#This Row],[Заказ]],"") | F4: =IF(OR(ISBLANK(C4),(I4)>0),"","предзаказ в течение 1-3 рабочих дней") | G4: =IF(IFERROR(VLOOKUP(Таблица7[[#This Row],[Наименование]],#REF!,2,0),-1)>0,1001,IF(IFERROR(VLOOKUP(Таблица7[[#This Row],[Наименование]],#REF!,2,0),-1)>0,50,IF(IFERROR(VLOOKUP(Таблица7[[#This Row],[Наименование]],#REF!,2,0),-1)>0,1002,IF(IFERROR(VLOOKUP(Таблица7[[#This Row],[Наименование]],#REF!,2,0),-1)>0,1003,)))) -> 0
A5: 996018RUS | B5: Роутер ASUS (RT-AX1800U) Wi-Fi 6, USB Type-A RUS | C5: 4300 | E5: =IF(Таблица7[[#This Row],[Цена]]<>"",Таблица7[[#This Row],[Цена]]*Таблица7[[#This Row],[Заказ]],"") -> 0 | F5: =IF(OR(ISBLANK(C5),(I5)>0),"","предзаказ в течение 1-3 рабочих дней") -> предзаказ в течение 1-3 рабочих дней | G5: =IF(IFERROR(VLOOKUP(Таблица7[[#This Row],[Наименование]],#REF!,2,0),-1)>0,1001,IF(IFERROR(VLOOKUP(Таблица7[[#This Row],[Наименование]],#REF!,2,0),-1)>0,50,IF(IFERROR(VLOOKUP(Таблица7[[#This Row],[Наименование]],#REF!,2,0),-1)>0,1002,IF(IFERROR(VLOOKUP(Таблица7[[#This Row],[Наименование]],#REF!,2,0),-1)>0,1003,)))) -> 0
A6: Аксессуары / Аксессуары и гаджеты / Cudy | E6: =IF(Таблица7[[#This Row],[Цена]]<>"",Таблица7[[#This Row],[Цена]]*Таблица7[[#This Row],[Заказ]],"") | F6: =IF(OR(ISBLANK(C6),(I6)>0),"","предзаказ в течение 1-3 рабочих дней") | G6: =IF(IFERROR(VLOOKUP(Таблица7[[#This Row],[Наименование]],#REF!,2,0),-1)>0,1001,IF(IFERROR(VLOOKUP(Таблица7[[#This Row],[Наименование]],#REF!,2,0),-1)>0,50,IF(IFERROR(VLOOKUP(Таблица7[[#This Row],[Наименование]],#REF!,2,0),-1)>0,1002,IF(IFERROR(VLOOKUP(Таблица7[[#This Row],[Наименование]],#REF!,2,0),-1)>0,1003,)))) -> 0
A7: 801221RUS | B7: Коммутатор Cudy GS1006P неуправляемый 6 портов 1Гбит/с 4xPoE 65W (GS1006P) RUS | C7: 3400 | E7: =IF(Таблица7[[#This Row],[Цена]]<>"",Таблица7[[#This Row],[Цена]]*Таблица7[[#This Row],[Заказ]],"") -> 0 | F7: =IF(OR(ISBLANK(C7),(I7)>0),"","предзаказ в течение 1-3 рабочих дней") -> предзаказ в течение 1-3 рабочих дней | G7: =IF(IFERROR(VLOOKUP(Таблица7[[#This Row],[Наименование]],#REF!,2,0),-1)>0,1001,IF(IFERROR(VLOOKUP(Таблица7[[#This Row],[Наименование]],#REF!,2,0),-1)>0,50,IF(IFERROR(VLOOKUP(Таблица7[[#This Row],[Наименование]],#REF!,2,0),-1)>0,1002,IF(IFERROR(VLOOKUP(Таблица7[[#This Row],[Наименование]],#REF!,2,0),-1)>0,1003,)))) -> 0
A8: 801226RUS | B8: Сетевой адаптер Cudy WU1300S Wi-Fi5 AC1300 USB 3.0 (WU1300S) RUS | C8: 1000 | E8: =IF(Таблица7[[#This Row],[Цена]]<>"",Таблица7[[#This Row],[Цена]]*Таблица7[[#This Row],[Заказ]],"") -> 0 | F8: =IF(OR(ISBLANK(C8),(I8)>0),"","предзаказ в течение 1-3 рабочих дней") -> предзаказ в течение 1-3 рабочих дней | G8: =IF(IFERROR(VLOOKUP(Таблица7[[#This Row],[Наименование]],#REF!,2,0),-1)>0,1001,IF(IFERROR(VLOOKUP(Таблица7[[#This Row],[Наименование]],#REF!,2,0),-1)>0,50,IF(IFERROR(VLOOKUP(Таблица7[[#This Row],[Наименование]],#REF!,2,0),-1)>0,1002,IF(IFERROR(VLOOKUP(Таблица7[[#This Row],[Наименование]],#REF!,2,0),-1)>0,1003,)))) -> 0
A9: Аксессуары / Аксессуары и гаджеты / Dyson | E9: =IF(Таблица7[[#This Row],[Цена]]<>"",Таблица7[[#This Row],[Цена]]*Таблица7[[#This Row],[Заказ]],"") | F9: =IF(OR(ISBLANK(C9),(I9)>0),"","предзаказ в течение 1-3 рабочих дней") | G9: =IF(IFERROR(VLOOKUP(Таблица7[[#This Row],[Наименование]],#REF!,2,0),-1)>0,1001,IF(IFERROR(VLOOKUP(Таблица7[[#This Row],[Наименование]],#REF!,2,0),-1)>0,50,IF(IFERROR(VLOOKUP(Таблица7[[#This Row],[Наименование]],#REF!,2,0),-1)>0,1002,IF(IFERROR(VLOOKUP(Таблица7[[#This Row],[Наименование]],#REF!,2,0),-1)>0,1003,)))) -> 0
A10: 810321-1 | B10: Беспроводные наушники Dyson OnTrac Ceramic Cinnabar | C10: 20500 | E10: =IF(Таблица7[[#This Row],[Цена]]<>"",Таблица7[[#This Row],[Цена]]*Таблица7[[#This Row],[Заказ]],"") -> 0 | F10: =IF(OR(ISBLANK(C10),(I10)>0),"","предзаказ в течение 1-3 рабочих дней") -> предзаказ в течение 1-3 рабочих дней | G10: =IF(IFERROR(VLOOKUP(Таблица7[[#This Row],[Наименование]],#REF!,2,0),-1)>0,1001,IF(IFERROR(VLOOKUP(Таблица7[[#This Row],[Наименование]],#REF!,2,0),-1)>0,50,IF(IFERROR(VLOOKUP(Таблица7[[#This Row],[Наименование]],#REF!,2,0),-1)>0,1002,IF(IFERROR(VLOOKUP(Таблица7[[#This Row],[Наименование]],#REF!,2,0),-1)>0,1003,)))) -> 0
A11: Аксессуары / Аксессуары и гаджеты / Fujifilm | E11: =IF(Таблица7[[#This Row],[Цена]]<>"",Таблица7[[#This Row],[Цена]]*Таблица7[[#This Row],[Заказ]],"") | F11: =IF(OR(ISBLANK(C11),(I11)>0),"","предзаказ в течение 1-3 рабочих дней") | G11: =IF(IFERROR(VLOOKUP(Таблица7[[#This Row],[Наименование]],#REF!,2,0),-1)>0,1001,IF(IFERROR(VLOOKUP(Таблица7[[#This Row],[Наименование]],#REF!,2,0),-1)>0,50,IF(IFERROR(VLOOKUP(Таблица7[[#This Row],[Наименование]],#REF!,2,0),-1)>0,1002,IF(IFERROR(VLOOKUP(Таблица7[[#This Row],[Наименование]],#REF!,2,0),-1)>0,1003,)))) -> 0
A12: 812994-1 | B12: Фотоаппарат Моментальной Печати Fujifilm Instax Mini Evo Black | C12: 15400 | E12: =IF(Таблица7[[#This Row],[Цена]]<>"",Таблица7[[#This Row],[Цена]]*Таблица7[[#This Row],[Заказ]],"") -> 0 | F12: =IF(OR(ISBLANK(C12),(I12)>0),"","предзаказ в течение 1-3 рабочих дней") -> предзаказ в течение 1-3 рабочих дней | G12: =IF(IFERROR(VLOOKUP(Таблица7[[#This Row],[Наименование]],#REF!,2,0),-1)>0,1001,IF(IFERROR(VLOOKUP(Таблица7[[#This Row],[Наименование]],#REF!,2,0),-1)>0,50,IF(IFERROR(VLOOKUP(Таблица7[[#This Row],[Наименование]],#REF!,2,0),-1)>0,1002,IF(IFERROR(VLOOKUP(Таблица7[[#This Row],[Наименование]],#REF!,2,0),-1)>0,1003,)))) -> 0
A13: 812994-2 | B13: Фотоаппарат Моментальной Печати Fujifilm Instax Mini Evo Brown | C13: 15400 | E13: =IF(Таблица7[[#This Row],[Цена]]<>"",Таблица7[[#This Row],[Цена]]*Таблица7[[#This Row],[Заказ]],"") -> 0 | F13: =IF(OR(ISBLANK(C13),(I13)>0),"","предзаказ в течение 1-3 рабочих дней") -> предзаказ в течение 1-3 рабочих дней | G13: =IF(IFERROR(VLOOKUP(Таблица7[[#This Row],[Наименование]],#REF!,2,0),-1)>0,1001,IF(IFERROR(VLOOKUP(Таблица7[[#This Row],[Наименование]],#REF!,2,0),-1)>0,50,IF(IFERROR(VLOOKUP(Таблица7[[#This Row],[Наименование]],#REF!,2,0),-1)>0,1002,IF(IFERROR(VLOOKUP(Таблица7[[#This Row],[Наименование]],#REF!,2,0),-1)>0,1003,)))) -> 0
A14: 812996-1 | B14: Фотоаппарат Моментальной Печати Fujifilm Instax Mini Evo Cinema Black | C14: 29400 | E14: =IF(Таблица7[[#This Row],[Цена]]<>"",Таблица7[[#This Row],[Цена]]*Таблица7[[#This Row],[Заказ]],"") -> 0 | F14: =IF(OR(ISBLANK(C14),(I14)>0),"","предзаказ в течение 1-3 рабочих дней") -> предзаказ в течение 1-3 рабочих дней | G14: =IF(IFERROR(VLOOKUP(Таблица7[[#This Row],[Наименование]],#REF!,2,0),-1)>0,1001,IF(IFERROR(VLOOKUP(Таблица7[[#This Row],[Наименование]],#REF!,2,0),-1)>0,50,IF(IFERROR(VLOOKUP(Таблица7[[#This Row],[Наименование]],#REF!,2,0),-1)>0,1002,IF(IFERROR(VLOOKUP(Таблица7[[#This Row],[Наименование]],#REF!,2,0),-1)>0,1003,)))) -> 0
A15: 812995-1 | B15: Фотоаппарат Моментальной Печати Fujifilm Instax Wide Evo Black | C15: 28100 | E15: =IF(Таблица7[[#This Row],[Цена]]<>"",Таблица7[[#This Row],[Цена]]*Таблица7[[#This Row],[Заказ]],"") -> 0 | F15: =IF(OR(ISBLANK(C15),(I15)>0),"","предзаказ в течение 1-3 рабочих дней") -> предзаказ в течение 1-3 рабочих дней | G15: =IF(IFERROR(VLOOKUP(Таблица7[[#This Row],[Наименование]],#REF!,2,0),-1)>0,1001,IF(IFERROR(VLOOKUP(Таблица7[[#This Row],[Наименование]],#REF!,2,0),-1)>0,50,IF(IFERROR(VLOOKUP(Таблица7[[#This Row],[Наименование]],#REF!,2,0),-1)>0,1002,IF(IFERROR(VLOOKUP(Таблица7[[#This Row],[Наименование]],#REF!,2,0),-1)>0,1003,)))) -> 0
A16: Аксессуары / Аксессуары и гаджеты / GoPro / Камеры GoPro HERO | E16: =IF(Таблица7[[#This Row],[Цена]]<>"",Таблица7[[#This Row],[Цена]]*Таблица7[[#This Row],[Заказ]],"") | F16: =IF(OR(ISBLANK(C16),(I16)>0),"","предзаказ в течение 1-3 рабочих дней") | G16: =IF(IFERROR(VLOOKUP(Таблица7[[#This Row],[Наименование]],#REF!,2,0),-1)>0,1001,IF(IFERROR(VLOOKUP(Таблица7[[#This Row],[Наименование]],#REF!,2,0),-1)>0,50,IF(IFERROR(VLOOKUP(Таблица7[[#This Row],[Наименование]],#REF!,2,0),-1)>0,1002,IF(IFERROR(VLOOKUP(Таблица7[[#This Row],[Наименование]],#REF!,2,0),-1)>0,1003,)))) -> 0
A17: 84123-1EU | B17: Камера GoPro Hero 13 Accessory Bundle 64GB Black EU | C17: 30900 | E17: =IF(Таблица7[[#This Row],[Цена]]<>"",Таблица7[[#This Row],[Цена]]*Таблица7[[#This Row],[Заказ]],"") -> 0 | F17: =IF(OR(ISBLANK(C17),(I17)>0),"","предзаказ в течение 1-3 рабочих дней") -> предзаказ в течение 1-3 рабочих дней | G17: =IF(IFERROR(VLOOKUP(Таблица7[[#This Row],[Наименование]],#REF!,2,0),-1)>0,1001,IF(IFERROR(VLOOKUP(Таблица7[[#This Row],[Наименование]],#REF!,2,0),-1)>0,50,IF(IFERROR(VLOOKUP(Таблица7[[#This Row],[Наименование]],#REF!,2,0),-1)>0,1002,IF(IFERROR(VLOOKUP(Таблица7[[#This Row],[Наименование]],#REF!,2,0),-1)>0,1003,)))) -> 0
A18: 84121-1EU | B18: Камера GoPro Hero 13 Black EU | C18: 23100 | E18: =IF(Таблица7[[#This Row],[Цена]]<>"",Таблица7[[#This Row],[Цена]]*Таблица7[[#This Row],[Заказ]],"") -> 0 | F18: =IF(OR(ISBLANK(C18),(I18)>0),"","предзаказ в течение 1-3 рабочих дней") -> предзаказ в течение 1-3 рабочих дней | G18: =IF(IFERROR(VLOOKUP(Таблица7[[#This Row],[Наименование]],#REF!,2,0),-1)>0,1001,IF(IFERROR(VLOOKUP(Таблица7[[#This Row],[Наименование]],#REF!,2,0),-1)>0,50,IF(IFERROR(VLOOKUP(Таблица7[[#This Row],[Наименование]],#REF!,2,0),-1)>0,1002,IF(IFERROR(VLOOKUP(Таблица7[[#This Row],[Наименование]],#REF!,2,0),-1)>0,1003,)))) -> 0
A19: Аксессуары / Аксессуары и гаджеты / Harman Kardon | E19: =IF(Таблица7[[#This Row],[Цена]]<>"",Таблица7[[#This Row],[Цена]]*Таблица7[[#This Row],[Заказ]],"") | F19: =IF(OR(ISBLANK(C19),(I19)>0),"","предзаказ в течение 1-3 рабочих дней") | G19: =IF(IFERROR(VLOOKUP(Таблица7[[#This Row],[Наименование]],#REF!,2,0),-1)>0,1001,IF(IFERROR(VLOOKUP(Таблица7[[#This Row],[Наименование]],#REF!,2,0),-1)>0,50,IF(IFERROR(VLOOKUP(Таблица7[[#This Row],[Наименование]],#REF!,2,0),-1)>0,1002,IF(IFERROR(VLOOKUP(Таблица7[[#This Row],[Наименование]],#REF!,2,0),-1)>0,1003,)))) -> 0
A20: 50308-1 | B20: Беспроводная колонка Harman Kardon Onyx Studio 9 Black | C20: 17000 | E20: =IF(Таблица7[[#This Row],[Цена]]<>"",Таблица7[[#This Row],[Цена]]*Таблица7[[#This Row],[Заказ]],"") -> 0 | F20: =IF(OR(ISBLANK(C20),(I20)>0),"","предзаказ в течение 1-3 рабочих дней") -> предзаказ в течение 1-3 рабочих дней | G20: =IF(IFERROR(VLOOKUP(Таблица7[[#This Row],[Наименование]],#REF!,2,0),-1)>0,1001,IF(IFERROR(VLOOKUP(Таблица7[[#This Row],[Наименование]],#REF!,2,0),-1)>0,50,IF(IFERROR(VLOOKUP(Таблица7[[#This Row],[Наименование]],#REF!,2,0),-1)>0,1002,IF(IFERROR(VLOOKUP(Таблица7[[#This Row],[Наименование]],#REF!,2,0),-1)>0,1003,)))) -> 0
A21: 50308-2 | B21: Беспроводная колонка Harman Kardon Onyx Studio 9 Grey | C21: 17000 | E21: =IF(Таблица7[[#This Row],[Цена]]<>"",Таблица7[[#This Row],[Цена]]*Таблица7[[#This Row],[Заказ]],"") -> 0 | F21: =IF(OR(ISBLANK(C21),(I21)>0),"","предзаказ в течение 1-3 рабочих дней") -> предзаказ в течение 1-3 рабочих дней | G21: =IF(IFERROR(VLOOKUP(Таблица7[[#This Row],[Наименование]],#REF!,2,0),-1)>0,1001,IF(IFERROR(VLOOKUP(Таблица7[[#This Row],[Наименование]],#REF!,2,0),-1)>0,50,IF(IFERROR(VLOOKUP(Таблица7[[#This Row],[Наименование]],#REF!,2,0),-1)>0,1002,IF(IFERROR(VLOOKUP(Таблица7[[#This Row],[Наименование]],#REF!,2,0),-1)>0,1003,)))) -> 0
A22: Аксессуары / Аксессуары и гаджеты / Insta360 | E22: =IF(Таблица7[[#This Row],[Цена]]<>"",Таблица7[[#This Row],[Цена]]*Таблица7[[#This Row],[Заказ]],"") | F22: =IF(OR(ISBLANK(C22),(I22)>0),"","предзаказ в течение 1-3 рабочих дней") | G22: =IF(IFERROR(VLOOKUP(Таблица7[[#This Row],[Наименование]],#REF!,2,0),-1)>0,1001,IF(IFERROR(VLOOKUP(Таблица7[[#This Row],[Наименование]],#REF!,2,0),-1)>0,50,IF(IFERROR(VLOOKUP(Таблица7[[#This Row],[Наименование]],#REF!,2,0),-1)>0,1002,IF(IFERROR(VLOOKUP(Таблица7[[#This Row],[Наименование]],#REF!,2,0),-1)>0,1003,)))) -> 0
A23: 801557GB | B23: Экшн-камера Insta 360 Ace Pro Black GB | C23: 22500 | E23: =IF(Таблица7[[#This Row],[Цена]]<>"",Таблица7[[#This Row],[Цена]]*Таблица7[[#This Row],[Заказ]],"") -> 0 | F23: =IF(OR(ISBLANK(C23),(I23)>0),"","предзаказ в течение 1-3 рабочих дней") -> предзаказ в течение 1-3 рабочих дней | G23: =IF(IFERROR(VLOOKUP(Таблица7[[#This Row],[Наименование]],#REF!,2,0),-1)>0,1001,IF(IFERROR(VLOOKUP(Таблица7[[#This Row],[Наименование]],#REF!,2,0),-1)>0,50,IF(IFERROR(VLOOKUP(Таблица7[[#This Row],[Наименование]],#REF!,2,0),-1)>0,1002,IF(IFERROR(VLOOKUP(Таблица7[[#This Row],[Наименование]],#REF!,2,0),-1)>0,1003,)))) -> 0
A24: 801550-1EU | B24: Экшн-камера Insta 360 GO 3S 4K 128Gb Midnight Black EU | C24: 27300 | E24: =IF(Таблица7[[#This Row],[Цена]]<>"",Таблица7[[#This Row],[Цена]]*Таблица7[[#This Row],[Заказ]],"") -> 0 | F24: =IF(OR(ISBLANK(C24),(I24)>0),"","предзаказ в течение 1-3 рабочих дней") -> предзаказ в течение 1-3 рабочих дней | G24: =IF(IFERROR(VLOOKUP(Таблица7[[#This Row],[Наименование]],#REF!,2,0),-1)>0,1001,IF(IFERROR(VLOOKUP(Таблица7[[#This Row],[Наименование]],#REF!,2,0),-1)>0,50,IF(IFERROR(VLOOKUP(Таблица7[[#This Row],[Наименование]],#REF!,2,0),-1)>0,1002,IF(IFERROR(VLOOKUP(Таблица7[[#This Row],[Наименование]],#REF!,2,0),-1)>0,1003,)))) -> 0
A25: 801552-1EU | B25: Экшн-камера Insta 360 GO 3S 4K 64GB Midnight Black EU | C25: 20900 | E25: =IF(Таблица7[[#This Row],[Цена]]<>"",Таблица7[[#This Row],[Цена]]*Таблица7[[#This Row],[Заказ]],"") -> 0 | F25: =IF(OR(ISBLANK(C25),(I25)>0),"","предзаказ в течение 1-3 рабочих дней") -> предзаказ в течение 1-3 рабочих дней | G25: =IF(IFERROR(VLOOKUP(Таблица7[[#This Row],[Наименование]],#REF!,2,0),-1)>0,1001,IF(IFERROR(VLOOKUP(Таблица7[[#This Row],[Наименование]],#REF!,2,0),-1)>0,50,IF(IFERROR(VLOOKUP(Таблица7[[#This Row],[Наименование]],#REF!,2,0),-1)>0,1002,IF(IFERROR(VLOOKUP(Таблица7[[#This Row],[Наименование]],#REF!,2,0),-1)>0,1003,)))) -> 0
A26: 801553-1EU | B26: Экшн-камера Insta 360 X4 - 8K 360 Action Cam Black EU | C26: 31400 | E26: =IF(Таблица7[[#This Row],[Цена]]<>"",Таблица7[[#This Row],[Цена]]*Таблица7[[#This Row],[Заказ]],"") -> 0 | F26: =IF(OR(ISBLANK(C26),(I26)>0),"","предзаказ в течение 1-3 рабочих дней") -> предзаказ в течение 1-3 рабочих дней | G26: =IF(IFERROR(VLOOKUP(Таблица7[[#This Row],[Наименование]],#REF!,2,0),-1)>0,1001,IF(IFERROR(VLOOKUP(Таблица7[[#This Row],[Наименование]],#REF!,2,0),-1)>0,50,IF(IFERROR(VLOOKUP(Таблица7[[#This Row],[Наименование]],#REF!,2,0),-1)>0,1002,IF(IFERROR(VLOOKUP(Таблица7[[#This Row],[Наименование]],#REF!,2,0),-1)>0,1003,)))) -> 0
A27: 801556GB | B27: Экшн-камера Insta 360 X5 - 8K 360 Essentials Bundle GB | C27: 43800 | E27: =IF(Таблица7[[#This Row],[Цена]]<>"",Таблица7[[#This Row],[Цена]]*Таблица7[[#This Row],[Заказ]],"") -> 0 | F27: =IF(OR(ISBLANK(C27),(I27)>0),"","предзаказ в течение 1-3 рабочих дней") -> предзаказ в течение 1-3 рабочих дней | G27: =IF(IFERROR(VLOOKUP(Таблица7[[#This Row],[Наименование]],#REF!,2,0),-1)>0,1001,IF(IFERROR(VLOOKUP(Таблица7[[#This Row],[Наименование]],#REF!,2,0),-1)>0,50,IF(IFERROR(VLOOKUP(Таблица7[[#This Row],[Наименование]],#REF!,2,0),-1)>0,1002,IF(IFERROR(VLOOKUP(Таблица7[[#This Row],[Наименование]],#REF!,2,0),-1)>0,1003,)))) -> 0
A28: Аксессуары / Аксессуары и гаджеты / JBL / Колонки JBL | E28: =IF(Таблица7[[#This Row],[Цена]]<>"",Таблица7[[#This Row],[Цена]]*Таблица7[[#This Row],[Заказ]],"") | F28: =IF(OR(ISBLANK(C28),(I28)>0),"","предзаказ в течение 1-3 рабочих дней") | G28: =IF(IFERROR(VLOOKUP(Таблица7[[#This Row],[Наименование]],#REF!,2,0),-1)>0,1001,IF(IFERROR(VLOOKUP(Таблица7[[#This Row],[Наименование]],#REF!,2,0),-1)>0,50,IF(IFERROR(VLOOKUP(Таблица7[[#This Row],[Наименование]],#REF!,2,0),-1)>0,1002,IF(IFERROR(VLOOKUP(Таблица7[[#This Row],[Наименование]],#REF!,2,0),-1)>0,1003,)))) -> 0
A29: 255071-8 | B29: Беспроводная колонка JBL Charge 5 (Green) | C29: 7500 | E29: =IF(Таблица7[[#This Row],[Цена]]<>"",Таблица7[[#This Row],[Цена]]*Таблица7[[#This Row],[Заказ]],"") -> 0 | F29: =IF(OR(ISBLANK(C29),(I29)>0),"","предзаказ в течение 1-3 рабочих дней") -> предзаказ в течение 1-3 рабочих дней | G29: =IF(IFERROR(VLOOKUP(Таблица7[[#This Row],[Наименование]],#REF!,2,0),-1)>0,1,IF(IFERROR(VLOOKUP(Таблица7[[#This Row],[Наименование]],#REF!,2,0),-1)>0,2,IF(IFERROR(VLOOKUP(Таблица7[[#This Row],[Наименование]],#REF!,2,0),-1)>0,3,IF(IFERROR(VLOOKUP(Таблица7[[#This Row],[Наименование]],#REF!,2,0),-1)>0,4,)))) -> 0
A30: 255028-1RUS | B30: Домашняя аудиосистема JBL PARTYBOX Club 120 White RUS | C30: 26800 | E30: =IF(Таблица7[[#This Row],[Цена]]<>"",Таблица7[[#This Row],[Цена]]*Таблица7[[#This Row],[Заказ]],"") -> 0 | F30: =IF(OR(ISBLANK(C30),(I30)>0),"","предзаказ в течение 1-3 рабочих дней") -> предзаказ в течение 1-3 рабочих дней | G30: =IF(IFERROR(VLOOKUP(Таблица7[[#This Row],[Наименование]],#REF!,2,0),-1)>0,1,IF(IFERROR(VLOOKUP(Таблица7[[#This Row],[Наименование]],#REF!,2,0),-1)>0,2,IF(IFERROR(VLOOKUP(Таблица7[[#This Row],[Наименование]],#REF!,2,0),-1)>0,3,IF(IFERROR(VLOOKUP(Таблица7[[#This Row],[Наименование]],#REF!,2,0),-1)>0,4,)))) -> 0
A31: Аксессуары / Аксессуары и гаджеты / Keenetic | E31: =IF(Таблица7[[#This Row],[Цена]]<>"",Таблица7[[#This Row],[Цена]]*Таблица7[[#This Row],[Заказ]],"") | F31: =IF(OR(ISBLANK(C31),(I31)>0),"","предзаказ в течение 1-3 рабочих дней") | G31: =IF(IFERROR(VLOOKUP(Таблица7[[#This Row],[Наименование]],#REF!,2,0),-1)>0,1,IF(IFERROR(VLOOKUP(Таблица7[[#This Row],[Наименование]],#REF!,2,0),-1)>0,2,IF(IFERROR(VLOOKUP(Таблица7[[#This Row],[Наименование]],#REF!,2,0),-1)>0,3,IF(IFERROR(VLOOKUP(Таблица7[[#This Row],[Наименование]],#REF!,2,0),-1)>0,4,)))) -> 0
A32: 800862RUS | B32: Коммутатор Keenetic PoE+ Switch 9 (KN-4710) RUS | C32: 7000 | E32: =IF(Таблица7[[#This Row],[Цена]]<>"",Таблица7[[#This Row],[Цена]]*Таблица7[[#This Row],[Заказ]],"") -> 0 | F32: =IF(OR(ISBLANK(C32),(I32)>0),"","предзаказ в течение 1-3 рабочих дней") -> предзаказ в течение 1-3 рабочих дней | G32: =IF(IFERROR(VLOOKUP(Таблица7[[#This Row],[Наименование]],#REF!,2,0),-1)>0,1,IF(IFERROR(VLOOKUP(Таблица7[[#This Row],[Наименование]],#REF!,2,0),-1)>0,2,IF(IFERROR(VLOOKUP(Таблица7[[#This Row],[Наименование]],#REF!,2,0),-1)>0,3,IF(IFERROR(VLOOKUP(Таблица7[[#This Row],[Наименование]],#REF!,2,0),-1)>0,4,)))) -> 0
A33: 800849RUS | B33: Ретранслятор сигнала Wi-Fi Keenetic Buddy 6 AX3000 (KN-3411) RUS | C33: 5200 | E33: =IF(Таблица7[[#This Row],[Цена]]<>"",Таблица7[[#This Row],[Цена]]*Таблица7[[#This Row],[Заказ]],"") -> 0 | F33: =IF(OR(ISBLANK(C33),(I33)>0),"","предзаказ в течение 1-3 рабочих дней") -> предзаказ в течение 1-3 рабочих дней | G33: =IF(IFERROR(VLOOKUP(Таблица7[[#This Row],[Наименование]],#REF!,2,0),-1)>0,1,IF(IFERROR(VLOOKUP(Таблица7[[#This Row],[Наименование]],#REF!,2,0),-1)>0,2,IF(IFERROR(VLOOKUP(Таблица7[[#This Row],[Наименование]],#REF!,2,0),-1)>0,3,IF(IFERROR(VLOOKUP(Таблица7[[#This Row],[Наименование]],#REF!,2,0),-1)>0,4,)))) -> 0
A34: 800854RUS | B34: Роутер Keenetic 4G (KN-1213) N300 RUS | C34: 2600 | E34: =IF(Таблица7[[#This Row],[Цена]]<>"",Таблица7[[#This Row],[Цена]]*Таблица7[[#This Row],[Заказ]],"") -> 0 | F34: =IF(OR(ISBLANK(C34),(I34)>0),"","предзаказ в течение 1-3 рабочих дней") -> предзаказ в течение 1-3 рабочих дней | G34: =IF(IFERROR(VLOOKUP(Таблица7[[#This Row],[Наименование]],#REF!,2,0),-1)>0,1,IF(IFERROR(VLOOKUP(Таблица7[[#This Row],[Наименование]],#REF!,2,0),-1)>0,2,IF(IFERROR(VLOOKUP(Таблица7[[#This Row],[Наименование]],#REF!,2,0),-1)>0,3,IF(IFERROR(VLOOKUP(Таблица7[[#This Row],[Наименование]],#REF!,2,0),-1)>0,4,)))) -> 0
A35: 800858RUS | B35: Роутер Keenetic Extra (KN-1714) AC1200 RUS | C35: 4100 | E35: =IF(Таблица7[[#This Row],[Цена]]<>"",Таблица7[[#This Row],[Цена]]*Таблица7[[#This Row],[Заказ]],"") -> 0 | F35: =IF(OR(ISBLANK(C35),(I35)>0),"","предзаказ в течение 1-3 рабочих дней") -> предзаказ в течение 1-3 рабочих дней | G35: =IF(IFERROR(VLOOKUP(Таблица7[[#This Row],[Наименование]],#REF!,2,0),-1)>0,1,IF(IFERROR(VLOOKUP(Таблица7[[#This Row],[Наименование]],#REF!,2,0),-1)>0,2,IF(IFERROR(VLOOKUP(Таблица7[[#This Row],[Наименование]],#REF!,2,0),-1)>0,3,IF(IFERROR(VLOOKUP(Таблица7[[#This Row],[Наименование]],#REF!,2,0),-1)>0,4,)))) -> 0
A36: 800859RUS | B36: Роутер Keenetic Hopper SE (KN-3812) AX3000 RUS | C36: 9500 | E36: =IF(Таблица7[[#This Row],[Цена]]<>"",Таблица7[[#This Row],[Цена]]*Таблица7[[#This Row],[Заказ]],"") -> 0 | F36: =IF(OR(ISBLANK(C36),(I36)>0),"","предзаказ в течение 1-3 рабочих дней") -> предзаказ в течение 1-3 рабочих дней | G36: =IF(IFERROR(VLOOKUP(Таблица7[[#This Row],[Наименование]],#REF!,2,0),-1)>0,1,IF(IFERROR(VLOOKUP(Таблица7[[#This Row],[Наименование]],#REF!,2,0),-1)>0,2,IF(IFERROR(VLOOKUP(Таблица7[[#This Row],[Наименование]],#REF!,2,0),-1)>0,3,IF(IFERROR(VLOOKUP(Таблица7[[#This Row],[Наименование]],#REF!,2,0),-1)>0,4,)))) -> 0
A37: 800863RUS | B37: Роутер Keenetic Launcher (KN-1221) RUS | C37: 2200 | E37: =IF(Таблица7[[#This Row],[Цена]]<>"",Таблица7[[#This Row],[Цена]]*Таблица7[[#This Row],[Заказ]],"") -> 0 | F37: =IF(OR(ISBLANK(C37),(I37)>0),"","предзаказ в течение 1-3 рабочих дней") -> предзаказ в течение 1-3 рабочих дней | G37: =IF(IFERROR(VLOOKUP(Таблица7[[#This Row],[Наименование]],#REF!,2,0),-1)>0,1,IF(IFERROR(VLOOKUP(Таблица7[[#This Row],[Наименование]],#REF!,2,0),-1)>0,2,IF(IFERROR(VLOOKUP(Таблица7[[#This Row],[Наименование]],#REF!,2,0),-1)>0,3,IF(IFERROR(VLOOKUP(Таблица7[[#This Row],[Наименование]],#REF!,2,0),-1)>0,4,)))) -> 0
A38: 800882RUS | B38: Роутер Keenetic Racer (KN-4010) Wi-Fi 6 AX3000 RUS | C38: 6400 | E38: =IF(Таблица7[[#This Row],[Цена]]<>"",Таблица7[[#This Row],[Цена]]*Таблица7[[#This Row],[Заказ]],"") -> 0 | F38: =IF(OR(ISBLANK(C38),(I38)>0),"","предзаказ в течение 1-3 рабочих дней") -> предзаказ в течение 1-3 рабочих дней | G38: =IF(IFERROR(VLOOKUP(Таблица7[[#This Row],[Наименование]],#REF!,2,0),-1)>0,1,IF(IFERROR(VLOOKUP(Таблица7[[#This Row],[Наименование]],#REF!,2,0),-1)>0,2,IF(IFERROR(VLOOKUP(Таблица7[[#This Row],[Наименование]],#REF!,2,0),-1)>0,3,IF(IFERROR(VLOOKUP(Таблица7[[#This Row],[Наименование]],#REF!,2,0),-1)>0,4,)))) -> 0
A39: 800867RUS | B39: Роутер Keenetic Sprinter SE (KN-3712) AX3000 RUS | C39: 8700 | E39: =IF(Таблица7[[#This Row],[Цена]]<>"",Таблица7[[#This Row],[Цена]]*Таблица7[[#This Row],[Заказ]],"") -> 0 | F39: =IF(OR(ISBLANK(C39),(I39)>0),"","предзаказ в течение 1-3 рабочих дней") -> предзаказ в течение 1-3 рабочих дней | G39: =IF(IFERROR(VLOOKUP(Таблица7[[#This Row],[Наименование]],#REF!,2,0),-1)>0,1,IF(IFERROR(VLOOKUP(Таблица7[[#This Row],[Наименование]],#REF!,2,0),-1)>0,2,IF(IFERROR(VLOOKUP(Таблица7[[#This Row],[Наименование]],#REF!,2,0),-1)>0,3,IF(IFERROR(VLOOKUP(Таблица7[[#This Row],[Наименование]],#REF!,2,0),-1)>0,4,)))) -> 0
A40: Аксессуары / Аксессуары и гаджеты / Kingston | E40: =IF(Таблица7[[#This Row],[Цена]]<>"",Таблица7[[#This Row],[Цена]]*Таблица7[[#This Row],[Заказ]],"") | F40: =IF(OR(ISBLANK(C40),(I40)>0),"","предзаказ в течение 1-3 рабочих дней") | G40: =IF(IFERROR(VLOOKUP(Таблица7[[#This Row],[Наименование]],#REF!,2,0),-1)>0,1,IF(IFERROR(VLOOKUP(Таблица7[[#This Row],[Наименование]],#REF!,2,0),-1)>0,2,IF(IFERROR(VLOOKUP(Таблица7[[#This Row],[Наименование]],#REF!,2,0),-1)>0,3,IF(IFERROR(VLOOKUP(Таблица7[[#This Row],[Наименование]],#REF!,2,0),-1)>0,4,)))) -> 0
A41: 993001EU | B41: Фотоаппарат Kodak FunSaver 27 кадров Black EU | C41: 3600 | E41: =IF(Таблица7[[#This Row],[Цена]]<>"",Таблица7[[#This Row],[Цена]]*Таблица7[[#This Row],[Заказ]],"") -> 0 | F41: =IF(OR(ISBLANK(C41),(I41)>0),"","предзаказ в течение 1-3 рабочих дней") -> предзаказ в течение 1-3 рабочих дней | G41: =IF(IFERROR(VLOOKUP(Таблица7[[#This Row],[Наименование]],#REF!,2,0),-1)>0,1,IF(IFERROR(VLOOKUP(Таблица7[[#This Row],[Наименование]],#REF!,2,0),-1)>0,2,IF(IFERROR(VLOOKUP(Таблица7[[#This Row],[Наименование]],#REF!,2,0),-1)>0,3,IF(IFERROR(VLOOKUP(Таблица7[[#This Row],[Наименование]],#REF!,2,0),-1)>0,4,)))) -> 0
A42: Аксессуары / Аксессуары и гаджеты / Maxvi | E42: =IF(Таблица7[[#This Row],[Цена]]<>"",Таблица7[[#This Row],[Цена]]*Таблица7[[#This Row],[Заказ]],"") | F42: =IF(OR(ISBLANK(C42),(I42)>0),"","предзаказ в течение 1-3 рабочих дней") | G42: =IF(IFERROR(VLOOKUP(Таблица7[[#This Row],[Наименование]],#REF!,2,0),-1)>0,1,IF(IFERROR(VLOOKUP(Таблица7[[#This Row],[Наименование]],#REF!,2,0),-1)>0,2,IF(IFERROR(VLOOKUP(Таблица7[[#This Row],[Наименование]],#REF!,2,0),-1)>0,3,IF(IFERROR(VLOOKUP(Таблица7[[#This Row],[Наименование]],#REF!,2,0),-1)>0,4,)))) -> 0
A43: 900839-1RUS | B43: LCD планшет для заметок и рисования Maxvi MGT-01 Black RUS | C43: 200 | E43: =IF(Таблица7[[#This Row],[Цена]]<>"",Таблица7[[#This Row],[Цена]]*Таблица7[[#This Row],[Заказ]],"") -> 0 | F43: =IF(OR(ISBLANK(C43),(I43)>0),"","предзаказ в течение 1-3 рабочих дней") -> предзаказ в течение 1-3 рабочих дней | G43: =IF(IFERROR(VLOOKUP(Таблица7[[#This Row],[Наименование]],#REF!,2,0),-1)>0,1,IF(IFERROR(VLOOKUP(Таблица7[[#This Row],[Наименование]],#REF!,2,0),-1)>0,2,IF(IFERROR(VLOOKUP(Таблица7[[#This Row],[Наименование]],#REF!,2,0),-1)>0,3,IF(IFERROR(VLOOKUP(Таблица7[[#This Row],[Наименование]],#REF!,2,0),-1)>0,4,)))) -> 0
A44: 900839-2RUS | B44: LCD планшет для заметок и рисования Maxvi MGT-01 Blue RUS | C44: 200 | E44: =IF(Таблица7[[#This Row],[Цена]]<>"",Таблица7[[#This Row],[Цена]]*Таблица7[[#This Row],[Заказ]],"") -> 0 | F44: =IF(OR(ISBLANK(C44),(I44)>0),"","предзаказ в течение 1-3 рабочих дней") -> предзаказ в течение 1-3 рабочих дней | G44: =IF(IFERROR(VLOOKUP(Таблица7[[#This Row],[Наименование]],#REF!,2,0),-1)>0,1,IF(IFERROR(VLOOKUP(Таблица7[[#This Row],[Наименование]],#REF!,2,0),-1)>0,2,IF(IFERROR(VLOOKUP(Таблица7[[#This Row],[Наименование]],#REF!,2,0),-1)>0,3,IF(IFERROR(VLOOKUP(Таблица7[[#This Row],[Наименование]],#REF!,2,0),-1)>0,4,)))) -> 0
A45: 900839-3RUS | B45: LCD планшет для заметок и рисования Maxvi MGT-01 Pink RUS | C45: 200 | E45: =IF(Таблица7[[#This Row],[Цена]]<>"",Таблица7[[#This Row],[Цена]]*Таблица7[[#This Row],[Заказ]],"") -> 0 | F45: =IF(OR(ISBLANK(C45),(I45)>0),"","предзаказ в течение 1-3 рабочих дней") -> предзаказ в течение 1-3 рабочих дней | G45: =IF(IFERROR(VLOOKUP(Таблица7[[#This Row],[Наименование]],#REF!,2,0),-1)>0,1,IF(IFERROR(VLOOKUP(Таблица7[[#This Row],[Наименование]],#REF!,2,0),-1)>0,2,IF(IFERROR(VLOOKUP(Таблица7[[#This Row],[Наименование]],#REF!,2,0),-1)>0,3,IF(IFERROR(VLOOKUP(Таблица7[[#This Row],[Наименование]],#REF!,2,0),-1)>0,4,)))) -> 0
A46: 900840-1RUS | B46: LCD планшет для заметок и рисования Maxvi MGT-01C Black RUS | C46: 300 | E46: =IF(Таблица7[[#This Row],[Цена]]<>"",Таблица7[[#This Row],[Цена]]*Таблица7[[#This Row],[Заказ]],"") -> 0 | F46: =IF(OR(ISBLANK(C46),(I46)>0),"","предзаказ в течение 1-3 рабочих дней") -> предзаказ в течение 1-3 рабочих дней | G46: =IF(IFERROR(VLOOKUP(Таблица7[[#This Row],[Наименование]],#REF!,2,0),-1)>0,1,IF(IFERROR(VLOOKUP(Таблица7[[#This Row],[Наименование]],#REF!,2,0),-1)>0,2,IF(IFERROR(VLOOKUP(Таблица7[[#This Row],[Наименование]],#REF!,2,0),-1)>0,3,IF(IFERROR(VLOOKUP(Таблица7[[#This Row],[Наименование]],#REF!,2,0),-1)>0,4,)))) -> 0
A47: 900841-1RUS | B47: LCD планшет для заметок и рисования Maxvi MGT-02 Black RUS | C47: 300 | E47: =IF(Таблица7[[#This Row],[Цена]]<>"",Таблица7[[#This Row],[Цена]]*Таблица7[[#This Row],[Заказ]],"") -> 0 | F47: =IF(OR(ISBLANK(C47),(I47)>0),"","предзаказ в течение 1-3 рабочих дней") -> предзаказ в течение 1-3 рабочих дней | G47: =IF(IFERROR(VLOOKUP(Таблица7[[#This Row],[Наименование]],#REF!,2,0),-1)>0,1,IF(IFERROR(VLOOKUP(Таблица7[[#This Row],[Наименование]],#REF!,2,0),-1)>0,2,IF(IFERROR(VLOOKUP(Таблица7[[#This Row],[Наименование]],#REF!,2,0),-1)>0,3,IF(IFERROR(VLOOKUP(Таблица7[[#This Row],[Наименование]],#REF!,2,0),-1)>0,4,)))) -> 0
A48: 900841-2RUS | B48: LCD планшет для заметок и рисования Maxvi MGT-02 Blue RUS | C48: 300 | E48: =IF(Таблица7[[#This Row],[Цена]]<>"",Таблица7[[#This Row],[Цена]]*Таблица7[[#This Row],[Заказ]],"") -> 0 | F48: =IF(OR(ISBLANK(C48),(I48)>0),"","предзаказ в течение 1-3 рабочих дней") -> предзаказ в течение 1-3 рабочих дней | G48: =IF(IFERROR(VLOOKUP(Таблица7[[#This Row],[Наименование]],#REF!,2,0),-1)>0,1,IF(IFERROR(VLOOKUP(Таблица7[[#This Row],[Наименование]],#REF!,2,0),-1)>0,2,IF(IFERROR(VLOOKUP(Таблица7[[#This Row],[Наименование]],#REF!,2,0),-1)>0,3,IF(IFERROR(VLOOKUP(Таблица7[[#This Row],[Наименование]],#REF!,2,0),-1)>0,4,)))) -> 0
A49: 900841-3RUS | B49: LCD планшет для заметок и рисования Maxvi MGT-02 Pink RUS | C49: 300 | E49: =IF(Таблица7[[#This Row],[Цена]]<>"",Таблица7[[#This Row],[Цена]]*Таблица7[[#This Row],[Заказ]],"") -> 0 | F49: =IF(OR(ISBLANK(C49),(I49)>0),"","предзаказ в течение 1-3 рабочих дней") -> предзаказ в течение 1-3 рабочих дней | G49: =IF(IFERROR(VLOOKUP(Таблица7[[#This Row],[Наименование]],#REF!,2,0),-1)>0,1,IF(IFERROR(VLOOKUP(Таблица7[[#This Row],[Наименование]],#REF!,2,0),-1)>0,2,IF(IFERROR(VLOOKUP(Таблица7[[#This Row],[Наименование]],#REF!,2,0),-1)>0,3,IF(IFERROR(VLOOKUP(Таблица7[[#This Row],[Наименование]],#REF!,2,0),-1)>0,4,)))) -> 0
A50: 900842-1RUS | B50: LCD планшет для заметок и рисования Maxvi MGT-02C Black RUS | C50: 400 | E50: =IF(Таблица7[[#This Row],[Цена]]<>"",Таблица7[[#This Row],[Цена]]*Таблица7[[#This Row],[Заказ]],"") -> 0 | F50: =IF(OR(ISBLANK(C50),(I50)>0),"","предзаказ в течение 1-3 рабочих дней") -> предзаказ в течение 1-3 рабочих дней | G50: =IF(IFERROR(VLOOKUP(Таблица7[[#This Row],[Наименование]],#REF!,2,0),-1)>0,1,IF(IFERROR(VLOOKUP(Таблица7[[#This Row],[Наименование]],#REF!,2,0),-1)>0,2,IF(IFERROR(VLOOKUP(Таблица7[[#This Row],[Наименование]],#REF!,2,0),-1)>0,3,IF(IFERROR(VLOOKUP(Таблица7[[#This Row],[Наименование]],#REF!,2,0),-1)>0,4,)))) -> 0
A51: 900842-2RUS | B51: LCD планшет для заметок и рисования Maxvi MGT-02C Blue RUS | C51: 400 | E51: =IF(Таблица7[[#This Row],[Цена]]<>"",Таблица7[[#This Row],[Цена]]*Таблица7[[#This Row],[Заказ]],"") -> 0 | F51: =IF(OR(ISBLANK(C51),(I51)>0),"","предзаказ в течение 1-3 рабочих дней") -> предзаказ в течение 1-3 рабочих дней | G51: =IF(IFERROR(VLOOKUP(Таблица7[[#This Row],[Наименование]],#REF!,2,0),-1)>0,1,IF(IFERROR(VLOOKUP(Таблица7[[#This Row],[Наименование]],#REF!,2,0),-1)>0,2,IF(IFERROR(VLOOKUP(Таблица7[[#This Row],[Наименование]],#REF!,2,0),-1)>0,3,IF(IFERROR(VLOOKUP(Таблица7[[#This Row],[Наименование]],#REF!,2,0),-1)>0,4,)))) -> 0
A52: 900842-3RUS | B52: LCD планшет для заметок и рисования Maxvi MGT-02C pink RUS | C52: 400 | E52: =IF(Таблица7[[#This Row],[Цена]]<>"",Таблица7[[#This Row],[Цена]]*Таблица7[[#This Row],[Заказ]],"") -> 0 | F52: =IF(OR(ISBLANK(C52),(I52)>0),"","предзаказ в течение 1-3 рабочих дней") -> предзаказ в течение 1-3 рабочих дней | G52: =IF(IFERROR(VLOOKUP(Таблица7[[#This Row],[Наименование]],#REF!,2,0),-1)>0,1,IF(IFERROR(VLOOKUP(Таблица7[[#This Row],[Наименование]],#REF!,2,0),-1)>0,2,IF(IFERROR(VLOOKUP(Таблица7[[#This Row],[Наименование]],#REF!,2,0),-1)>0,3,IF(IFERROR(VLOOKUP(Таблица7[[#This Row],[Наименование]],#REF!,2,0),-1)>0,4,)))) -> 0
A53: 205129-1RUS | B53: LCD планшет для заметок и рисования Maxvi MGT-03 Black RUS | C53: 400 | E53: =IF(Таблица7[[#This Row],[Цена]]<>"",Таблица7[[#This Row],[Цена]]*Таблица7[[#This Row],[Заказ]],"") -> 0 | F53: =IF(OR(ISBLANK(C53),(I53)>0),"","предзаказ в течение 1-3 рабочих дней") -> предзаказ в течение 1-3 рабочих дней | G53: =IF(IFERROR(VLOOKUP(Таблица7[[#This Row],[Наименование]],#REF!,2,0),-1)>0,1,IF(IFERROR(VLOOKUP(Таблица7[[#This Row],[Наименование]],#REF!,2,0),-1)>0,2,IF(IFERROR(VLOOKUP(Таблица7[[#This Row],[Наименование]],#REF!,2,0),-1)>0,3,IF(IFERROR(VLOOKUP(Таблица7[[#This Row],[Наименование]],#REF!,2,0),-1)>0,4,)))) -> 0
A54: Аксессуары / Аксессуары и гаджеты / MikroTik | E54: =IF(Таблица7[[#This Row],[Цена]]<>"",Таблица7[[#This Row],[Цена]]*Таблица7[[#This Row],[Заказ]],"") | F54: =IF(OR(ISBLANK(C54),(I54)>0),"","предзаказ в течение 1-3 рабочих дней") | G54: =IF(IFERROR(VLOOKUP(Таблица7[[#This Row],[Наименование]],#REF!,2,0),-1)>0,1,IF(IFERROR(VLOOKUP(Таблица7[[#This Row],[Наименование]],#REF!,2,0),-1)>0,2,IF(IFERROR(VLOOKUP(Таблица7[[#This Row],[Наименование]],#REF!,2,0),-1)>0,3,IF(IFERROR(VLOOKUP(Таблица7[[#This Row],[Наименование]],#REF!,2,0),-1)>0,4,)))) -> 0
A55: 802228RUS | B55: Точка доступа MikroTik cAP XL ac (RBCAPGI-5ACD2ND-XL) RUS | C55: 7900 | E55: =IF(Таблица7[[#This Row],[Цена]]<>"",Таблица7[[#This Row],[Цена]]*Таблица7[[#This Row],[Заказ]],"") -> 0 | F55: =IF(OR(ISBLANK(C55),(I55)>0),"","предзаказ в течение 1-3 рабочих дней") -> предзаказ в течение 1-3 рабочих дней | G55: =IF(IFERROR(VLOOKUP(Таблица7[[#This Row],[Наименование]],#REF!,2,0),-1)>0,1,IF(IFERROR(VLOOKUP(Таблица7[[#This Row],[Наименование]],#REF!,2,0),-1)>0,2,IF(IFERROR(VLOOKUP(Таблица7[[#This Row],[Наименование]],#REF!,2,0),-1)>0,3,IF(IFERROR(VLOOKUP(Таблица7[[#This Row],[Наименование]],#REF!,2,0),-1)>0,4,)))) -> 0
A56: Аксессуары / Аксессуары и гаджеты / Oculus | E56: =IF(Таблица7[[#This Row],[Цена]]<>"",Таблица7[[#This Row],[Цена]]*Таблица7[[#This Row],[Заказ]],"") | F56: =IF(OR(ISBLANK(C56),(I56)>0),"","предзаказ в течение 1-3 рабочих дней") | G56: =IF(IFERROR(VLOOKUP(Таблица7[[#This Row],[Наименование]],#REF!,2,0),-1)>0,1,IF(IFERROR(VLOOKUP(Таблица7[[#This Row],[Наименование]],#REF!,2,0),-1)>0,2,IF(IFERROR(VLOOKUP(Таблица7[[#This Row],[Наименование]],#REF!,2,0),-1)>0,3,IF(IFERROR(VLOOKUP(Таблица7[[#This Row],[Наименование]],#REF!,2,0),-1)>0,4,)))) -> 0
A57: 801127-1JP | B57: VR шлем Oculus Quest 3 4K 512GB JP | C57: 45400 | E57: =IF(Таблица7[[#This Row],[Цена]]<>"",Таблица7[[#This Row],[Цена]]*Таблица7[[#This Row],[Заказ]],"") -> 0 | F57: =IF(OR(ISBLANK(C57),(I57)>0),"","предзаказ в течение 1-3 рабочих дней") -> предзаказ в течение 1-3 рабочих дней | G57: =IF(IFERROR(VLOOKUP(Таблица7[[#This Row],[Наименование]],#REF!,2,0),-1)>0,1,IF(IFERROR(VLOOKUP(Таблица7[[#This Row],[Наименование]],#REF!,2,0),-1)>0,2,IF(IFERROR(VLOOKUP(Таблица7[[#This Row],[Наименование]],#REF!,2,0),-1)>0,3,IF(IFERROR(VLOOKUP(Таблица7[[#This Row],[Наименование]],#REF!,2,0),-1)>0,4,)))) -> 0
A58: 801177-1JP | B58: VR шлем Oculus Quest 3S 128GB JP | C58: 30000 | E58: =IF(Таблица7[[#This Row],[Цена]]<>"",Таблица7[[#This Row],[Цена]]*Таблица7[[#This Row],[Заказ]],"") -> 0 | F58: =IF(OR(ISBLANK(C58),(I58)>0),"","предзаказ в течение 1-3 рабочих дней") -> предзаказ в течение 1-3 рабочих дней | G58: =IF(IFERROR(VLOOKUP(Таблица7[[#This Row],[Наименование]],#REF!,2,0),-1)>0,1,IF(IFERROR(VLOOKUP(Таблица7[[#This Row],[Наименование]],#REF!,2,0),-1)>0,2,IF(IFERROR(VLOOKUP(Таблица7[[#This Row],[Наименование]],#REF!,2,0),-1)>0,3,IF(IFERROR(VLOOKUP(Таблица7[[#This Row],[Наименование]],#REF!,2,0),-1)>0,4,)))) -> 0
A59: Аксессуары / Аксессуары и гаджеты / Samsung | E59: =IF(Таблица7[[#This Row],[Цена]]<>"",Таблица7[[#This Row],[Цена]]*Таблица7[[#This Row],[Заказ]],"") | F59: =IF(OR(ISBLANK(C59),(I59)>0),"","предзаказ в течение 1-3 рабочих дней") | G59: =IF(IFERROR(VLOOKUP(Таблица7[[#This Row],[Наименование]],#REF!,2,0),-1)>0,1,IF(IFERROR(VLOOKUP(Таблица7[[#This Row],[Наименование]],#REF!,2,0),-1)>0,2,IF(IFERROR(VLOOKUP(Таблица7[[#This Row],[Наименование]],#REF!,2,0),-1)>0,3,IF(IFERROR(VLOOKUP(Таблица7[[#This Row],[Наименование]],#REF!,2,0),-1)>0,4,)))) -> 0
A60: 900866-1EU | B60: Гео Метка Samsung Galaxy Smart Tag 2 (EI-T5600) Black EU | C60: 1500 | E60: =IF(Таблица7[[#This Row],[Цена]]<>"",Таблица7[[#This Row],[Цена]]*Таблица7[[#This Row],[Заказ]],"") -> 0 | F60: =IF(OR(ISBLANK(C60),(I60)>0),"","предзаказ в течение 1-3 рабочих дней") -> предзаказ в течение 1-3 рабочих дней | G60: =IF(IFERROR(VLOOKUP(Таблица7[[#This Row],[Наименование]],#REF!,2,0),-1)>0,1,IF(IFERROR(VLOOKUP(Таблица7[[#This Row],[Наименование]],#REF!,2,0),-1)>0,2,IF(IFERROR(VLOOKUP(Таблица7[[#This Row],[Наименование]],#REF!,2,0),-1)>0,3,IF(IFERROR(VLOOKUP(Таблица7[[#This Row],[Наименование]],#REF!,2,0),-1)>0,4,)))) -> 0
A61: Аксессуары / Аксессуары и гаджеты / Samsung / Провода и зарядки | E61: =IF(Таблица7[[#This Row],[Цена]]<>"",Таблица7[[#This Row],[Цена]]*Таблица7[[#This Row],[Заказ]],"") | F61: =IF(OR(ISBLANK(C61),(I61)>0),"","предзаказ в течение 1-3 рабочих дней") | G61: =IF(IFERROR(VLOOKUP(Таблица7[[#This Row],[Наименование]],#REF!,2,0),-1)>0,1,IF(IFERROR(VLOOKUP(Таблица7[[#This Row],[Наименование]],#REF!,2,0),-1)>0,2,IF(IFERROR(VLOOKUP(Таблица7[[#This Row],[Наименование]],#REF!,2,0),-1)>0,3,IF(IFERROR(VLOOKUP(Таблица7[[#This Row],[Наименование]],#REF!,2,0),-1)>0,4,)))) -> 0
A62: 902111-2 | B62: Сетевое зарядное устройство Samsung (2025) EP-TA845 45W Type-C + Cable Black | C62: 1700 | E62: =IF(Таблица7[[#This Row],[Цена]]<>"",Таблица7[[#This Row],[Цена]]*Таблица7[[#This Row],[Заказ]],"") -> 0 | F62: =IF(OR(ISBLANK(C62),(I62)>0),"","предзаказ в течение 1-3 рабочих дней") -> предзаказ в течение 1-3 рабочих дней | G62: =IF(IFERROR(VLOOKUP(Таблица7[[#This Row],[Наименование]],#REF!,2,0),-1)>0,1,IF(IFERROR(VLOOKUP(Таблица7[[#This Row],[Наименование]],#REF!,2,0),-1)>0,2,IF(IFERROR(VLOOKUP(Таблица7[[#This Row],[Наименование]],#REF!,2,0),-1)>0,3,IF(IFERROR(VLOOKUP(Таблица7[[#This Row],[Наименование]],#REF!,2,0),-1)>0,4,)))) -> 0
A63: 902111-1 | B63: Сетевое зарядное устройство Samsung (2025) EP-TA845 45W Type-C + Cable White | C63: 1700 | E63: =IF(Таблица7[[#This Row],[Цена]]<>"",Таблица7[[#This Row],[Цена]]*Таблица7[[#This Row],[Заказ]],"") -> 0 | F63: =IF(OR(ISBLANK(C63),(I63)>0),"","предзаказ в течение 1-3 рабочих дней") -> предзаказ в течение 1-3 рабочих дней | G63: =IF(IFERROR(VLOOKUP(Таблица7[[#This Row],[Наименование]],#REF!,2,0),-1)>0,1,IF(IFERROR(VLOOKUP(Таблица7[[#This Row],[Наименование]],#REF!,2,0),-1)>0,2,IF(IFERROR(VLOOKUP(Таблица7[[#This Row],[Наименование]],#REF!,2,0),-1)>0,3,IF(IFERROR(VLOOKUP(Таблица7[[#This Row],[Наименование]],#REF!,2,0),-1)>0,4,)))) -> 0
A64: 803006-2 | B64: Сетевое зарядное устройство Samsung EP-T2510 25W Type-C + Cable Black | C64: 1100 | E64: =IF(Таблица7[[#This Row],[Цена]]<>"",Таблица7[[#This Row],[Цена]]*Таблица7[[#This Row],[Заказ]],"") -> 0 | F64: =IF(OR(ISBLANK(C64),(I64)>0),"","предзаказ в течение 1-3 рабочих дней") -> предзаказ в течение 1-3 рабочих дней | G64: =IF(IFERROR(VLOOKUP(Таблица7[[#This Row],[Наименование]],#REF!,2,0),-1)>0,1,IF(IFERROR(VLOOKUP(Таблица7[[#This Row],[Наименование]],#REF!,2,0),-1)>0,2,IF(IFERROR(VLOOKUP(Таблица7[[#This Row],[Наименование]],#REF!,2,0),-1)>0,3,IF(IFERROR(VLOOKUP(Таблица7[[#This Row],[Наименование]],#REF!,2,0),-1)>0,4,)))) -> 0
A65: 803006-1 | B65: Сетевое зарядное устройство Samsung EP-T2510 25W Type-C + Cable White | C65: 1100 | E65: =IF(Таблица7[[#This Row],[Цена]]<>"",Таблица7[[#This Row],[Цена]]*Таблица7[[#This Row],[Заказ]],"") -> 0 | F65: =IF(OR(ISBLANK(C65),(I65)>0),"","предзаказ в течение 1-3 рабочих дней") -> предзаказ в течение 1-3 рабочих дней | G65: =IF(IFERROR(VLOOKUP(Таблица7[[#This Row],[Наименование]],#REF!,2,0),-1)>0,1,IF(IFERROR(VLOOKUP(Таблица7[[#This Row],[Наименование]],#REF!,2,0),-1)>0,2,IF(IFERROR(VLOOKUP(Таблица7[[#This Row],[Наименование]],#REF!,2,0),-1)>0,3,IF(IFERROR(VLOOKUP(Таблица7[[#This Row],[Наименование]],#REF!,2,0),-1)>0,4,)))) -> 0
A66: 600869-1 | B66: Сетевое зарядное устройство Samsung EP-T2510 25W Type-C Black | C66: 1000 | E66: =IF(Таблица7[[#This Row],[Цена]]<>"",Таблица7[[#This Row],[Цена]]*Таблица7[[#This Row],[Заказ]],"") -> 0 | F66: =IF(OR(ISBLANK(C66),(I66)>0),"","предзаказ в течение 1-3 рабочих дней") -> предзаказ в течение 1-3 рабочих дней | G66: =IF(IFERROR(VLOOKUP(Таблица7[[#This Row],[Наименование]],#REF!,2,0),-1)>0,1,IF(IFERROR(VLOOKUP(Таблица7[[#This Row],[Наименование]],#REF!,2,0),-1)>0,2,IF(IFERROR(VLOOKUP(Таблица7[[#This Row],[Наименование]],#REF!,2,0),-1)>0,3,IF(IFERROR(VLOOKUP(Таблица7[[#This Row],[Наименование]],#REF!,2,0),-1)>0,4,)))) -> 0
A67: 600869-2 | B67: Сетевое зарядное устройство Samsung EP-T2510 25W Type-C White | C67: 1000 | E67: =IF(Таблица7[[#This Row],[Цена]]<>"",Таблица7[[#This Row],[Цена]]*Таблица7[[#This Row],[Заказ]],"") -> 0 | F67: =IF(OR(ISBLANK(C67),(I67)>0),"","предзаказ в течение 1-3 рабочих дней") -> предзаказ в течение 1-3 рабочих дней | G67: =IF(IFERROR(VLOOKUP(Таблица7[[#This Row],[Наименование]],#REF!,2,0),-1)>0,1,IF(IFERROR(VLOOKUP(Таблица7[[#This Row],[Наименование]],#REF!,2,0),-1)>0,2,IF(IFERROR(VLOOKUP(Таблица7[[#This Row],[Наименование]],#REF!,2,0),-1)>0,3,IF(IFERROR(VLOOKUP(Таблица7[[#This Row],[Наименование]],#REF!,2,0),-1)>0,4,)))) -> 0
A68: 800580-2 | B68: Сетевое зарядное устройство Samsung EP-T4510 45W Type-C + Cable White | C68: 1600 | E68: =IF(Таблица7[[#This Row],[Цена]]<>"",Таблица7[[#This Row],[Цена]]*Таблица7[[#This Row],[Заказ]],"") -> 0 | F68: =IF(OR(ISBLANK(C68),(I68)>0),"","предзаказ в течение 1-3 рабочих дней") -> предзаказ в течение 1-3 рабочих дней | G68: =IF(IFERROR(VLOOKUP(Таблица7[[#This Row],[Наименование]],#REF!,2,0),-1)>0,1,IF(IFERROR(VLOOKUP(Таблица7[[#This Row],[Наименование]],#REF!,2,0),-1)>0,2,IF(IFERROR(VLOOKUP(Таблица7[[#This Row],[Наименование]],#REF!,2,0),-1)>0,3,IF(IFERROR(VLOOKUP(Таблица7[[#This Row],[Наименование]],#REF!,2,0),-1)>0,4,)))) -> 0
A69: 900921-1 | B69: Сетевое зарядное устройство Samsung EP-T4511 45W Type-C + Cable Black | C69: 1600 | E69: =IF(Таблица7[[#This Row],[Цена]]<>"",Таблица7[[#This Row],[Цена]]*Таблица7[[#This Row],[Заказ]],"") -> 0 | F69: =IF(OR(ISBLANK(C69),(I69)>0),"","предзаказ в течение 1-3 рабочих дней") -> предзаказ в течение 1-3 рабочих дней | G69: =IF(IFERROR(VLOOKUP(Таблица7[[#This Row],[Наименование]],#REF!,2,0),-1)>0,1,IF(IFERROR(VLOOKUP(Таблица7[[#This Row],[Наименование]],#REF!,2,0),-1)>0,2,IF(IFERROR(VLOOKUP(Таблица7[[#This Row],[Наименование]],#REF!,2,0),-1)>0,3,IF(IFERROR(VLOOKUP(Таблица7[[#This Row],[Наименование]],#REF!,2,0),-1)>0,4,)))) -> 0
A70: 900921-2 | B70: Сетевое зарядное устройство Samsung EP-T4511 45W Type-C + Cable White | C70: 1600 | E70: =IF(Таблица7[[#This Row],[Цена]]<>"",Таблица7[[#This Row],[Цена]]*Таблица7[[#This Row],[Заказ]],"") -> 0 | F70: =IF(OR(ISBLANK(C70),(I70)>0),"","предзаказ в течение 1-3 рабочих дней") -> предзаказ в течение 1-3 рабочих дней | G70: =IF(IFERROR(VLOOKUP(Таблица7[[#This Row],[Наименование]],#REF!,2,0),-1)>0,1,IF(IFERROR(VLOOKUP(Таблица7[[#This Row],[Наименование]],#REF!,2,0),-1)>0,2,IF(IFERROR(VLOOKUP(Таблица7[[#This Row],[Наименование]],#REF!,2,0),-1)>0,3,IF(IFERROR(VLOOKUP(Таблица7[[#This Row],[Наименование]],#REF!,2,0),-1)>0,4,)))) -> 0
A71: 900920-1 | B71: Сетевое зарядное устройство Samsung EP-T4511 45W Type-C Black | C71: 1500 | E71: =IF(Таблица7[[#This Row],[Цена]]<>"",Таблица7[[#This Row],[Цена]]*Таблица7[[#This Row],[Заказ]],"") -> 0 | F71: =IF(OR(ISBLANK(C71),(I71)>0),"","предзаказ в течение 1-3 рабочих дней") -> предзаказ в течение 1-3 рабочих дней | G71: =IF(IFERROR(VLOOKUP(Таблица7[[#This Row],[Наименование]],#REF!,2,0),-1)>0,1,IF(IFERROR(VLOOKUP(Таблица7[[#This Row],[Наименование]],#REF!,2,0),-1)>0,2,IF(IFERROR(VLOOKUP(Таблица7[[#This Row],[Наименование]],#REF!,2,0),-1)>0,3,IF(IFERROR(VLOOKUP(Таблица7[[#This Row],[Наименование]],#REF!,2,0),-1)>0,4,)))) -> 0
A72: 900920-2 | B72: Сетевое зарядное устройство Samsung EP-T4511 45W Type-C White | C72: 1500 | E72: =IF(Таблица7[[#This Row],[Цена]]<>"",Таблица7[[#This Row],[Цена]]*Таблица7[[#This Row],[Заказ]],"") -> 0 | F72: =IF(OR(ISBLANK(C72),(I72)>0),"","предзаказ в течение 1-3 рабочих дней") -> предзаказ в течение 1-3 рабочих дней | G72: =IF(IFERROR(VLOOKUP(Таблица7[[#This Row],[Наименование]],#REF!,2,0),-1)>0,1,IF(IFERROR(VLOOKUP(Таблица7[[#This Row],[Наименование]],#REF!,2,0),-1)>0,2,IF(IFERROR(VLOOKUP(Таблица7[[#This Row],[Наименование]],#REF!,2,0),-1)>0,3,IF(IFERROR(VLOOKUP(Таблица7[[#This Row],[Наименование]],#REF!,2,0),-1)>0,4,)))) -> 0
A73: 600872-1 | B73: Сетевое зарядное устройство Samsung EP-T6530 65W Trio USB-C X2, USB-A + Cable Black | C73: 2200 | E73: =IF(Таблица7[[#This Row],[Цена]]<>"",Таблица7[[#This Row],[Цена]]*Таблица7[[#This Row],[Заказ]],"") -> 0 | F73: =IF(OR(ISBLANK(C73),(I73)>0),"","предзаказ в течение 1-3 рабочих дней") -> предзаказ в течение 1-3 рабочих дней | G73: =IF(IFERROR(VLOOKUP(Таблица7[[#This Row],[Наименование]],#REF!,2,0),-1)>0,1,IF(IFERROR(VLOOKUP(Таблица7[[#This Row],[Наименование]],#REF!,2,0),-1)>0,2,IF(IFERROR(VLOOKUP(Таблица7[[#This Row],[Наименование]],#REF!,2,0),-1)>0,3,IF(IFERROR(VLOOKUP(Таблица7[[#This Row],[Наименование]],#REF!,2,0),-1)>0,4,)))) -> 0
... A78: 800582-1 | B78: Сетевое зарядное устройство Samsung EP-TA800 25W Type-C White | C78: 1100 | E78: =IF(Таблица7[[#This Row],[Цена]]<>"",Таблица7[[#This Row],[Цена]]*Таблица7[[#This Row],[Заказ]],"") -> 0 | F78: =IF(OR(ISBLANK(C78),(I78)>0),"","предзаказ в течение 1-3 рабочих дней") -> предзаказ в течение 1-3 рабочих дней | G78: =IF(IFERROR(VLOOKUP(Таблица7[[#This Row],[Наименование]],#REF!,2,0),-1)>0,1,IF(IFERROR(VLOOKUP(Таблица7[[#This Row],[Наименование]],#REF!,2,0),-1)>0,2,IF(IFERROR(VLOOKUP(Таблица7[[#This Row],[Наименование]],#REF!,2,0),-1)>0,3,IF(IFERROR(VLOOKUP(Таблица7[[#This Row],[Наименование]],#REF!,2,0),-1)>0,4,)))) -> 0
A79: Аксессуары / Аксессуары и гаджеты / Samsung / Чехол-клавиатура | E79: =IF(Таблица7[[#This Row],[Цена]]<>"",Таблица7[[#This Row],[Цена]]*Таблица7[[#This Row],[Заказ]],"") | F79: =IF(OR(ISBLANK(C79),(I79)>0),"","предзаказ в течение 1-3 рабочих дней") | G79: =IF(IFERROR(VLOOKUP(Таблица7[[#This Row],[Наименование]],#REF!,2,0),-1)>0,1,IF(IFERROR(VLOOKUP(Таблица7[[#This Row],[Наименование]],#REF!,2,0),-1)>0,2,IF(IFERROR(VLOOKUP(Таблица7[[#This Row],[Наименование]],#REF!,2,0),-1)>0,3,IF(IFERROR(VLOOKUP(Таблица7[[#This Row],[Наименование]],#REF!,2,0),-1)>0,4,)))) -> 0
A80: 902172-1RUS | B80: Чехол-клавиатура Samsung Book Cover для Galaxy Tab S9/S9 FE/S10 FE/S10 Lite Black RUS | C80: 18400 | E80: =IF(Таблица7[[#This Row],[Цена]]<>"",Таблица7[[#This Row],[Цена]]*Таблица7[[#This Row],[Заказ]],"") -> 0 | F80: =IF(OR(ISBLANK(C80),(I80)>0),"","предзаказ в течение 1-3 рабочих дней") -> предзаказ в течение 1-3 рабочих дней | G80: =IF(IFERROR(VLOOKUP(Таблица7[[#This Row],[Наименование]],#REF!,2,0),-1)>0,1,IF(IFERROR(VLOOKUP(Таблица7[[#This Row],[Наименование]],#REF!,2,0),-1)>0,2,IF(IFERROR(VLOOKUP(Таблица7[[#This Row],[Наименование]],#REF!,2,0),-1)>0,3,IF(IFERROR(VLOOKUP(Таблица7[[#This Row],[Наименование]],#REF!,2,0),-1)>0,4,)))) -> 0
A81: Аксессуары / Аксессуары и гаджеты / Sber | E81: =IF(Таблица7[[#This Row],[Цена]]<>"",Таблица7[[#This Row],[Цена]]*Таблица7[[#This Row],[Заказ]],"") | F81: =IF(OR(ISBLANK(C81),(I81)>0),"","предзаказ в течение 1-3 рабочих дней") | G81: =IF(IFERROR(VLOOKUP(Таблица7[[#This Row],[Наименование]],#REF!,2,0),-1)>0,1,IF(IFERROR(VLOOKUP(Таблица7[[#This Row],[Наименование]],#REF!,2,0),-1)>0,2,IF(IFERROR(VLOOKUP(Таблица7[[#This Row],[Наименование]],#REF!,2,0),-1)>0,3,IF(IFERROR(VLOOKUP(Таблица7[[#This Row],[Наименование]],#REF!,2,0),-1)>0,4,)))) -> 0
A82: 910001-2RUS | B82: Умная колонка SberBoom Home Blue RUS | C82: 3900 | E82: =IF(Таблица7[[#This Row],[Цена]]<>"",Таблица7[[#This Row],[Цена]]*Таблица7[[#This Row],[Заказ]],"") -> 0 | F82: =IF(OR(ISBLANK(C82),(I82)>0),"","предзаказ в течение 1-3 рабочих дней") -> предзаказ в течение 1-3 рабочих дней | G82: =IF(IFERROR(VLOOKUP(Таблица7[[#This Row],[Наименование]],#REF!,2,0),-1)>0,1,IF(IFERROR(VLOOKUP(Таблица7[[#This Row],[Наименование]],#REF!,2,0),-1)>0,2,IF(IFERROR(VLOOKUP(Таблица7[[#This Row],[Наименование]],#REF!,2,0),-1)>0,3,IF(IFERROR(VLOOKUP(Таблица7[[#This Row],[Наименование]],#REF!,2,0),-1)>0,4,)))) -> 0
A83: 910001-4RUS | B83: Умная колонка SberBoom Home Brown RUS | C83: 3900 | E83: =IF(Таблица7[[#This Row],[Цена]]<>"",Таблица7[[#This Row],[Цена]]*Таблица7[[#This Row],[Заказ]],"") -> 0 | F83: =IF(OR(ISBLANK(C83),(I83)>0),"","предзаказ в течение 1-3 рабочих дней") -> предзаказ в течение 1-3 рабочих дней | G83: =IF(IFERROR(VLOOKUP(Таблица7[[#This Row],[Наименование]],#REF!,2,0),-1)>0,1,IF(IFERROR(VLOOKUP(Таблица7[[#This Row],[Наименование]],#REF!,2,0),-1)>0,2,IF(IFERROR(VLOOKUP(Таблица7[[#This Row],[Наименование]],#REF!,2,0),-1)>0,3,IF(IFERROR(VLOOKUP(Таблица7[[#This Row],[Наименование]],#REF!,2,0),-1)>0,4,)))) -> 0
A84: 910000-3RUS | B84: Умная колонка SberBoom Mini 2 Gray RUS | C84: 1200 | E84: =IF(Таблица7[[#This Row],[Цена]]<>"",Таблица7[[#This Row],[Цена]]*Таблица7[[#This Row],[Заказ]],"") -> 0 | F84: =IF(OR(ISBLANK(C84),(I84)>0),"","предзаказ в течение 1-3 рабочих дней") -> предзаказ в течение 1-3 рабочих дней | G84: =IF(IFERROR(VLOOKUP(Таблица7[[#This Row],[Наименование]],#REF!,2,0),-1)>0,1,IF(IFERROR(VLOOKUP(Таблица7[[#This Row],[Наименование]],#REF!,2,0),-1)>0,2,IF(IFERROR(VLOOKUP(Таблица7[[#This Row],[Наименование]],#REF!,2,0),-1)>0,3,IF(IFERROR(VLOOKUP(Таблица7[[#This Row],[Наименование]],#REF!,2,0),-1)>0,4,)))) -> 0
A85: 910000-4RUS | B85: Умная колонка SberBoom Mini 2 Yellow RUS | C85: 1200 | E85: =IF(Таблица7[[#This Row],[Цена]]<>"",Таблица7[[#This Row],[Цена]]*Таблица7[[#This Row],[Заказ]],"") -> 0 | F85: =IF(OR(ISBLANK(C85),(I85)>0),"","предзаказ в течение 1-3 рабочих дней") -> предзаказ в течение 1-3 рабочих дней | G85: =IF(IFERROR(VLOOKUP(Таблица7[[#This Row],[Наименование]],#REF!,2,0),-1)>0,1,IF(IFERROR(VLOOKUP(Таблица7[[#This Row],[Наименование]],#REF!,2,0),-1)>0,2,IF(IFERROR(VLOOKUP(Таблица7[[#This Row],[Наименование]],#REF!,2,0),-1)>0,3,IF(IFERROR(VLOOKUP(Таблица7[[#This Row],[Наименование]],#REF!,2,0),-1)>0,4,)))) -> 0
A86: Аксессуары / Аксессуары и гаджеты / TP-LINK | E86: =IF(Таблица7[[#This Row],[Цена]]<>"",Таблица7[[#This Row],[Цена]]*Таблица7[[#This Row],[Заказ]],"") | F86: =IF(OR(ISBLANK(C86),(I86)>0),"","предзаказ в течение 1-3 рабочих дней") | G86: =IF(IFERROR(VLOOKUP(Таблица7[[#This Row],[Наименование]],#REF!,2,0),-1)>0,1,IF(IFERROR(VLOOKUP(Таблица7[[#This Row],[Наименование]],#REF!,2,0),-1)>0,2,IF(IFERROR(VLOOKUP(Таблица7[[#This Row],[Наименование]],#REF!,2,0),-1)>0,3,IF(IFERROR(VLOOKUP(Таблица7[[#This Row],[Наименование]],#REF!,2,0),-1)>0,4,)))) -> 0
A87: 801158RUS | B87: Сетевой адаптер PCI Express с поддержкой Wi-Fi TP-LINK (TL-WN881ND) N300 RUS | C87: 1200 | E87: =IF(Таблица7[[#This Row],[Цена]]<>"",Таблица7[[#This Row],[Цена]]*Таблица7[[#This Row],[Заказ]],"") -> 0 | F87: =IF(OR(ISBLANK(C87),(I87)>0),"","предзаказ в течение 1-3 рабочих дней") -> предзаказ в течение 1-3 рабочих дней | G87: =IF(IFERROR(VLOOKUP(Таблица7[[#This Row],[Наименование]],#REF!,2,0),-1)>0,1,IF(IFERROR(VLOOKUP(Таблица7[[#This Row],[Наименование]],#REF!,2,0),-1)>0,2,IF(IFERROR(VLOOKUP(Таблица7[[#This Row],[Наименование]],#REF!,2,0),-1)>0,3,IF(IFERROR(VLOOKUP(Таблица7[[#This Row],[Наименование]],#REF!,2,0),-1)>0,4,)))) -> 0
A88: Аксессуары / Аксессуары и гаджеты / Vention | E88: =IF(Таблица7[[#This Row],[Цена]]<>"",Таблица7[[#This Row],[Цена]]*Таблица7[[#This Row],[Заказ]],"") | F88: =IF(OR(ISBLANK(C88),(I88)>0),"","предзаказ в течение 1-3 рабочих дней") | G88: =IF(IFERROR(VLOOKUP(Таблица7[[#This Row],[Наименование]],#REF!,2,0),-1)>0,1,IF(IFERROR(VLOOKUP(Таблица7[[#This Row],[Наименование]],#REF!,2,0),-1)>0,2,IF(IFERROR(VLOOKUP(Таблица7[[#This Row],[Наименование]],#REF!,2,0),-1)>0,3,IF(IFERROR(VLOOKUP(Таблица7[[#This Row],[Наименование]],#REF!,2,0),-1)>0,4,)))) -> 0
A89: 16376RUS | B89: Вставка Vention Keystone Jack Cat.5e UTP (IPAW0) White RUS | C89: 300 | E89: =IF(Таблица7[[#This Row],[Цена]]<>"",Таблица7[[#This Row],[Цена]]*Таблица7[[#This Row],[Заказ]],"") -> 0 | F89: =IF(OR(ISBLANK(C89),(I89)>0),"","предзаказ в течение 1-3 рабочих дней") -> предзаказ в течение 1-3 рабочих дней | G89: =IF(IFERROR(VLOOKUP(Таблица7[[#This Row],[Наименование]],#REF!,2,0),-1)>0,1,IF(IFERROR(VLOOKUP(Таблица7[[#This Row],[Наименование]],#REF!,2,0),-1)>0,2,IF(IFERROR(VLOOKUP(Таблица7[[#This Row],[Наименование]],#REF!,2,0),-1)>0,3,IF(IFERROR(VLOOKUP(Таблица7[[#This Row],[Наименование]],#REF!,2,0),-1)>0,4,)))) -> 0
A90: 16378RUS | B90: Вставка Vention Keystone Jack Cat.6 неэкранированный 180 градусов (IRHW0) White RUS | C90: 300 | E90: =IF(Таблица7[[#This Row],[Цена]]<>"",Таблица7[[#This Row],[Цена]]*Таблица7[[#This Row],[Заказ]],"") -> 0 | F90: =IF(OR(ISBLANK(C90),(I90)>0),"","предзаказ в течение 1-3 рабочих дней") -> предзаказ в течение 1-3 рабочих дней | G90: =IF(IFERROR(VLOOKUP(Таблица7[[#This Row],[Наименование]],#REF!,2,0),-1)>0,1,IF(IFERROR(VLOOKUP(Таблица7[[#This Row],[Наименование]],#REF!,2,0),-1)>0,2,IF(IFERROR(VLOOKUP(Таблица7[[#This Row],[Наименование]],#REF!,2,0),-1)>0,3,IF(IFERROR(VLOOKUP(Таблица7[[#This Row],[Наименование]],#REF!,2,0),-1)>0,4,)))) -> 0
A91: 16381RUS | B91: Лицевая панель Vention под модуль Keystone (IFBW0) White RUS | C91: 200 | E91: =IF(Таблица7[[#This Row],[Цена]]<>"",Таблица7[[#This Row],[Цена]]*Таблица7[[#This Row],[Заказ]],"") -> 0 | F91: =IF(OR(ISBLANK(C91),(I91)>0),"","предзаказ в течение 1-3 рабочих дней") -> предзаказ в течение 1-3 рабочих дней | G91: =IF(IFERROR(VLOOKUP(Таблица7[[#This Row],[Наименование]],#REF!,2,0),-1)>0,1,IF(IFERROR(VLOOKUP(Таблица7[[#This Row],[Наименование]],#REF!,2,0),-1)>0,2,IF(IFERROR(VLOOKUP(Таблица7[[#This Row],[Наименование]],#REF!,2,0),-1)>0,3,IF(IFERROR(VLOOKUP(Таблица7[[#This Row],[Наименование]],#REF!,2,0),-1)>0,4,)))) -> 0
A92: 16380RUS | B92: Лицевая панель Vention под модуль Keystone (IFDW0) White RUS | C92: 300 | E92: =IF(Таблица7[[#This Row],[Цена]]<>"",Таблица7[[#This Row],[Цена]]*Таблица7[[#This Row],[Заказ]],"") -> 0 | F92: =IF(OR(ISBLANK(C92),(I92)>0),"","предзаказ в течение 1-3 рабочих дней") -> предзаказ в течение 1-3 рабочих дней | G92: =IF(IFERROR(VLOOKUP(Таблица7[[#This Row],[Наименование]],#REF!,2,0),-1)>0,1,IF(IFERROR(VLOOKUP(Таблица7[[#This Row],[Наименование]],#REF!,2,0),-1)>0,2,IF(IFERROR(VLOOKUP(Таблица7[[#This Row],[Наименование]],#REF!,2,0),-1)>0,3,IF(IFERROR(VLOOKUP(Таблица7[[#This Row],[Наименование]],#REF!,2,0),-1)>0,4,)))) -> 0
A93: 16457RUS | B93: Мультифункциональный инструмент для зачистки коаксиального кабеля Vention KEBL0 (KEBL0) RUS | C93: 800 | E93: =IF(Таблица7[[#This Row],[Цена]]<>"",Таблица7[[#This Row],[Цена]]*Таблица7[[#This Row],[Заказ]],"") -> 0 | F93: =IF(OR(ISBLANK(C93),(I93)>0),"","предзаказ в течение 1-3 рабочих дней") -> предзаказ в течение 1-3 рабочих дней | G93: =IF(IFERROR(VLOOKUP(Таблица7[[#This Row],[Наименование]],#REF!,2,0),-1)>0,1,IF(IFERROR(VLOOKUP(Таблица7[[#This Row],[Наименование]],#REF!,2,0),-1)>0,2,IF(IFERROR(VLOOKUP(Таблица7[[#This Row],[Наименование]],#REF!,2,0),-1)>0,3,IF(IFERROR(VLOOKUP(Таблица7[[#This Row],[Наименование]],#REF!,2,0),-1)>0,4,)))) -> 0
A94: 16382RUS | B94: Обжимной инструмент Vention (KEAB0) для витой пары с фиксатором RUS | C94: 1000 | E94: =IF(Таблица7[[#This Row],[Цена]]<>"",Таблица7[[#This Row],[Цена]]*Таблица7[[#This Row],[Заказ]],"") -> 0 | F94: =IF(OR(ISBLANK(C94),(I94)>0),"","предзаказ в течение 1-3 рабочих дней") -> предзаказ в течение 1-3 рабочих дней | G94: =IF(IFERROR(VLOOKUP(Таблица7[[#This Row],[Наименование]],#REF!,2,0),-1)>0,1,IF(IFERROR(VLOOKUP(Таблица7[[#This Row],[Наименование]],#REF!,2,0),-1)>0,2,IF(IFERROR(VLOOKUP(Таблица7[[#This Row],[Наименование]],#REF!,2,0),-1)>0,3,IF(IFERROR(VLOOKUP(Таблица7[[#This Row],[Наименование]],#REF!,2,0),-1)>0,4,)))) -> 0
A95: Аксессуары / Аксессуары и гаджеты / Xiaomi / Гаджеты / Бритвы | E95: =IF(Таблица7[[#This Row],[Цена]]<>"",Таблица7[[#This Row],[Цена]]*Таблица7[[#This Row],[Заказ]],"") | F95: =IF(OR(ISBLANK(C95),(I95)>0),"","предзаказ в течение 1-3 рабочих дней") | G95: =IF(IFERROR(VLOOKUP(Таблица7[[#This Row],[Наименование]],#REF!,2,0),-1)>0,1,IF(IFERROR(VLOOKUP(Таблица7[[#This Row],[Наименование]],#REF!,2,0),-1)>0,2,IF(IFERROR(VLOOKUP(Таблица7[[#This Row],[Наименование]],#REF!,2,0),-1)>0,3,IF(IFERROR(VLOOKUP(Таблица7[[#This Row],[Наименование]],#REF!,2,0),-1)>0,4,)))) -> 0
A96: 811021-1 | B96: Электробритва Xiaomi ENCHEN BlackStone Sahver Black | C96: 300 | E96: =IF(Таблица7[[#This Row],[Цена]]<>"",Таблица7[[#This Row],[Цена]]*Таблица7[[#This Row],[Заказ]],"") -> 0 | F96: =IF(OR(ISBLANK(C96),(I96)>0),"","предзаказ в течение 1-3 рабочих дней") -> предзаказ в течение 1-3 рабочих дней | G96: =IF(IFERROR(VLOOKUP(Таблица7[[#This Row],[Наименование]],#REF!,2,0),-1)>0,1,IF(IFERROR(VLOOKUP(Таблица7[[#This Row],[Наименование]],#REF!,2,0),-1)>0,2,IF(IFERROR(VLOOKUP(Таблица7[[#This Row],[Наименование]],#REF!,2,0),-1)>0,3,IF(IFERROR(VLOOKUP(Таблица7[[#This Row],[Наименование]],#REF!,2,0),-1)>0,4,)))) -> 0
A97: 811021 | B97: Электробритва Xiaomi ENCHEN BlackStone Shaver Black/Grey | C97: 300 | E97: =IF(Таблица7[[#This Row],[Цена]]<>"",Таблица7[[#This Row],[Цена]]*Таблица7[[#This Row],[Заказ]],"") -> 0 | F97: =IF(OR(ISBLANK(C97),(I97)>0),"","предзаказ в течение 1-3 рабочих дней") -> предзаказ в течение 1-3 рабочих дней | G97: =IF(IFERROR(VLOOKUP(Таблица7[[#This Row],[Наименование]],#REF!,2,0),-1)>0,1,IF(IFERROR(VLOOKUP(Таблица7[[#This Row],[Наименование]],#REF!,2,0),-1)>0,2,IF(IFERROR(VLOOKUP(Таблица7[[#This Row],[Наименование]],#REF!,2,0),-1)>0,3,IF(IFERROR(VLOOKUP(Таблица7[[#This Row],[Наименование]],#REF!,2,0),-1)>0,4,)))) -> 0
A98: Аксессуары / Аксессуары и гаджеты / Xiaomi / Гаджеты / Гаджеты | E98: =IF(Таблица7[[#This Row],[Цена]]<>"",Таблица7[[#This Row],[Цена]]*Таблица7[[#This Row],[Заказ]],"") | F98: =IF(OR(ISBLANK(C98),(I98)>0),"","предзаказ в течение 1-3 рабочих дней") | G98: =IF(IFERROR(VLOOKUP(Таблица7[[#This Row],[Наименование]],#REF!,2,0),-1)>0,1,IF(IFERROR(VLOOKUP(Таблица7[[#This Row],[Наименование]],#REF!,2,0),-1)>0,2,IF(IFERROR(VLOOKUP(Таблица7[[#This Row],[Наименование]],#REF!,2,0),-1)>0,3,IF(IFERROR(VLOOKUP(Таблица7[[#This Row],[Наименование]],#REF!,2,0),-1)>0,4,)))) -> 0
A99: 404021-5 | B99: Xiaomi перчатки для сенсорных экранов (Коричневый) (XMST01MT) | C99: 200 | E99: =IF(Таблица7[[#This Row],[Цена]]<>"",Таблица7[[#This Row],[Цена]]*Таблица7[[#This Row],[Заказ]],"") -> 0 | F99: =IF(OR(ISBLANK(C99),(I99)>0),"","предзаказ в течение 1-3 рабочих дней") -> предзаказ в течение 1-3 рабочих дней | G99: =IF(IFERROR(VLOOKUP(Таблица7[[#This Row],[Наименование]],#REF!,2,0),-1)>0,1,IF(IFERROR(VLOOKUP(Таблица7[[#This Row],[Наименование]],#REF!,2,0),-1)>0,2,IF(IFERROR(VLOOKUP(Таблица7[[#This Row],[Наименование]],#REF!,2,0),-1)>0,3,IF(IFERROR(VLOOKUP(Таблица7[[#This Row],[Наименование]],#REF!,2,0),-1)>0,4,)))) -> 0
A100: 404021-2 | B100: Xiaomi перчатки для сенсорных экранов (Серый) (XMST01MT) | C100: 200 | E100: =IF(Таблица7[[#This Row],[Цена]]<>"",Таблица7[[#This Row],[Цена]]*Таблица7[[#This Row],[Заказ]],"") -> 0 | F100: =IF(OR(ISBLANK(C100),(I100)>0),"","предзаказ в течение 1-3 рабочих дней") -> предзаказ в течение 1-3 рабочих дней | G100: =IF(IFERROR(VLOOKUP(Таблица7[[#This Row],[Наименование]],#REF!,2,0),-1)>0,1,IF(IFERROR(VLOOKUP(Таблица7[[#This Row],[Наименование]],#REF!,2,0),-1)>0,2,IF(IFERROR(VLOOKUP(Таблица7[[#This Row],[Наименование]],#REF!,2,0),-1)>0,3,IF(IFERROR(VLOOKUP(Таблица7[[#This Row],[Наименование]],#REF!,2,0),-1)>0,4,)))) -> 0
A101: 404021-4 | B101: Xiaomi перчатки для сенсорных экранов (Синий) (XMST01MT) | C101: 200 | E101: =IF(Таблица7[[#This Row],[Цена]]<>"",Таблица7[[#This Row],[Цена]]*Таблица7[[#This Row],[Заказ]],"") -> 0 | F101: =IF(OR(ISBLANK(C101),(I101)>0),"","предзаказ в течение 1-3 рабочих дней") -> предзаказ в течение 1-3 рабочих дней | G101: =IF(IFERROR(VLOOKUP(Таблица7[[#This Row],[Наименование]],#REF!,2,0),-1)>0,1,IF(IFERROR(VLOOKUP(Таблица7[[#This Row],[Наименование]],#REF!,2,0),-1)>0,2,IF(IFERROR(VLOOKUP(Таблица7[[#This Row],[Наименование]],#REF!,2,0),-1)>0,3,IF(IFERROR(VLOOKUP(Таблица7[[#This Row],[Наименование]],#REF!,2,0),-1)>0,4,)))) -> 0
A102: 404021-3 | B102: Xiaomi перчатки для сенсорных экранов (Черный) (XMST01MT) | C102: 200 | E102: =IF(Таблица7[[#This Row],[Цена]]<>"",Таблица7[[#This Row],[Цена]]*Таблица7[[#This Row],[Заказ]],"") -> 0 | F102: =IF(OR(ISBLANK(C102),(I102)>0),"","предзаказ в течение 1-3 рабочих дней") -> предзаказ в течение 1-3 рабочих дней | G102: =IF(IFERROR(VLOOKUP(Таблица7[[#This Row],[Наименование]],#REF!,2,0),-1)>0,1,IF(IFERROR(VLOOKUP(Таблица7[[#This Row],[Наименование]],#REF!,2,0),-1)>0,2,IF(IFERROR(VLOOKUP(Таблица7[[#This Row],[Наименование]],#REF!,2,0),-1)>0,3,IF(IFERROR(VLOOKUP(Таблица7[[#This Row],[Наименование]],#REF!,2,0),-1)>0,4,)))) -> 0
A103: 914520-1RUS | B103: Умные очки Xiaomi Mijia Smart Audio Glasses Aviator (BHR08VYGL) Black RUS | C103: 15400 | E103: =IF(Таблица7[[#This Row],[Цена]]<>"",Таблица7[[#This Row],[Цена]]*Таблица7[[#This Row],[Заказ]],"") -> 0 | F103: =IF(OR(ISBLANK(C103),(I103)>0),"","предзаказ в течение 1-3 рабочих дней") -> предзаказ в течение 1-3 рабочих дней | G103: =IF(IFERROR(VLOOKUP(Таблица7[[#This Row],[Наименование]],#REF!,2,0),-1)>0,1,IF(IFERROR(VLOOKUP(Таблица7[[#This Row],[Наименование]],#REF!,2,0),-1)>0,2,IF(IFERROR(VLOOKUP(Таблица7[[#This Row],[Наименование]],#REF!,2,0),-1)>0,3,IF(IFERROR(VLOOKUP(Таблица7[[#This Row],[Наименование]],#REF!,2,0),-1)>0,4,)))) -> 0
A104: 914520-2RUS | B104: Умные очки Xiaomi Mijia Smart Audio Glasses Browline (BHR08VXGL) Black RUS | C104: 15400 | E104: =IF(Таблица7[[#This Row],[Цена]]<>"",Таблица7[[#This Row],[Цена]]*Таблица7[[#This Row],[Заказ]],"") -> 0 | F104: =IF(OR(ISBLANK(C104),(I104)>0),"","предзаказ в течение 1-3 рабочих дней") -> предзаказ в течение 1-3 рабочих дней | G104: =IF(IFERROR(VLOOKUP(Таблица7[[#This Row],[Наименование]],#REF!,2,0),-1)>0,1,IF(IFERROR(VLOOKUP(Таблица7[[#This Row],[Наименование]],#REF!,2,0),-1)>0,2,IF(IFERROR(VLOOKUP(Таблица7[[#This Row],[Наименование]],#REF!,2,0),-1)>0,3,IF(IFERROR(VLOOKUP(Таблица7[[#This Row],[Наименование]],#REF!,2,0),-1)>0,4,)))) -> 0
...

Sheet Гаджеты и МБТ. Выгодно
A1: 5.Аксессуары и гаджеты. Наличные и б/н с НДС 5% | B1: Назад в оглавление
A2: Аксессуары(наличные). Отгрузка со склада "Рубин". Предоплата 100% | D2: итого | E2: =SUM(Таблица729[Заказ]) -> 0 | F2: =SUM(Таблица729[Сумма заказа]) -> 0
A3: Код | B3: Наименование | C3: остаток | D3: Цена | E3: Заказ | F3: Сумма заказа | G3: Особенности заказа | H3: Особенности заказа2
F4: =IF(Таблица729[[#This Row],[Цена]]<>"",Таблица729[[#This Row],[Цена]]*Таблица729[[#This Row],[Заказ]],"") | G4: =IF(OR(ISBLANK(D4),(J4)>0),"","предзаказ в течение 1-3 рабочих дней") | H4: =IF(IFERROR(VLOOKUP(Таблица729[[#This Row],[Наименование]],#REF!,2,0),-1)>0,1001,IF(IFERROR(VLOOKUP(Таблица729[[#This Row],[Наименование]],#REF!,2,0),-1)>0,50,IF(IFERROR(VLOOKUP(Таблица729[[#This Row],[Наименование]],#REF!,2,0),-1)>0,1002,IF(IFERROR(VLOOKUP(Таблица729[[#This Row],[Наименование]],#REF!,2,0),-1)>0,1003,)))) -> 0
F5: =IF(Таблица729[[#This Row],[Цена]]<>"",Таблица729[[#This Row],[Цена]]*Таблица729[[#This Row],[Заказ]],"") | G5: =IF(OR(ISBLANK(D5),(J5)>0),"","предзаказ в течение 1-3 рабочих дней") | H5: =IF(IFERROR(VLOOKUP(Таблица729[[#This Row],[Наименование]],#REF!,2,0),-1)>0,1001,IF(IFERROR(VLOOKUP(Таблица729[[#This Row],[Наименование]],#REF!,2,0),-1)>0,50,IF(IFERROR(VLOOKUP(Таблица729[[#This Row],[Наименование]],#REF!,2,0),-1)>0,1002,IF(IFERROR(VLOOKUP(Таблица729[[#This Row],[Наименование]],#REF!,2,0),-1)>0,1003,)))) -> 0
F6: =IF(Таблица729[[#This Row],[Цена]]<>"",Таблица729[[#This Row],[Цена]]*Таблица729[[#This Row],[Заказ]],"") | G6: =IF(OR(ISBLANK(D6),(J6)>0),"","предзаказ в течение 1-3 рабочих дней") | H6: =IF(IFERROR(VLOOKUP(Таблица729[[#This Row],[Наименование]],#REF!,2,0),-1)>0,1001,IF(IFERROR(VLOOKUP(Таблица729[[#This Row],[Наименование]],#REF!,2,0),-1)>0,50,IF(IFERROR(VLOOKUP(Таблица729[[#This Row],[Наименование]],#REF!,2,0),-1)>0,1002,IF(IFERROR(VLOOKUP(Таблица729[[#This Row],[Наименование]],#REF!,2,0),-1)>0,1003,)))) -> 0
F7: =IF(Таблица729[[#This Row],[Цена]]<>"",Таблица729[[#This Row],[Цена]]*Таблица729[[#This Row],[Заказ]],"") | G7: =IF(OR(ISBLANK(D7),(J7)>0),"","предзаказ в течение 1-3 рабочих дней") | H7: =IF(IFERROR(VLOOKUP(Таблица729[[#This Row],[Наименование]],#REF!,2,0),-1)>0,1001,IF(IFERROR(VLOOKUP(Таблица729[[#This Row],[Наименование]],#REF!,2,0),-1)>0,50,IF(IFERROR(VLOOKUP(Таблица729[[#This Row],[Наименование]],#REF!,2,0),-1)>0,1002,IF(IFERROR(VLOOKUP(Таблица729[[#This Row],[Наименование]],#REF!,2,0),-1)>0,1003,)))) -> 0
F8: =IF(Таблица729[[#This Row],[Цена]]<>"",Таблица729[[#This Row],[Цена]]*Таблица729[[#This Row],[Заказ]],"") | G8: =IF(OR(ISBLANK(D8),(J8)>0),"","предзаказ в течение 1-3 рабочих дней") | H8: =IF(IFERROR(VLOOKUP(Таблица729[[#This Row],[Наименование]],#REF!,2,0),-1)>0,1001,IF(IFERROR(VLOOKUP(Таблица729[[#This Row],[Наименование]],#REF!,2,0),-1)>0,50,IF(IFERROR(VLOOKUP(Таблица729[[#This Row],[Наименование]],#REF!,2,0),-1)>0,1002,IF(IFERROR(VLOOKUP(Таблица729[[#This Row],[Наименование]],#REF!,2,0),-1)>0,1003,)))) -> 0
F9: =IF(Таблица729[[#This Row],[Цена]]<>"",Таблица729[[#This Row],[Цена]]*Таблица729[[#This Row],[Заказ]],"") | G9: =IF(OR(ISBLANK(D9),(J9)>0),"","предзаказ в течение 1-3 рабочих дней") | H9: =IF(IFERROR(VLOOKUP(Таблица729[[#This Row],[Наименование]],#REF!,2,0),-1)>0,1001,IF(IFERROR(VLOOKUP(Таблица729[[#This Row],[Наименование]],#REF!,2,0),-1)>0,50,IF(IFERROR(VLOOKUP(Таблица729[[#This Row],[Наименование]],#REF!,2,0),-1)>0,1002,IF(IFERROR(VLOOKUP(Таблица729[[#This Row],[Наименование]],#REF!,2,0),-1)>0,1003,)))) -> 0
F10: =IF(Таблица729[[#This Row],[Цена]]<>"",Таблица729[[#This Row],[Цена]]*Таблица729[[#This Row],[Заказ]],"") | G10: =IF(OR(ISBLANK(D10),(J10)>0),"","предзаказ в течение 1-3 рабочих дней") | H10: =IF(IFERROR(VLOOKUP(Таблица729[[#This Row],[Наименование]],#REF!,2,0),-1)>0,1001,IF(IFERROR(VLOOKUP(Таблица729[[#This Row],[Наименование]],#REF!,2,0),-1)>0,50,IF(IFERROR(VLOOKUP(Таблица729[[#This Row],[Наименование]],#REF!,2,0),-1)>0,1002,IF(IFERROR(VLOOKUP(Таблица729[[#This Row],[Наименование]],#REF!,2,0),-1)>0,1003,)))) -> 0
F11: =IF(Таблица729[[#This Row],[Цена]]<>"",Таблица729[[#This Row],[Цена]]*Таблица729[[#This Row],[Заказ]],"") | G11: =IF(OR(ISBLANK(D11),(J11)>0),"","предзаказ в течение 1-3 рабочих дней") | H11: =IF(IFERROR(VLOOKUP(Таблица729[[#This Row],[Наименование]],#REF!,2,0),-1)>0,1001,IF(IFERROR(VLOOKUP(Таблица729[[#This Row],[Наименование]],#REF!,2,0),-1)>0,50,IF(IFERROR(VLOOKUP(Таблица729[[#This Row],[Наименование]],#REF!,2,0),-1)>0,1002,IF(IFERROR(VLOOKUP(Таблица729[[#This Row],[Наименование]],#REF!,2,0),-1)>0,1003,)))) -> 0
F12: =IF(Таблица729[[#This Row],[Цена]]<>"",Таблица729[[#This Row],[Цена]]*Таблица729[[#This Row],[Заказ]],"") | G12: =IF(OR(ISBLANK(D12),(J12)>0),"","предзаказ в течение 1-3 рабочих дней") | H12: =IF(IFERROR(VLOOKUP(Таблица729[[#This Row],[Наименование]],#REF!,2,0),-1)>0,1001,IF(IFERROR(VLOOKUP(Таблица729[[#This Row],[Наименование]],#REF!,2,0),-1)>0,50,IF(IFERROR(VLOOKUP(Таблица729[[#This Row],[Наименование]],#REF!,2,0),-1)>0,1002,IF(IFERROR(VLOOKUP(Таблица729[[#This Row],[Наименование]],#REF!,2,0),-1)>0,1003,)))) -> 0
F13: =IF(Таблица729[[#This Row],[Цена]]<>"",Таблица729[[#This Row],[Цена]]*Таблица729[[#This Row],[Заказ]],"") | G13: =IF(OR(ISBLANK(D13),(J13)>0),"","предзаказ в течение 1-3 рабочих дней") | H13: =IF(IFERROR(VLOOKUP(Таблица729[[#This Row],[Наименование]],#REF!,2,0),-1)>0,1001,IF(IFERROR(VLOOKUP(Таблица729[[#This Row],[Наименование]],#REF!,2,0),-1)>0,50,IF(IFERROR(VLOOKUP(Таблица729[[#This Row],[Наименование]],#REF!,2,0),-1)>0,1002,IF(IFERROR(VLOOKUP(Таблица729[[#This Row],[Наименование]],#REF!,2,0),-1)>0,1003,)))) -> 0
F14: =IF(Таблица729[[#This Row],[Цена]]<>"",Таблица729[[#This Row],[Цена]]*Таблица729[[#This Row],[Заказ]],"") | G14: =IF(OR(ISBLANK(D14),(J14)>0),"","предзаказ в течение 1-3 рабочих дней") | H14: =IF(IFERROR(VLOOKUP(Таблица729[[#This Row],[Наименование]],#REF!,2,0),-1)>0,1001,IF(IFERROR(VLOOKUP(Таблица729[[#This Row],[Наименование]],#REF!,2,0),-1)>0,50,IF(IFERROR(VLOOKUP(Таблица729[[#This Row],[Наименование]],#REF!,2,0),-1)>0,1002,IF(IFERROR(VLOOKUP(Таблица729[[#This Row],[Наименование]],#REF!,2,0),-1)>0,1003,)))) -> 0
F15: =IF(Таблица729[[#This Row],[Цена]]<>"",Таблица729[[#This Row],[Цена]]*Таблица729[[#This Row],[Заказ]],"") | G15: =IF(OR(ISBLANK(D15),(J15)>0),"","предзаказ в течение 1-3 рабочих дней") | H15: =IF(IFERROR(VLOOKUP(Таблица729[[#This Row],[Наименование]],#REF!,2,0),-1)>0,1001,IF(IFERROR(VLOOKUP(Таблица729[[#This Row],[Наименование]],#REF!,2,0),-1)>0,50,IF(IFERROR(VLOOKUP(Таблица729[[#This Row],[Наименование]],#REF!,2,0),-1)>0,1002,IF(IFERROR(VLOOKUP(Таблица729[[#This Row],[Наименование]],#REF!,2,0),-1)>0,1003,)))) -> 0
... F28: =IF(Таблица729[[#This Row],[Цена]]<>"",Таблица729[[#This Row],[Цена]]*Таблица729[[#This Row],[Заказ]],"") | G28: =IF(OR(ISBLANK(D28),(J28)>0),"","предзаказ в течение 1-3 рабочих дней") | H28: =IF(IFERROR(VLOOKUP(Таблица729[[#This Row],[Наименование]],#REF!,2,0),-1)>0,1001,IF(IFERROR(VLOOKUP(Таблица729[[#This Row],[Наименование]],#REF!,2,0),-1)>0,50,IF(IFERROR(VLOOKUP(Таблица729[[#This Row],[Наименование]],#REF!,2,0),-1)>0,1002,IF(IFERROR(VLOOKUP(Таблица729[[#This Row],[Наименование]],#REF!,2,0),-1)>0,1003,)))) -> 0
F29: =IF(Таблица729[[#This Row],[Цена]]<>"",Таблица729[[#This Row],[Цена]]*Таблица729[[#This Row],[Заказ]],"") | G29: =IF(OR(ISBLANK(D29),(J29)>0),"","предзаказ в течение 1-3 рабочих дней") | H29: =IF(IFERROR(VLOOKUP(Таблица729[[#This Row],[Наименование]],#REF!,2,0),-1)>0,1,IF(IFERROR(VLOOKUP(Таблица729[[#This Row],[Наименование]],#REF!,2,0),-1)>0,2,IF(IFERROR(VLOOKUP(Таблица729[[#This Row],[Наименование]],#REF!,2,0),-1)>0,3,IF(IFERROR(VLOOKUP(Таблица729[[#This Row],[Наименование]],#REF!,2,0),-1)>0,4,)))) -> 0
F30: =IF(Таблица729[[#This Row],[Цена]]<>"",Таблица729[[#This Row],[Цена]]*Таблица729[[#This Row],[Заказ]],"") | G30: =IF(OR(ISBLANK(D30),(J30)>0),"","предзаказ в течение 1-3 рабочих дней") | H30: =IF(IFERROR(VLOOKUP(Таблица729[[#This Row],[Наименование]],#REF!,2,0),-1)>0,1,IF(IFERROR(VLOOKUP(Таблица729[[#This Row],[Наименование]],#REF!,2,0),-1)>0,2,IF(IFERROR(VLOOKUP(Таблица729[[#This Row],[Наименование]],#REF!,2,0),-1)>0,3,IF(IFERROR(VLOOKUP(Таблица729[[#This Row],[Наименование]],#REF!,2,0),-1)>0,4,)))) -> 0
F31: =IF(Таблица729[[#This Row],[Цена]]<>"",Таблица729[[#This Row],[Цена]]*Таблица729[[#This Row],[Заказ]],"") | G31: =IF(OR(ISBLANK(D31),(J31)>0),"","предзаказ в течение 1-3 рабочих дней") | H31: =IF(IFERROR(VLOOKUP(Таблица729[[#This Row],[Наименование]],#REF!,2,0),-1)>0,1,IF(IFERROR(VLOOKUP(Таблица729[[#This Row],[Наименование]],#REF!,2,0),-1)>0,2,IF(IFERROR(VLOOKUP(Таблица729[[#This Row],[Наименование]],#REF!,2,0),-1)>0,3,IF(IFERROR(VLOOKUP(Таблица729[[#This Row],[Наименование]],#REF!,2,0),-1)>0,4,)))) -> 0
F32: =IF(Таблица729[[#This Row],[Цена]]<>"",Таблица729[[#This Row],[Цена]]*Таблица729[[#This Row],[Заказ]],"") | G32: =IF(OR(ISBLANK(D32),(J32)>0),"","предзаказ в течение 1-3 рабочих дней") | H32: =IF(IFERROR(VLOOKUP(Таблица729[[#This Row],[Наименование]],#REF!,2,0),-1)>0,1,IF(IFERROR(VLOOKUP(Таблица729[[#This Row],[Наименование]],#REF!,2,0),-1)>0,2,IF(IFERROR(VLOOKUP(Таблица729[[#This Row],[Наименование]],#REF!,2,0),-1)>0,3,IF(IFERROR(VLOOKUP(Таблица729[[#This Row],[Наименование]],#REF!,2,0),-1)>0,4,)))) -> 0
F33: =IF(Таблица729[[#This Row],[Цена]]<>"",Таблица729[[#This Row],[Цена]]*Таблица729[[#This Row],[Заказ]],"") | G33: =IF(OR(ISBLANK(D33),(J33)>0),"","предзаказ в течение 1-3 рабочих дней") | H33: =IF(IFERROR(VLOOKUP(Таблица729[[#This Row],[Наименование]],#REF!,2,0),-1)>0,1,IF(IFERROR(VLOOKUP(Таблица729[[#This Row],[Наименование]],#REF!,2,0),-1)>0,2,IF(IFERROR(VLOOKUP(Таблица729[[#This Row],[Наименование]],#REF!,2,0),-1)>0,3,IF(IFERROR(VLOOKUP(Таблица729[[#This Row],[Наименование]],#REF!,2,0),-1)>0,4,)))) -> 0
F34: =IF(Таблица729[[#This Row],[Цена]]<>"",Таблица729[[#This Row],[Цена]]*Таблица729[[#This Row],[Заказ]],"") | G34: =IF(OR(ISBLANK(D34),(J34)>0),"","предзаказ в течение 1-3 рабочих дней") | H34: =IF(IFERROR(VLOOKUP(Таблица729[[#This Row],[Наименование]],#REF!,2,0),-1)>0,1,IF(IFERROR(VLOOKUP(Таблица729[[#This Row],[Наименование]],#REF!,2,0),-1)>0,2,IF(IFERROR(VLOOKUP(Таблица729[[#This Row],[Наименование]],#REF!,2,0),-1)>0,3,IF(IFERROR(VLOOKUP(Таблица729[[#This Row],[Наименование]],#REF!,2,0),-1)>0,4,)))) -> 0
A35: Итог | E35: =SUBTOTAL(109,Таблица729[Заказ]) -> 0 | F35: =SUBTOTAL(109,Таблица729[Сумма заказа]) -> 0

Sheet Предзаказ аксессуары
A1: 9.Аксессуары и гаджеты.Наличные и б/н с НДС 20%, от 150 тыс | B1: Назад в оглавление
A2: Аксессуары (предзаказ безнал с НДС 20% и наличные)
A3: Срок поставки на наш склад: 1-3 дня. Предоплата 100%
A4: Минимальный заказ: от 150 000р. | D4: итого | E4: =SUM(Таблица62547[Заказ наличные]) -> 0 | F4: =SUM(Таблица62547[заказ б/н]) -> 0 | G4: =SUM(Таблица62547[сумма заказа наличные]) -> 0 | H4: =SUM(Таблица62547[Сумма заказа б/н]) -> 0
A5: бренд | B5: Полное название модели | C5: цена наличные | D5: Цена б/н | E5: Заказ наличные | F5: заказ б/н | G5: сумма заказа наличные | H5: Сумма заказа б/н
G6: =IF(Таблица62547[[#This Row],[Цена б/н]]>0,IFERROR(Таблица62547[[#This Row],[цена наличные]]*Таблица62547[[#This Row],[Заказ наличные]],"-"),"") | H6: =IF(Таблица62547[[#This Row],[Цена б/н]]>0,IFERROR(Таблица62547[[#This Row],[Цена б/н]]*Таблица62547[[#This Row],[заказ б/н]],"-"),"")
G7: =IF(Таблица62547[[#This Row],[Цена б/н]]>0,IFERROR(Таблица62547[[#This Row],[цена наличные]]*Таблица62547[[#This Row],[Заказ наличные]],"-"),"") | H7: =IF(Таблица62547[[#This Row],[Цена б/н]]>0,IFERROR(Таблица62547[[#This Row],[Цена б/н]]*Таблица62547[[#This Row],[заказ б/н]],"-"),"")
G8: =IF(Таблица62547[[#This Row],[Цена б/н]]>0,IFERROR(Таблица62547[[#This Row],[цена наличные]]*Таблица62547[[#This Row],[Заказ наличные]],"-"),"") | H8: =IF(Таблица62547[[#This Row],[Цена б/н]]>0,IFERROR(Таблица62547[[#This Row],[Цена б/н]]*Таблица62547[[#This Row],[заказ б/н]],"-"),"")
G9: =IF(Таблица62547[[#This Row],[Цена б/н]]>0,IFERROR(Таблица62547[[#This Row],[цена наличные]]*Таблица62547[[#This Row],[Заказ наличные]],"-"),"") | H9: =IF(Таблица62547[[#This Row],[Цена б/н]]>0,IFERROR(Таблица62547[[#This Row],[Цена б/н]]*Таблица62547[[#This Row],[заказ б/н]],"-"),"")
G10: =IF(Таблица62547[[#This Row],[Цена б/н]]>0,IFERROR(Таблица62547[[#This Row],[цена наличные]]*Таблица62547[[#This Row],[Заказ наличные]],"-"),"") | H10: =IF(Таблица62547[[#This Row],[Цена б/н]]>0,IFERROR(Таблица62547[[#This Row],[Цена б/н]]*Таблица62547[[#This Row],[заказ б/н]],"-"),"")
G11: =IF(Таблица62547[[#This Row],[Цена б/н]]>0,IFERROR(Таблица62547[[#This Row],[цена наличные]]*Таблица62547[[#This Row],[Заказ наличные]],"-"),"") | H11: =IF(Таблица62547[[#This Row],[Цена б/н]]>0,IFERROR(Таблица62547[[#This Row],[Цена б/н]]*Таблица62547[[#This Row],[заказ б/н]],"-"),"")
G12: =IF(Таблица62547[[#This Row],[Цена б/н]]>0,IFERROR(Таблица62547[[#This Row],[цена наличные]]*Таблица62547[[#This Row],[Заказ наличные]],"-"),"") | H12: =IF(Таблица62547[[#This Row],[Цена б/н]]>0,IFERROR(Таблица62547[[#This Row],[Цена б/н]]*Таблица62547[[#This Row],[заказ б/н]],"-"),"")
G13: =IF(Таблица62547[[#This Row],[Цена б/н]]>0,IFERROR(Таблица62547[[#This Row],[цена наличные]]*Таблица62547[[#This Row],[Заказ наличные]],"-"),"") | H13: =IF(Таблица62547[[#This Row],[Цена б/н]]>0,IFERROR(Таблица62547[[#This Row],[Цена б/н]]*Таблица62547[[#This Row],[заказ б/н]],"-"),"")
G14: =IF(Таблица62547[[#This Row],[Цена б/н]]>0,IFERROR(Таблица62547[[#This Row],[цена наличные]]*Таблица62547[[#This Row],[Заказ наличные]],"-"),"") | H14: =IF(Таблица62547[[#This Row],[Цена б/н]]>0,IFERROR(Таблица62547[[#This Row],[Цена б/н]]*Таблица62547[[#This Row],[заказ б/н]],"-"),"")
G15: =IF(Таблица62547[[#This Row],[Цена б/н]]>0,IFERROR(Таблица62547[[#This Row],[цена наличные]]*Таблица62547[[#This Row],[Заказ наличные]],"-"),"") | H15: =IF(Таблица62547[[#This Row],[Цена б/н]]>0,IFERROR(Таблица62547[[#This Row],[Цена б/н]]*Таблица62547[[#This Row],[заказ б/н]],"-"),"")
G16: =IF(Таблица62547[[#This Row],[Цена б/н]]>0,IFERROR(Таблица62547[[#This Row],[цена наличные]]*Таблица62547[[#This Row],[Заказ наличные]],"-"),"") | H16: =IF(Таблица62547[[#This Row],[Цена б/н]]>0,IFERROR(Таблица62547[[#This Row],[Цена б/н]]*Таблица62547[[#This Row],[заказ б/н]],"-"),"")
G17: =IF(Таблица62547[[#This Row],[Цена б/н]]>0,IFERROR(Таблица62547[[#This Row],[цена наличные]]*Таблица62547[[#This Row],[Заказ наличные]],"-"),"") | H17: =IF(Таблица62547[[#This Row],[Цена б/н]]>0,IFERROR(Таблица62547[[#This Row],[Цена б/н]]*Таблица62547[[#This Row],[заказ б/н]],"-"),"")
... G101: =IF(Таблица62547[[#This Row],[Цена б/н]]>0,IFERROR(Таблица62547[[#This Row],[цена наличные]]*Таблица62547[[#This Row],[Заказ наличные]],"-"),"") | H101: =IF(Таблица62547[[#This Row],[Цена б/н]]>0,IFERROR(Таблица62547[[#This Row],[Цена б/н]]*Таблица62547[[#This Row],[заказ б/н]],"-"),"")
A102: Итог | E102: =SUBTOTAL(109,Таблица62547[Заказ наличные]) -> 0 | F102: =SUBTOTAL(109,Таблица62547[заказ б/н]) -> 0 | G102: =SUBTOTAL(109,Таблица62547[сумма заказа наличные]) -> 0 | H102: =SUBTOTAL(109,Таблица62547[Сумма заказа б/н]) -> 0

Sheet Предзаказ аксессуары(от 150)
A1: Назад в оглавление
A2: Аксессуары (предзаказ, безнал с НДС 22% и наличные)
A3: Срок поставки на наш склад: 1-3 дня. Предоплата 100%
A4: Минимальный заказ: от 150 000р. | F4: итого | G4: =SUM(Таблица625410[Заказ наличные]) -> 0 | H4: =SUM(Таблица625410[заказ б/н]) -> 0 | I4: =SUM(Таблица625410[сумма заказа наличные]) -> 0 | J4: =SUM(Таблица625410[Сумма заказа б/н]) -> 0
A5: категория | B5: бренд | C5: артикул | D5: Полное название модели | E5: цена наличные | F5: Цена б/н | G5: Заказ наличные | H5: заказ б/н | I5: сумма заказа наличные | J5: Сумма заказа б/н
A6: Автотовары | B6: Автотовары | I6: =IF(AND(Таблица625410[[#This Row],[цена наличные]]<>"-",Таблица625410[[#This Row],[цена наличные]]<>""),Таблица625410[[#This Row],[цена наличные]]*Таблица625410[[#This Row],[Заказ наличные]],"") | J6: =IF(AND(Таблица625410[[#This Row],[Цена б/н]]<>"-",Таблица625410[[#This Row],[Цена б/н]]<>""),Таблица625410[[#This Row],[Цена б/н]]*Таблица625410[[#This Row],[заказ б/н]],"")
A7: Автотовары | B7: TTEC | C7: 2TT32 | D7: Автомобильный держатель для телефона TTEC EasyDrive Pro M MagSafe Competible In-Car Holder. Цвет: черный | E7: 687.7289 | F7: 790.493 | I7: =IF(AND(Таблица625410[[#This Row],[цена наличные]]<>"-",Таблица625410[[#This Row],[цена наличные]]<>""),Таблица625410[[#This Row],[цена наличные]]*Таблица625410[[#This Row],[Заказ наличные]],"") -> 0 | J7: =IF(AND(Таблица625410[[#This Row],[Цена б/н]]<>"-",Таблица625410[[#This Row],[Цена б/н]]<>""),Таблица625410[[#This Row],[Цена б/н]]*Таблица625410[[#This Row],[заказ б/н]],"") -> 0
A8: Компрессоры | B8: Компрессоры | I8: =IF(AND(Таблица625410[[#This Row],[цена наличные]]<>"-",Таблица625410[[#This Row],[цена наличные]]<>""),Таблица625410[[#This Row],[цена наличные]]*Таблица625410[[#This Row],[Заказ наличные]],"") | J8: =IF(AND(Таблица625410[[#This Row],[Цена б/н]]<>"-",Таблица625410[[#This Row],[Цена б/н]]<>""),Таблица625410[[#This Row],[Цена б/н]]*Таблица625410[[#This Row],[заказ б/н]],"")
A9: Компрессоры | B9: UGREEN | C9: 35976_ | D9: Портативный насос для шин UGREEN ET723 (35976) Portable Tire Inflator Pro. Цвет: серый космос | E9: 4320.156 | F9: 4965.696 | I9: =IF(AND(Таблица625410[[#This Row],[цена наличные]]<>"-",Таблица625410[[#This Row],[цена наличные]]<>""),Таблица625410[[#This Row],[цена наличные]]*Таблица625410[[#This Row],[Заказ наличные]],"") -> 0 | J9: =IF(AND(Таблица625410[[#This Row],[Цена б/н]]<>"-",Таблица625410[[#This Row],[Цена б/н]]<>""),Таблица625410[[#This Row],[Цена б/н]]*Таблица625410[[#This Row],[заказ б/н]],"") -> 0
A10: Наборы для мойки | B10: Наборы для мойки | I10: =IF(AND(Таблица625410[[#This Row],[цена наличные]]<>"-",Таблица625410[[#This Row],[цена наличные]]<>""),Таблица625410[[#This Row],[цена наличные]]*Таблица625410[[#This Row],[Заказ наличные]],"") | J10: =IF(AND(Таблица625410[[#This Row],[Цена б/н]]<>"-",Таблица625410[[#This Row],[Цена б/н]]<>""),Таблица625410[[#This Row],[Цена б/н]]*Таблица625410[[#This Row],[заказ б/н]],"")
A11: Наборы для мойки | B11: HOTO | C11: HTT0027GL | D11: Набор для уборки Hoto Outdoor Wash Kit (складное ведро, губка, тряпка, QWOGJ002) | E11: 973.7475 | F11: 1119.25 | I11: =IF(AND(Таблица625410[[#This Row],[цена наличные]]<>"-",Таблица625410[[#This Row],[цена наличные]]<>""),Таблица625410[[#This Row],[цена наличные]]*Таблица625410[[#This Row],[Заказ наличные]],"") -> 0 | J11: =IF(AND(Таблица625410[[#This Row],[Цена б/н]]<>"-",Таблица625410[[#This Row],[Цена б/н]]<>""),Таблица625410[[#This Row],[Цена б/н]]*Таблица625410[[#This Row],[заказ б/н]],"") -> 0
A12: Аксессуары | B12: Аксессуары | I12: =IF(AND(Таблица625410[[#This Row],[цена наличные]]<>"-",Таблица625410[[#This Row],[цена наличные]]<>""),Таблица625410[[#This Row],[цена наличные]]*Таблица625410[[#This Row],[Заказ наличные]],"") | J12: =IF(AND(Таблица625410[[#This Row],[Цена б/н]]<>"-",Таблица625410[[#This Row],[Цена б/н]]<>""),Таблица625410[[#This Row],[Цена б/н]]*Таблица625410[[#This Row],[заказ б/н]],"")
A13: Внешние аккумуляторы | B13: Внешние аккумуляторы | I13: =IF(AND(Таблица625410[[#This Row],[цена наличные]]<>"-",Таблица625410[[#This Row],[цена наличные]]<>""),Таблица625410[[#This Row],[цена наличные]]*Таблица625410[[#This Row],[Заказ наличные]],"") | J13: =IF(AND(Таблица625410[[#This Row],[Цена б/н]]<>"-",Таблица625410[[#This Row],[Цена б/н]]<>""),Таблица625410[[#This Row],[Цена б/н]]*Таблица625410[[#This Row],[заказ б/н]],"")
A14: Внешние аккумуляторы | B14: Belkin | C14: CAB011bt1MBW2PK | D14: Кабель Belkin BoostCharge Pro Flex Braided Silicone USB-C To USB-C 2 шт. Длина: 1м. Цвет: черный/белый | E14: 2273.354 | F14: 2613.051 | I14: =IF(AND(Таблица625410[[#This Row],[цена наличные]]<>"-",Таблица625410[[#This Row],[цена наличные]]<>""),Таблица625410[[#This Row],[цена наличные]]*Таблица625410[[#This Row],[Заказ наличные]],"") -> 0 | J14: =IF(AND(Таблица625410[[#This Row],[Цена б/н]]<>"-",Таблица625410[[#This Row],[Цена б/н]]<>""),Таблица625410[[#This Row],[Цена б/н]]*Таблица625410[[#This Row],[заказ б/н]],"") -> 0
A15: Внешние аккумуляторы | B15: Belkin | C15: CAA010bt1MBK | D15: Кабель Belkin BoostCharge PRO Flex USB-A-Lightning Braided Silicone Cable. Длина: 1м. Цвет: черный | E15: 1641.207 | F15: 1886.445 | I15: =IF(AND(Таблица625410[[#This Row],[цена наличные]]<>"-",Таблица625410[[#This Row],[цена наличные]]<>""),Таблица625410[[#This Row],[цена наличные]]*Таблица625410[[#This Row],[Заказ наличные]],"") -> 0 | J15: =IF(AND(Таблица625410[[#This Row],[Цена б/н]]<>"-",Таблица625410[[#This Row],[Цена б/н]]<>""),Таблица625410[[#This Row],[Цена б/н]]*Таблица625410[[#This Row],[заказ б/н]],"") -> 0
A16: Внешние аккумуляторы | B16: Belkin | C16: CAA010bt1MWH | D16: Кабель Belkin BoostCharge PRO Flex USB-A-Lightning Braided Silicone Cable. Длина: 1м. Цвет: белый | E16: 1641.207 | F16: 1886.445 | I16: =IF(AND(Таблица625410[[#This Row],[цена наличные]]<>"-",Таблица625410[[#This Row],[цена наличные]]<>""),Таблица625410[[#This Row],[цена наличные]]*Таблица625410[[#This Row],[Заказ наличные]],"") -> 0 | J16: =IF(AND(Таблица625410[[#This Row],[Цена б/н]]<>"-",Таблица625410[[#This Row],[Цена б/н]]<>""),Таблица625410[[#This Row],[Цена б/н]]*Таблица625410[[#This Row],[заказ б/н]],"") -> 0
A17: Внешние аккумуляторы | B17: Belkin | C17: BPB027hqBK | D17: Внешний аккумулятор Belkin BoostСharge Power Bank 10000mAh 2*USB-C 20W с цифровым дисплеем. Цвет: черный | E17: 2260.607 | F17: 2598.399 | I17: =IF(AND(Таблица625410[[#This Row],[цена наличные]]<>"-",Таблица625410[[#This Row],[цена наличные]]<>""),Таблица625410[[#This Row],[цена наличные]]*Таблица625410[[#This Row],[Заказ наличные]],"") -> 0 | J17: =IF(AND(Таблица625410[[#This Row],[Цена б/н]]<>"-",Таблица625410[[#This Row],[Цена б/н]]<>""),Таблица625410[[#This Row],[Цена б/н]]*Таблица625410[[#This Row],[заказ б/н]],"") -> 0
A18: Внешние аккумуляторы | B18: Belkin | C18: BPB027hqBL | D18: Внешний аккумулятор Belkin BoostСharge Power Bank 10000mAh 2*USB-C 20W с цифровым дисплеем. Цвет: синий | E18: 2260.607 | F18: 2598.399 | I18: =IF(AND(Таблица625410[[#This Row],[цена наличные]]<>"-",Таблица625410[[#This Row],[цена наличные]]<>""),Таблица625410[[#This Row],[цена наличные]]*Таблица625410[[#This Row],[Заказ наличные]],"") -> 0 | J18: =IF(AND(Таблица625410[[#This Row],[Цена б/н]]<>"-",Таблица625410[[#This Row],[Цена б/н]]<>""),Таблица625410[[#This Row],[Цена б/н]]*Таблица625410[[#This Row],[заказ б/н]],"") -> 0
A19: Внешние аккумуляторы | B19: Belkin | C19: BPB027hqSD | D19: Внешний аккумулятор Belkin BoostСharge Power Bank 10000mAh 2*USB-C 20W с цифровым дисплеем. Цвет: песочно-бежевый | E19: 2260.607 | F19: 2598.399 | I19: =IF(AND(Таблица625410[[#This Row],[цена наличные]]<>"-",Таблица625410[[#This Row],[цена наличные]]<>""),Таблица625410[[#This Row],[цена наличные]]*Таблица625410[[#This Row],[Заказ наличные]],"") -> 0 | J19: =IF(AND(Таблица625410[[#This Row],[Цена б/н]]<>"-",Таблица625410[[#This Row],[Цена б/н]]<>""),Таблица625410[[#This Row],[Цена б/н]]*Таблица625410[[#This Row],[заказ б/н]],"") -> 0
A20: Внешние аккумуляторы | B20: Belkin | C20: BPB021hqBK | D20: Внешний аккумулятор Belkin BoostСharge Power Bank 10000mAh USB-C 20W со встроенным кабелем USB-C. Цвет: черный | E20: 1324.844 | F20: 1522.809 | I20: =IF(AND(Таблица625410[[#This Row],[цена наличные]]<>"-",Таблица625410[[#This Row],[цена наличные]]<>""),Таблица625410[[#This Row],[цена наличные]]*Таблица625410[[#This Row],[Заказ наличные]],"") -> 0 | J20: =IF(AND(Таблица625410[[#This Row],[Цена б/н]]<>"-",Таблица625410[[#This Row],[Цена б/н]]<>""),Таблица625410[[#This Row],[Цена б/н]]*Таблица625410[[#This Row],[заказ б/н]],"") -> 0
A21: Внешние аккумуляторы | B21: Belkin | C21: BPB021hqPK | D21: Внешний аккумулятор Belkin BoostСharge Power Bank 10000mAh USB-C 20W со встроенным кабелем USB-C. Цвет: розовый | E21: 1324.844 | F21: 1522.809 | I21: =IF(AND(Таблица625410[[#This Row],[цена наличные]]<>"-",Таблица625410[[#This Row],[цена наличные]]<>""),Таблица625410[[#This Row],[цена наличные]]*Таблица625410[[#This Row],[Заказ наличные]],"") -> 0 | J21: =IF(AND(Таблица625410[[#This Row],[Цена б/н]]<>"-",Таблица625410[[#This Row],[Цена б/н]]<>""),Таблица625410[[#This Row],[Цена б/н]]*Таблица625410[[#This Row],[заказ б/н]],"") -> 0
A22: Внешние аккумуляторы | B22: Belkin | C22: BPB024hqBK | D22: Внешний аккумулятор Belkin BoostСharge Power Bank 20000mAh USB-A&USB-C 30W со встроенным кабелем USB-C. Цвет: черный | E22: 2112.855 | F22: 2428.569 | I22: =IF(AND(Таблица625410[[#This Row],[цена наличные]]<>"-",Таблица625410[[#This Row],[цена наличные]]<>""),Таблица625410[[#This Row],[цена наличные]]*Таблица625410[[#This Row],[Заказ наличные]],"") -> 0 | J22: =IF(AND(Таблица625410[[#This Row],[Цена б/н]]<>"-",Таблица625410[[#This Row],[Цена б/н]]<>""),Таблица625410[[#This Row],[Цена б/н]]*Таблица625410[[#This Row],[заказ б/н]],"") -> 0
A23: Внешние аккумуляторы | B23: Belkin | C23: BPB024hqBL | D23: Внешний аккумулятор Belkin BoostСharge Power Bank 20000mAh USB-A&USB-C 30W со встроенным кабелем USB-C. Цвет: синий | E23: 2112.855 | F23: 2428.569 | I23: =IF(AND(Таблица625410[[#This Row],[цена наличные]]<>"-",Таблица625410[[#This Row],[цена наличные]]<>""),Таблица625410[[#This Row],[цена наличные]]*Таблица625410[[#This Row],[Заказ наличные]],"") -> 0 | J23: =IF(AND(Таблица625410[[#This Row],[Цена б/н]]<>"-",Таблица625410[[#This Row],[Цена б/н]]<>""),Таблица625410[[#This Row],[Цена б/н]]*Таблица625410[[#This Row],[заказ б/н]],"") -> 0
A24: Внешние аккумуляторы | B24: Belkin | C24: BPB024hqPK | D24: Внешний аккумулятор Belkin BoostСharge Power Bank 20000mAh USB-A&USB-C 30W со встроенным кабелем USB-C. Цвет: розовый | E24: 2112.855 | F24: 2428.569 | I24: =IF(AND(Таблица625410[[#This Row],[цена наличные]]<>"-",Таблица625410[[#This Row],[цена наличные]]<>""),Таблица625410[[#This Row],[цена наличные]]*Таблица625410[[#This Row],[Заказ наличные]],"") -> 0 | J24: =IF(AND(Таблица625410[[#This Row],[Цена б/н]]<>"-",Таблица625410[[#This Row],[Цена б/н]]<>""),Таблица625410[[#This Row],[Цена б/н]]*Таблица625410[[#This Row],[заказ б/н]],"") -> 0
A25: Внешние аккумуляторы | B25: Belkin | C25: BPD008btBK | D25: Внешний аккумулятор Belkin BoostСharge Pro Magnetic Power Bank 10000mAh USB-C Qi2 15W с подставкой. Цвет: черный | E25: 3836.63 | F25: 4409.919 | I25: =IF(AND(Таблица625410[[#This Row],[цена наличные]]<>"-",Таблица625410[[#This Row],[цена наличные]]<>""),Таблица625410[[#This Row],[цена наличные]]*Таблица625410[[#This Row],[Заказ наличные]],"") -> 0 | J25: =IF(AND(Таблица625410[[#This Row],[Цена б/н]]<>"-",Таблица625410[[#This Row],[Цена б/н]]<>""),Таблица625410[[#This Row],[Цена б/н]]*Таблица625410[[#This Row],[заказ б/н]],"") -> 0
... A87: Внешние аккумуляторы | B87: Xiaomi | C87: BHR9074GL | D87: Внешний магнитный аккумулятор Xiaomi Magnetic Power Bank 6000 mAh GL | E87: 2246.749 | F87: 2582.471 | I87: =IF(AND(Таблица625410[[#This Row],[цена наличные]]<>"-",Таблица625410[[#This Row],[цена наличные]]<>""),Таблица625410[[#This Row],[цена наличные]]*Таблица625410[[#This Row],[Заказ наличные]],"") -> 0 | J87: =IF(AND(Таблица625410[[#This Row],[Цена б/н]]<>"-",Таблица625410[[#This Row],[Цена б/н]]<>""),Таблица625410[[#This Row],[Цена б/н]]*Таблица625410[[#This Row],[заказ б/н]],"") -> 0
A88: Внешние звуковые карты | B88: Внешние звуковые карты | I88: =IF(AND(Таблица625410[[#This Row],[цена наличные]]<>"-",Таблица625410[[#This Row],[цена наличные]]<>""),Таблица625410[[#This Row],[цена наличные]]*Таблица625410[[#This Row],[Заказ наличные]],"") | J88: =IF(AND(Таблица625410[[#This Row],[Цена б/н]]<>"-",Таблица625410[[#This Row],[Цена б/н]]<>""),Таблица625410[[#This Row],[Цена б/н]]*Таблица625410[[#This Row],[заказ б/н]],"")
A89: Внешние звуковые карты | B89: UGREEN | C89: 30143_ | D89: Внешняя звуковая карта UGREEN US205 (30143) USB 2.0 External Sound Adapter. Длина: 15см. Цвет: белый | E89: 534.0347 | F89: 613.833 | I89: =IF(AND(Таблица625410[[#This Row],[цена наличные]]<>"-",Таблица625410[[#This Row],[цена наличные]]<>""),Таблица625410[[#This Row],[цена наличные]]*Таблица625410[[#This Row],[Заказ наличные]],"") -> 0 | J89: =IF(AND(Таблица625410[[#This Row],[Цена б/н]]<>"-",Таблица625410[[#This Row],[Цена б/н]]<>""),Таблица625410[[#This Row],[Цена б/н]]*Таблица625410[[#This Row],[заказ б/н]],"") -> 0
A90: Зарядные устройства | B90: Зарядные устройства | I90: =IF(AND(Таблица625410[[#This Row],[цена наличные]]<>"-",Таблица625410[[#This Row],[цена наличные]]<>""),Таблица625410[[#This Row],[цена наличные]]*Таблица625410[[#This Row],[Заказ наличные]],"") | J90: =IF(AND(Таблица625410[[#This Row],[Цена б/н]]<>"-",Таблица625410[[#This Row],[Цена б/н]]<>""),Таблица625410[[#This Row],[Цена б/н]]*Таблица625410[[#This Row],[заказ б/н]],"")
A91: Автомобильные зарядные устройства и держатели | B91: Автомобильные зарядные устройства и держатели | I91: =IF(AND(Таблица625410[[#This Row],[цена наличные]]<>"-",Таблица625410[[#This Row],[цена наличные]]<>""),Таблица625410[[#This Row],[цена наличные]]*Таблица625410[[#This Row],[Заказ наличные]],"") | J91: =IF(AND(Таблица625410[[#This Row],[Цена б/н]]<>"-",Таблица625410[[#This Row],[Цена б/н]]<>""),Таблица625410[[#This Row],[Цена б/н]]*Таблица625410[[#This Row],[заказ б/н]],"")
A92: Автомобильные зарядные устройства и держатели | B92: Belkin | C92: WIC012hqBK | D92: Автомобильный магнитный держатель с функцией быстрой беспроводной зарядки Belkin BoostCharge Magnetic Wireless Charging 15W Car Vent And Dash Mount. Цвет: черный | E92: 3077.01 | F92: 3536.793 | I92: =IF(AND(Таблица625410[[#This Row],[цена наличные]]<>"-",Таблица625410[[#This Row],[цена наличные]]<>""),Таблица625410[[#This Row],[цена наличные]]*Таблица625410[[#This Row],[Заказ наличные]],"") -> 0 | J92: =IF(AND(Таблица625410[[#This Row],[Цена б/н]]<>"-",Таблица625410[[#This Row],[Цена б/н]]<>""),Таблица625410[[#This Row],[Цена б/н]]*Таблица625410[[#This Row],[заказ б/н]],"") -> 0
A93: Автомобильные зарядные устройства и держатели | B93: Satechi | C93: ST-TCPDCCM | D93: Автомобильное зарядное устройство Satechi 72W Type-C PD Car Charger. Цвет серый космос. | E93: 1674.717 | F93: 1924.962 | I93: =IF(AND(Таблица625410[[#This Row],[цена наличные]]<>"-",Таблица625410[[#This Row],[цена наличные]]<>""),Таблица625410[[#This Row],[цена наличные]]*Таблица625410[[#This Row],[Заказ наличные]],"") -> 0 | J93: =IF(AND(Таблица625410[[#This Row],[Цена б/н]]<>"-",Таблица625410[[#This Row],[Цена б/н]]<>""),Таблица625410[[#This Row],[Цена б/н]]*Таблица625410[[#This Row],[заказ б/н]],"") -> 0
A94: Автомобильные зарядные устройства и держатели | B94: Satechi | C94: ST-Q2CCM | D94: Автомобильное беспроводное зарядное устройство Satechi Qi2 Wireless Car Charger 15W. Цвет: серый космос | E94: 3470.726 | F94: 3989.34 | I94: =IF(AND(Таблица625410[[#This Row],[цена наличные]]<>"-",Таблица625410[[#This Row],[цена наличные]]<>""),Таблица625410[[#This Row],[цена наличные]]*Таблица625410[[#This Row],[Заказ наличные]],"") -> 0 | J94: =IF(AND(Таблица625410[[#This Row],[Цена б/н]]<>"-",Таблица625410[[#This Row],[Цена б/н]]<>""),Таблица625410[[#This Row],[Цена б/н]]*Таблица625410[[#This Row],[заказ б/н]],"") -> 0
A95: Автомобильные зарядные устройства и держатели | B95: TTEC | C95: 2KS33S | D95: Автомобильный держатель для телефона TTEC AirCharger Drive Go MagSafcompt In Car Holder+Charger. Цвет: черный | E95: 1447.584 | F95: 1663.89 | I95: =IF(AND(Таблица625410[[#This Row],[цена наличные]]<>"-",Таблица625410[[#This Row],[цена наличные]]<>""),Таблица625410[[#This Row],[цена наличные]]*Таблица625410[[#This Row],[Заказ наличные]],"") -> 0 | J95: =IF(AND(Таблица625410[[#This Row],[Цена б/н]]<>"-",Таблица625410[[#This Row],[Цена б/н]]<>""),Таблица625410[[#This Row],[Цена б/н]]*Таблица625410[[#This Row],[заказ б/н]],"") -> 0
A96: Автомобильные зарядные устройства и держатели | B96: TTEC | C96: 2KS35S | D96: Автомобильное беспроводное зарядное устройство TTEC AirCharger Drive Pro Qi2/MagSafe 15W Wireless Fast Charger&Phone Holder с функцией охлаждения. Цвет: черный | E96: 2650.364 | F96: 3046.395 | I96: =IF(AND(Таблица625410[[#This Row],[цена наличные]]<>"-",Таблица625410[[#This Row],[цена наличные]]<>""),Таблица625410[[#This Row],[цена наличные]]*Таблица625410[[#This Row],[Заказ наличные]],"") -> 0 | J96: =IF(AND(Таблица625410[[#This Row],[Цена б/н]]<>"-",Таблица625410[[#This Row],[Цена б/н]]<>""),Таблица625410[[#This Row],[Цена б/н]]*Таблица625410[[#This Row],[заказ б/н]],"") -> 0
A97: Автомобильные зарядные устройства и держатели | B97: TTEC | C97: 2DK41S | D97: Кабель TTEC AlumiCable USB-C-Lightning 20W PD Fast Charge&Data Cable. Длина: 150см. Цвет: черный | E97: 468.9779 | F97: 539.055 | I97: =IF(AND(Таблица625410[[#This Row],[цена наличные]]<>"-",Таблица625410[[#This Row],[цена наличные]]<>""),Таблица625410[[#This Row],[цена наличные]]*Таблица625410[[#This Row],[Заказ наличные]],"") -> 0 | J97: =IF(AND(Таблица625410[[#This Row],[Цена б/н]]<>"-",Таблица625410[[#This Row],[Цена б/н]]<>""),Таблица625410[[#This Row],[Цена б/н]]*Таблица625410[[#This Row],[заказ б/н]],"") -> 0
A98: Автомобильные зарядные устройства и держатели | B98: TTEC | C98: 2DK41UG | D98: Кабель TTEC AlumiCable USB-C-Lightning 20W PD Fast Charge&Data Cable. Длина: 150см. Цвет: серый космос | E98: 468.9779 | F98: 539.055 | I98: =IF(AND(Таблица625410[[#This Row],[цена наличные]]<>"-",Таблица625410[[#This Row],[цена наличные]]<>""),Таблица625410[[#This Row],[цена наличные]]*Таблица625410[[#This Row],[Заказ наличные]],"") -> 0 | J98: =IF(AND(Таблица625410[[#This Row],[Цена б/н]]<>"-",Таблица625410[[#This Row],[Цена б/н]]<>""),Таблица625410[[#This Row],[Цена б/н]]*Таблица625410[[#This Row],[заказ б/н]],"") -> 0
A99: Автомобильные зарядные устройства и держатели | B99: TTEC | C99: 2TT39 | D99: Автомобильный магнитный держатель для телефона TTEC EasyDash Pro In-Car Phone Holder. Цвет: черный | E99: 588.7751 | F99: 676.753 | I99: =IF(AND(Таблица625410[[#This Row],[цена наличные]]<>"-",Таблица625410[[#This Row],[цена наличные]]<>""),Таблица625410[[#This Row],[цена наличные]]*Таблица625410[[#This Row],[Заказ наличные]],"") -> 0 | J99: =IF(AND(Таблица625410[[#This Row],[Цена б/н]]<>"-",Таблица625410[[#This Row],[Цена б/н]]<>""),Таблица625410[[#This Row],[Цена б/н]]*Таблица625410[[#This Row],[заказ б/н]],"") -> 0
A100: Автомобильные зарядные устройства и держатели | B100: TTEC | C100: 2TT38 | D100: Автомобильный магнитный держатель для телефона TTEC EasyDash Pro M MagSafe Compatible In-Car Phone Holder. Цвет: черный | E100: 651.8318 | F100: 749.232 | I100: =IF(AND(Таблица625410[[#This Row],[цена наличные]]<>"-",Таблица625410[[#This Row],[цена наличные]]<>""),Таблица625410[[#This Row],[цена наличные]]*Таблица625410[[#This Row],[Заказ наличные]],"") -> 0 | J100: =IF(AND(Таблица625410[[#This Row],[Цена б/н]]<>"-",Таблица625410[[#This Row],[Цена б/н]]<>""),Таблица625410[[#This Row],[Цена б/н]]*Таблица625410[[#This Row],[заказ б/н]],"") -> 0
A101: Автомобильные зарядные устройства и держатели | B101: TTEC | C101: 2TT41 | D101: Автомобильный магнитный держатель для телефона TTEC EasyDash Pro M MagSafe Compatible In-Car Phone Holder. Цвет: черный | E101: 705.8354 | F101: 811.305 | I101: =IF(AND(Таблица625410[[#This Row],[цена наличные]]<>"-",Таблица625410[[#This Row],[цена наличные]]<>""),Таблица625410[[#This Row],[цена наличные]]*Таблица625410[[#This Row],[Заказ наличные]],"") -> 0 | J101: =IF(AND(Таблица625410[[#This Row],[Цена б/н]]<>"-",Таблица625410[[#This Row],[Цена б/н]]<>""),Таблица625410[[#This Row],[Цена б/н]]*Таблица625410[[#This Row],[заказ б/н]],"") -> 0
A102: Автомобильные зарядные устройства и держатели | B102: TTEC | C102: 2TT40 | D102: Автомобильный магнитный держатель для телефона TTEC EasyDash Pro M MagSafe Compatible Phone Holder. Цвет: черный | E102: 1385.973 | F102: 1593.072 | I102: =IF(AND(Таблица625410[[#This Row],[цена наличные]]<>"-",Таблица625410[[#This Row],[цена наличные]]<>""),Таблица625410[[#This Row],[цена наличные]]*Таблица625410[[#This Row],[Заказ наличные]],"") -> 0 | J102: =IF(AND(Таблица625410[[#This Row],[Цена б/н]]<>"-",Таблица625410[[#This Row],[Цена б/н]]<>""),Таблица625410[[#This Row],[Цена б/н]]*Таблица625410[[#This Row],[заказ б/н]],"") -> 0
A103: Автомобильные зарядные устройства и держатели | B103: TTEC | C103: 2TT35 | D103: Автомобильный держатель для телефона TTEC EasyDrive Flex M MagSafe Compatable In-Car Phone Holder. Цвет: черный | E103: 702.3614 | F103: 807.312 | I103: =IF(AND(Таблица625410[[#This Row],[цена наличные]]<>"-",Таблица625410[[#This Row],[цена наличные]]<>""),Таблица625410[[#This Row],[цена наличные]]*Таблица625410[[#This Row],[Заказ наличные]],"") -> 0 | J103: =IF(AND(Таблица625410[[#This Row],[Цена б/н]]<>"-",Таблица625410[[#This Row],[Цена б/н]]<>""),Таблица625410[[#This Row],[Цена б/н]]*Таблица625410[[#This Row],[заказ б/н]],"") -> 0
... A145: Автомобильные зарядные устройства и держатели | B145: TTEC | C145: 2DK65G | D145: Кабель выдвижной TTEC USB-C to USB-C Mini Retractable 100W PD/QC 120cm Fast Charge Cable. Длина: 120 см. Цвет: лунный белый | E145: 678.9915 | F145: 780.45 | I145: =IF(AND(Таблица625410[[#This Row],[цена наличные]]<>"-",Таблица625410[[#This Row],[цена наличные]]<>""),Таблица625410[[#This Row],[цена наличные]]*Таблица625410[[#This Row],[Заказ наличные]],"") -> 0 | J145: =IF(AND(Таблица625410[[#This Row],[Цена б/н]]<>"-",Таблица625410[[#This Row],[Цена б/н]]<>""),Таблица625410[[#This Row],[Цена б/н]]*Таблица625410[[#This Row],[заказ б/н]],"") -> 0
A146: Автомобильные зарядные устройства и держатели | B146: UGREEN | C146: 60980 | D146: Автомобильное зарядное устройство UGREEN CD213 (60980) USB-C PD+USB-A QC 52.5W Fast Car Charger. Цвет: серый | E146: 1049.647 | F146: 1206.491 | I146: =IF(AND(Таблица625410[[#This Row],[цена наличные]]<>"-",Таблица625410[[#This Row],[цена наличные]]<>""),Таблица625410[[#This Row],[цена наличные]]*Таблица625410[[#This Row],[Заказ наличные]],"") -> 0 | J146: =IF(AND(Таблица625410[[#This Row],[Цена б/н]]<>"-",Таблица625410[[#This Row],[Цена б/н]]<>""),Таблица625410[[#This Row],[Цена б/н]]*Таблица625410[[#This Row],[заказ б/н]],"") -> 0
A147: Автомобильные зарядные устройства и держатели | B147: UGREEN | C147: 25845_ | D147: Автомобильное зарядное устройство UGREEN EC305 (25845) USB-C PD+USB-A QC 30W Fast Car Charger с чехлом. Цвет: черный | E147: 465.7145 | F147: 535.304 | I147: =IF(AND(Таблица625410[[#This Row],[цена наличные]]<>"-",Таблица625410[[#This Row],[цена наличные]]<>""),Таблица625410[[#This Row],[цена наличные]]*Таблица625410[[#This Row],[Заказ наличные]],"") -> 0 | J147: =IF(AND(Таблица625410[[#This Row],[Цена б/н]]<>"-",Таблица625410[[#This Row],[Цена б/н]]<>""),Таблица625410[[#This Row],[Цена б/н]]*Таблица625410[[#This Row],[заказ б/н]],"") -> 0
A148: Автомобильные зарядные устройства и держатели | B148: UGREEN | C148: 45843_ | D148: Автомобильное зарядное устройство UGREEN EC307 (45843) 30W 3-Port Fast Car Charger. Цвет: серый | E148: 665.5169 | F148: 764.962 | I148: =IF(AND(Таблица625410[[#This Row],[цена наличные]]<>"-",Таблица625410[[#This Row],[цена наличные]]<>""),Таблица625410[[#This Row],[цена наличные]]*Таблица625410[[#This Row],[Заказ наличные]],"") -> 0 | J148: =IF(AND(Таблица625410[[#This Row],[Цена б/н]]<>"-",Таблица625410[[#This Row],[Цена б/н]]<>""),Таблица625410[[#This Row],[Цена б/н]]*Таблица625410[[#This Row],[заказ б/н]],"") -> 0
A149: Беспроводные зарядные устройства | B149: Беспроводные зарядные устройства | I149: =IF(AND(Таблица625410[[#This Row],[цена наличные]]<>"-",Таблица625410[[#This Row],[цена наличные]]<>""),Таблица625410[[#This Row],[цена наличные]]*Таблица625410[[#This Row],[Заказ наличные]],"") | J149: =IF(AND(Таблица625410[[#This Row],[Цена б/н]]<>"-",Таблица625410[[#This Row],[Цена б/н]]<>""),Таблица625410[[#This Row],[Цена б/н]]*Таблица625410[[#This Row],[заказ б/н]],"")
A150: Беспроводные зарядные устройства | B150: Satechi | C150: ST-WCS5PM-EU | D150: Зарядная станция Satechi Dock5 Multi-Device Charging Station with Wireless Charging. Цвет: серый космос. | E150: 2794.929 | F150: 3212.562 | I150: =IF(AND(Таблица625410[[#This Row],[цена наличные]]<>"-",Таблица625410[[#This Row],[цена наличные]]<>""),Таблица625410[[#This Row],[цена наличные]]*Таблица625410[[#This Row],[Заказ наличные]],"") -> 0 | J150: =IF(AND(Таблица625410[[#This Row],[Цена б/н]]<>"-",Таблица625410[[#This Row],[Цена б/н]]<>""),Таблица625410[[#This Row],[Цена б/н]]*Таблица625410[[#This Row],[заказ б/н]],"") -> 0
A151: Беспроводные зарядные устройства | B151: Satechi | C151: ST-UCQIMCM | D151: Беспроводное зарядное устройство Satechi Magnetic Wireless Charging Cable. Интерфейс Type-C, длина 1.5м. Цвет: серый космос. | E151: 1216.299 | F151: 1398.045 | I151: =IF(AND(Таблица625410[[#This Row],[цена наличные]]<>"-",Таблица625410[[#This Row],[цена наличные]]<>""),Таблица625410[[#This Row],[цена наличные]]*Таблица625410[[#This Row],[Заказ наличные]],"") -> 0 | J151: =IF(AND(Таблица625410[[#This Row],[Цена б/н]]<>"-",Таблица625410[[#This Row],[Цена б/н]]<>""),Таблица625410[[#This Row],[Цена б/н]]*Таблица625410[[#This Row],[заказ б/н]],"") -> 0
A152: Беспроводные зарядные устройства | B152: Satechi | C152: ST-QTPM-EA | D152: Зарядное устройство 3-в-1 Satechi Qi2 Trio Wireless Charging Pad с вилками типа A/C/G. Цвет: черный | E152: 7740.947 | F152: 8897.64 | I152: =IF(AND(Таблица625410[[#This Row],[цена наличные]]<>"-",Таблица625410[[#This Row],[цена наличные]]<>""),Таблица625410[[#This Row],[цена наличные]]*Таблица625410[[#This Row],[Заказ наличные]],"") -> 0 | J152: =IF(AND(Таблица625410[[#This Row],[Цена б/н]]<>"-",Таблица625410[[#This Row],[Цена б/н]]<>""),Таблица625410[[#This Row],[Цена б/н]]*Таблица625410[[#This Row],[заказ б/н]],"") -> 0
A153: Беспроводные зарядные устройства | B153: TTEC | C153: 2KS29B | D153: Беспроводное зарядное устройство TTEC AirCharger M+ MagSafe Wireless Charger. Цвет: белый | E153: 1481.867 | F153: 1703.295 | I153: =IF(AND(Таблица625410[[#This Row],[цена наличные]]<>"-",Таблица625410[[#This Row],[цена наличные]]<>""),Таблица625410[[#This Row],[цена наличные]]*Таблица625410[[#This Row],[Заказ наличные]],"") -> 0 | J153: =IF(AND(Таблица625410[[#This Row],[Цена б/н]]<>"-",Таблица625410[[#This Row],[Цена б/н]]<>""),Таблица625410[[#This Row],[Цена б/н]]*Таблица625410[[#This Row],[заказ б/н]],"") -> 0
A154: Беспроводные зарядные устройства | B154: TTEC | C154: 2KS30B | D154: Беспроводная зарядка TTEC AirCharger M+ MagSafe Wireless Charger&PD Charger. Цвет: белый | E154: 1906.775 | F154: 2191.695 | I154: =IF(AND(Таблица625410[[#This Row],[цена наличные]]<>"-",Таблица625410[[#This Row],[цена наличные]]<>""),Таблица625410[[#This Row],[цена наличные]]*Таблица625410[[#This Row],[Заказ наличные]],"") -> 0 | J154: =IF(AND(Таблица625410[[#This Row],[Цена б/н]]<>"-",Таблица625410[[#This Row],[Цена б/н]]<>""),Таблица625410[[#This Row],[Цена б/н]]*Таблица625410[[#This Row],[заказ б/н]],"") -> 0
A155: Беспроводные зарядные устройства | B155: TTEC | C155: 2KS31B | D155: Беспроводная зарядка складная TTEC AirCharger Up M MagSafe Wireless Charger. Цвет: белый | E155: 1747.434 | F155: 2008.545 | I155: =IF(AND(Таблица625410[[#This Row],[цена наличные]]<>"-",Таблица625410[[#This Row],[цена наличные]]<>""),Таблица625410[[#This Row],[цена наличные]]*Таблица625410[[#This Row],[Заказ наличные]],"") -> 0 | J155: =IF(AND(Таблица625410[[#This Row],[Цена б/н]]<>"-",Таблица625410[[#This Row],[Цена б/н]]<>""),Таблица625410[[#This Row],[Цена б/н]]*Таблица625410[[#This Row],[заказ б/н]],"") -> 0
A156: Беспроводные зарядные устройства | B156: UGREEN | C156: 55677_ | D156: Беспроводное зарядное устройство UGREEN W711 (55677) "MagFlow" Desktop 3-in-1 Magnetic Wireless Charger 25W QI2.2. Цвет: серебристо-голубой | E156: 7547.008 | F156: 8674.722 | I156: =IF(AND(Таблица625410[[#This Row],[цена наличные]]<>"-",Таблица625410[[#This Row],[цена наличные]]<>""),Таблица625410[[#This Row],[цена наличные]]*Таблица625410[[#This Row],[Заказ наличные]],"") -> 0 | J156: =IF(AND(Таблица625410[[#This Row],[Цена б/н]]<>"-",Таблица625410[[#This Row],[Цена б/н]]<>""),Таблица625410[[#This Row],[Цена б/н]]*Таблица625410[[#This Row],[заказ б/н]],"") -> 0
A157: Зарядные устройства | B157: Зарядные устройства | I157: =IF(AND(Таблица625410[[#This Row],[цена наличные]]<>"-",Таблица625410[[#This Row],[цена наличные]]<>""),Таблица625410[[#This Row],[цена наличные]]*Таблица625410[[#This Row],[Заказ наличные]],"") | J157: =IF(AND(Таблица625410[[#This Row],[Цена б/н]]<>"-",Таблица625410[[#This Row],[Цена б/н]]<>""),Таблица625410[[#This Row],[Цена б/н]]*Таблица625410[[#This Row],[заказ б/н]],"")
A158: Зарядные устройства | B158: Belkin | C158: INC006vfSGY | D158: Зарядная станция Belkin Connect PRO 12-in-1 Thunderbolt 4 Docking Station. Цвет: серый космос | E158: 25571.61 | F158: 29392.65 | I158: =IF(AND(Таблица625410[[#This Row],[цена наличные]]<>"-",Таблица625410[[#This Row],[цена наличные]]<>""),Таблица625410[[#This Row],[цена наличные]]*Таблица625410[[#This Row],[Заказ наличные]],"") -> 0 | J158: =IF(AND(Таблица625410[[#This Row],[Цена б/н]]<>"-",Таблица625410[[#This Row],[Цена б/н]]<>""),Таблица625410[[#This Row],[Цена б/н]]*Таблица625410[[#This Row],[заказ б/н]],"") -> 0
A159: Зарядные устройства | B159: Belkin | C159: INC020kqSGY | D159: Док-станция Belkin Connect USB-C 11-in-1 Pro GaN Dock 150W. Цвет: черный | E159: 14245.12 | F159: 16373.7 | I159: =IF(AND(Таблица625410[[#This Row],[цена наличные]]<>"-",Таблица625410[[#This Row],[цена наличные]]<>""),Таблица625410[[#This Row],[цена наличные]]*Таблица625410[[#This Row],[Заказ наличные]],"") -> 0 | J159: =IF(AND(Таблица625410[[#This Row],[Цена б/н]]<>"-",Таблица625410[[#This Row],[Цена б/н]]<>""),Таблица625410[[#This Row],[Цена б/н]]*Таблица625410[[#This Row],[заказ б/н]],"") -> 0
A160: Зарядные устройства | B160: Belkin | C160: INC018vfBK | D160: Док-станция Belkin Connect USB-C 6-in-1 130W HDMI&2-USB-C 3.0&USB-A 3.1 GaN Dock. Цвет: черный | E160: 9400.907 | F160: 10805.64 | I160: =IF(AND(Таблица625410[[#This Row],[цена наличные]]<>"-",Таблица625410[[#This Row],[цена наличные]]<>""),Таблица625410[[#This Row],[цена наличные]]*Таблица625410[[#This Row],[Заказ наличные]],"") -> 0 | J160: =IF(AND(Таблица625410[[#This Row],[Цена б/н]]<>"-",Таблица625410[[#This Row],[Цена б/н]]<>""),Таблица625410[[#This Row],[Цена б/н]]*Таблица625410[[#This Row],[заказ б/н]],"") -> 0
